Workbook

Sheet ACCUEIL
B2: ANNEXE 7 - PRÉVISIONNEL FINANCIER
B3: Cabinet d'Expertise Comptable 100% Numérique
B5: Guide de création d'un prévisionnel financier sur 3 ans
B8: OBJECTIF DE L'OUTIL
B9: Cet outil permet de créer rapidement un prévisionnel financier complet pour la création d'un cabinet d'expertise comptable.
B10: Il génère automatiquement : Bilan, Plan de Financement, Compte de Résultat, Plan de Trésorerie et Synthèse.
B13: MODE D'EMPLOI
B15: 1. Allez dans l'onglet SAISIE
B16: 2. Remplissez UNIQUEMENT les cellules jaunes avec vos données annuelles
B17: 3. Les montants sont automatiquement répartis mensuellement (÷12)
B18: 4. Consultez les onglets de synthèse pour voir vos résultats
B21: STRUCTURE DES ONGLETS
B23: • SAISIE | C23: Saisie simplifiée des données annuelles (POINT D'ENTRÉE)
B24: • Synthèse | C24: Indicateurs clés agrégés
B25: • Bilan | C25: Bilan prévisionnel sur 3 ans
B26: • Plan de Financement | C26: Sources et emplois des fonds
B27: • Compte de Résultat | C27: Performances prévisionnelles
B28: • Plan de trésorerie | C28: Flux de trésorerie mensuels
B29: • Prévisions mensuelles | C29: Détail mensuel généré automatiquement
B30: • Personnel | C30: Détail de la masse salariale
B34: POINTS D'ATTENTION
B36: ⚠ Les valeurs par défaut sont des exemples - adaptez-les à votre projet
B37: ⚠ La répartition mensuelle est linéaire (÷12) - ajustez si nécessaire dans les prévisions mensuelles
B38: ⚠ Le taux de charges sociales par défaut est de 42% - vérifiez selon votre statut
B39: ⚠ Le taux d'IS par défaut est de 25% - appliquez le taux réduit PME si éligible (15%)
B40: ⚠ Les durées d'amortissement doivent respecter les usages comptables
B43: CONFORMITÉ PROFESSIONNELLE
B45: Cet outil respecte les principes comptables français (PCG) et les normes professionnelles.
B46: Il est destiné à servir de base de travail pour l'expert-comptable souhaitant créer son cabinet.
B47: Les projections doivent être validées par un professionnel avant utilisation auprès des banques ou investisseurs.
B50: Outil développé dans le cadre du mémoire d'expertise comptable
B53: ⚠ HYPOTHÈSE DE RÉPARTITION
B54: Le CA et les charges sont répartis linéairement (÷12) par simplification. L'activité réelle d'un cabinet d'EC est saisonnière (bilans jan-avr, creux estival). Le plan de trésorerie mensuel est donc indicatif. Pour une analyse fine, appliquer des coefficients mensuels de saisonnalité.

Sheet SAISIE
B1: ANNEXE 7 - PRÉVISIONNEL CRÉATION CABINET D'EXPERTISE COMPTABLE
B2: Guide de saisie: Remplissez uniquement les cellules jaunes avec vos données annuelles
B3: Les montants mensuels seront calculés automatiquement (répartition linéaire sur 12 mois)
B5: PARAMÈTRES | C5: Année N | D5: Année N+1 | E5: Année N+2 | F5: Commentaires / Instructions
B7: 1) BUDGET DES VENTES (Chiffre d'affaires HT)
B8: a) Mission Expertise-Comptable | C8: =+D8/2 -> 80000 | D8: 160000 | E8: 240000 | F8: Mission principale - Tenue comptabilité, révision, bilan
B9: b) Mission CAC (Commissariat aux comptes) | C9: 0 | D9: 36000 | E9: 72000 | F9: Audit légal et missions de certification
B10: c) Mission Social (Paie) | C10: 5000 | D10: 10000 | E10: 15000 | F10: Établissement des bulletins de paie et DSN
B11: d) Mission Juridique | C11: =+D11/2 -> 3000 | D11: 6000 | E11: 18000 | F11: Secrétariat juridique, AG, cessions...
B12: e) DAF externalisé / Conseil | C12: 25000 | D12: 36000 | E12: 72000 | F12: Direction financière externalisée, conseil stratégique
B13: TOTAL CHIFFRE D'AFFAIRES | C13: =SUM(C8:C12) -> 113000 | D13: =SUM(D8:D12) -> 248000 | E13: =SUM(E8:E12) -> 417000
B15: 2) CHARGES DIRECTES (Coûts production)
B16: Logiciels métier (Prod. comptable) | C16: 6000 | D16: 6000 | E16: 6000 | F16: Cegid, ACD, Sage, Pennylane, FULLL …
B17: Marketing / Publicité | C17: 1200 | D17: 1200 | E17: 1200 | F17: Campagnes, sponsoring, événements
B18: TOTAL CHARGES DIRECTES | C18: =SUM(C16:C17) -> 7200 | D18: =SUM(D16:D17) -> 7200 | E18: =SUM(E16:E17) -> 7200
B20: 3) CHARGES EXTERNES
B21: Cotisations Ordre des Experts-Comptables | C21: 500 | D21: 500 | E21: 500 | F21: Cotisation annuelle obligatoire
B22: Assurances (RCP + autres) | C22: 2000 | D22: 3000 | E22: 5000 | F22: Responsabilité civile professionnelle obligatoire
B23: Loyers crédit-bail (véhicules...) | C23: 0 | D23: 0 | E23: 0 | F23: Leasing voiture, matériel
B24: Location bureaux / Coworking | C24: 1200 | D24: 1200 | E24: 1200 | F24: Loyer mensuel bureau ou espace coworking
B25: Frais de production | C25: 600 | D25: 600 | E25: 600 | F25: Fournitures bureau, consommables
B26: Honoraires (avocat, expert...) | C26: 2400 | D26: 2400 | E26: 2400 | F26: Conseils externes ponctuels
B27: Publicité | C27: 600 | D27: 600 | E27: 600 | F27: Annonces, Google Ads, réseaux sociaux
B28: Frais de déplacement | C28: 1200 | D28: 1200 | E28: 1200 | F28: Carburant, transports, parking
B29: Frais de missions/réceptions | C29: 1800 | D29: 1800 | E29: 1800 | F29: Repas clients, séminaires
B30: Divers | C30: 1200 | D30: 1200 | E30: 1200 | F30: Autres charges non listées
B31: TOTAL CHARGES EXTERNES | C31: =SUM(C21:C30) -> 11500 | D31: =SUM(D21:D30) -> 12500 | E31: =SUM(E21:E30) -> 14500
B33: 4) PERSONNEL & RÉMUNÉRATION
B34: Rémunération de l'EC (annuelle) | C34: 25000 | D34: 45000 | E34: 80000 | F34: Salaire annuel brut du dirigeant TNS ou assimilé salarié
B35: Masse salariale collaborateurs (brut) | C35: 30000 | D35: 74400 | E35: 128400 | F35: Total brut annuel de tous les salariés
B36: Charges sociales estimées (%) | C36: 0.42 | D36: 0.42 | E36: 0.42 | F36: En % des salaires bruts (environ 42% si salarié, 45% si TNS)
B37: Charges sociales calculées | C37: =C35*C36 -> 12600 | D37: =D35*D36 -> 31248 | E37: =E35*E36 -> 53928
B38: TOTAL CHARGES DE PERSONNEL | C38: =C34+C35+C37+C62 -> 78850 | D38: =D34+D35+D37+D62 -> 170898 | E38: =E34+E35+E37+E62 -> 298328
B40: 5) INVESTISSEMENTS (Immobilisations)
B41: R&D / Logiciels immobilisés | C41: 0 | D41: 0 | E41: 0 | F41: Développement interne, logiciels > 500€
B42: Matériel de transport | C42: 0 | D42: 0 | E42: 0 | F42: Véhicules achetés (non en crédit-bail)
B43: Mobilier et matériel de bureau | C43: 1500 | D43: 500 | E43: 500 | F43: Bureau, chaises, armoires, écrans...
B44: Matériel informatique | C44: 4000 | D44: 1500 | E44: 2000 | F44: Serveurs, ordinateurs, imprimantes > 500€
B45: Durée d'amortissement moyenne (années) | C45: 3 | D45: 3 | E45: 3 | F45: 3 ans = logiciels, 5 ans = mobilier, 5-7 ans = véhicules
B46: TOTAL INVESTISSEMENTS | C46: =SUM(C41:C44) -> 5500 | D46: =SUM(D41:D44) -> 2000 | E46: =SUM(E41:E44) -> 2500
B48: 6) FINANCEMENT
B49: Capital social apporté | C49: 10000 | D49: 0 | E49: 0 | F49: Apport initial en capital
B50: Emprunt bancaire contracté | C50: 20000 | D50: 0 | E50: 0 | F50: Montant total des emprunts
B51: Taux d'intérêt annuel emprunt (%) | C51: 0.04 | D51: 0.04 | E51: 0.04 | F51: Taux nominal annuel
B52: Durée de l'emprunt (années) | C52: 5 | D52: 5 | E52: 5 | F52: Nombre d'années de remboursement
B53: Remboursement annuel emprunt | C53: =IF(C52>0,C50/C52,0) -> 4000 | D53: =IF(D52>0,D50/D52,0) -> 0 | E53: =IF(E52>0,E50/E52,0) -> 0
B54: Intérêts annuels estimés | C54: =C50*C51 -> 800 | D54: =(C50-C53)*D51 -> 640 | E54: =(C50-2*C53)*E51 -> 480
B56: 7) PARAMÈTRES COMPLÉMENTAIRES
B57: Impôts et taxes (CFE, CVAE...) | C57: 600 | D57: 600 | E57: 600 | F57: Cotisation foncière, CVAE si applicable
B58: Taux d'IS (%) | C58: 0.25 | D58: 0.25 | E58: 0.25 | F58: Taux nominal 25%. Le calcul applique automatiquement le taux réduit PME de 15% sur les premiers 42 500 € de bénéfice (art. 219-I-b CGI).
B59: Autres impôts et taxes | C59: 0 | D59: 0 | E59: 0
B61: Taux charges sociales dirigeant TNS (%) | C61: 0.45 | D61: 0.45 | E61: 0.45
B62: Charges sociales dirigeant TNS | C62: =C34*C61 -> 11250 | D62: =D34*D61 -> 20250 | E62: =E34*E61 -> 36000

Sheet Tableau de bord KPI
B1: TABLEAU DE BORD — INDICATEURS DE PILOTAGE
B2: Cabinet d'expertise comptable 100% numérique — Prévisionnel sur 3 ans
B4: INDICATEUR | C4: Année N (2026) | D4: Année N+1 (2027) | E4: Année N+2 (2028)
B5: 1. PERFORMANCE ÉCONOMIQUE
B6: Chiffre d'affaires | C6: =SAISIE!C13 -> 113000 | D6: =SAISIE!D13 -> 248000 | E6: =SAISIE!E13 -> 417000
B7: Marge brute | C7: =Synthèse!C8 -> 62000 | D7: =Synthèse!D8 -> 133952 | E7: =Synthèse!E8 -> 226272
B8: Taux de marge brute (%) | C8: =Synthèse!C9 -> 0.54867257 | D8: =Synthèse!D9 -> 0.54012903 | E8: =Synthèse!E9 -> 0.54261871
B9: EBITDA | C9: =Synthèse!C10 -> 14850 | D9: =Synthèse!D10 -> 56802 | E9: =Synthèse!E10 -> 96372
B10: Taux EBITDA (%) | C10: =Synthèse!C11 -> 0.13141593 | D10: =Synthèse!D11 -> 0.22904032 | E10: =Synthèse!E11 -> 0.23110791
B11: Résultat net | C11: ='Compte de Résultat'!D31 -> 10434.592 | D11: ='Compte de Résultat'!E31 -> 45895.585 | E11: ='Compte de Résultat'!F31 -> 75551.735
B12: Taux de marge nette (%) | C12: ='Compte de Résultat'!D32 -> 0.092341518 | D12: ='Compte de Résultat'!E32 -> 0.18506284 | E12: ='Compte de Résultat'!F32 -> 0.18117922
B14: 2. SEUIL DE RENTABILITÉ (POINT MORT)
B15: Charges fixes annuelles | C15: =SAISIE!C34+SAISIE!C62+SAISIE!C21+SAISIE!C22+SAISIE!C23+SAISIE!C24+SAISIE!C26+SAISIE!C57 -> 42950 | D15: =SAISIE!D34+SAISIE!D62+SAISIE!D21+SAISIE!D22+SAISIE!D23+SAISIE!D24+SAISIE!D26+SAISIE!D57 -> 72950 | E15: =SAISIE!E34+SAISIE!E62+SAISIE!E21+SAISIE!E22+SAISIE!E23+SAISIE!E24+SAISIE!E26+SAISIE!E57 -> 125700
B16: Charges variables (personnel + production) | C16: =SAISIE!C35+SAISIE!C37+SAISIE!C16+SAISIE!C17 -> 49800 | D16: =SAISIE!D35+SAISIE!D37+SAISIE!D16+SAISIE!D17 -> 112848 | E16: =SAISIE!E35+SAISIE!E37+SAISIE!E16+SAISIE!E17 -> 189528
B17: Taux de marge sur coûts variables (%) | C17: =IF(C6=0,0,(C6-C16)/C6) -> 0.55929204 | D17: =IF(D6=0,0,(D6-D16)/D6) -> 0.54496774 | E17: =IF(E6=0,0,(E6-E16)/E6) -> 0.5454964
B18: Point mort (CA seuil de rentabilité) | C18: =IF(C17=0,0,C15/C17) -> 76793.513 | D18: =IF(D17=0,0,D15/D17) -> 133861.13 | E18: =IF(E17=0,0,E15/E17) -> 230432.32
B19: Point mort atteint en mois | C19: =IF(C6=0,0,ROUND(C18/C6*12,1)) -> 8.2 | D19: =IF(D6=0,0,ROUND(D18/D6*12,1)) -> 6.5 | E19: =IF(E6=0,0,ROUND(E18/E6*12,1)) -> 6.6
B21: 3. TRÉSORERIE ET SOLIDITÉ FINANCIÈRE
B22: Trésorerie fin d'année | C22: =Synthèse!C14 -> 31630.157 | D22: =Synthèse!D14 -> 72051.14 | E22: =Synthèse!E14 -> 137165.29
B23: Plus bas de trésorerie dans l'année | C23: =Synthèse!C15 -> 25516.667 | D23: =Synthèse!D15 -> 27467.521 | E23: =Synthèse!E15 -> 69813.478
B24: Mois de charges couvertes par la trésorerie | C24: =IF(C6=0,0,ROUND(Synthèse!C14/((SAISIE!C38+SAISIE!C18+SAISIE!C31+SAISIE!C62)/12),1)) -> 3.5 | D24: =IF(D6=0,0,ROUND(Synthèse!D14/((SAISIE!D38+SAISIE!D18+SAISIE!D31+SAISIE!D62)/12),1)) -> 4.1 | E24: =IF(E6=0,0,ROUND(Synthèse!E14/((SAISIE!E38+SAISIE!E18+SAISIE!E31+SAISIE!E62)/12),1)) -> 4.6
B25: Fonds propres | C25: =Synthèse!C16 -> 20434.592 | D25: =Synthèse!D16 -> 66330.177 | E25: =Synthèse!E16 -> 141881.91
B26: Ratio d'autonomie financière (%) | C26: =IF(Bilan!D39=0,0,Synthèse!C16/Bilan!D39) -> 0.43854044 | D26: =IF(Bilan!E39=0,0,Synthèse!D16/Bilan!E39) -> 0.65124629 | E26: =IF(Bilan!F39=0,0,Synthèse!E16/Bilan!F39) -> 0.76473029
B27: BFR | C27: =Synthèse!C17 -> 1137.7682 | D27: =Synthèse!D17 -> 1279.0369 | E27: =Synthèse!E17 -> 6049.95
B29: 4. ACTIVITÉ ET CROISSANCE
B30: Effectif moyen (ETP) | C30: =Synthèse!C13 -> 1 | D30: =Synthèse!D13 -> 2 | E30: =Synthèse!E13 -> 3
B31: CA moyen par collaborateur | C31: =IF(C30=0,0,C6/(C30+1)) -> 56500 | D31: =IF(D30=0,0,D6/(D30+1)) -> 82666.667 | E31: =IF(E30=0,0,E6/(E30+1)) -> 104250
B32: Taux de croissance CA (%) | C32: ="N/A" -> N/A | D32: =IF(C6=0,0,(D6-C6)/C6) -> 1.1946903 | E32: =IF(D6=0,0,(E6-D6)/D6) -> 0.68145161
B33: CA moyen mensuel | C33: =C6/12 -> 9416.6667 | D33: =D6/12 -> 20666.667 | E33: =E6/12 -> 34750
B35: 5. KPI MÉTIER — CABINET D'EXPERTISE COMPTABLE
B36: Objectif clients signés (cumulé) | C36: =25 -> 25 | D36: =60 -> 60 | E36: =100 -> 100
B37: Panier moyen par client (CA / nb clients) | C37: =IF(C36=0,0,C6/C36) -> 4520 | D37: =IF(D36=0,0,D6/D36) -> 4133.3333 | E37: =IF(E36=0,0,E6/E36) -> 4170
B38: Part EC dans CA total (%) | C38: =IF(C6=0,0,SAISIE!C8/C6) -> 0.7079646 | D38: =IF(D6=0,0,SAISIE!D8/D6) -> 0.64516129 | E38: =IF(E6=0,0,SAISIE!E8/E6) -> 0.57553957
B39: Indice de diversification (nb missions >5% CA) | C39: =COUNTIF(SAISIE!C8:C12,">"&C6*5%) -> 2 | D39: =COUNTIF(SAISIE!D8:D12,">"&D6*5%) -> 3 | E39: =COUNTIF(SAISIE!E8:E12,">"&E6*5%) -> 3
B41: SEUILS D'ALERTE (repères)
B42: ⚠ Trésorerie < 15 000 € → risque de cessation de paiement
B43: ⚠ Mois charges couvertes < 2 → tension critique
B44: ⚠ Marge EBITDA < 10% → modèle non viable à terme
B45: ⚠ Point mort > 10 mois → croissance trop lente
B46: ⚠ Autonomie financière < 30% → dépendance bancaire élevée
B48: Note : Les KPI sont calculés automatiquement à partir des données SAISIE et des états financiers.

Sheet Synthèse
B2: Synthèse agrégats
B3: en k€ | C3: 46387 | D3: 46752 | E3: 47118
C4: 12m | D4: 12m | E4: 12m
B6: Chiffre d'affaires | C6: ='Compte de Résultat'!D7 -> 113000 | D6: ='Compte de Résultat'!E7 -> 248000 | E6: ='Compte de Résultat'!F7 -> 417000
B7: Coût direct | C7: =+SAISIE!C18+SAISIE!C30+SAISIE!C35+SAISIE!C37 -> 51000 | D7: =+SAISIE!D18+SAISIE!D30+SAISIE!D35+SAISIE!D37 -> 114048 | E7: =+SAISIE!E18+SAISIE!E30+SAISIE!E35+SAISIE!E37 -> 190728
B8: Marge brute | C8: =+C6-C7 -> 62000 | D8: =+D6-D7 -> 133952 | E8: =+E6-E7 -> 226272
B9: % marge brute | C9: =+C8/C6 -> 0.54867257 | D9: =+D8/D6 -> 0.54012903 | E9: =+E8/E6 -> 0.54261871
B10: EBITDA | C10: ='Compte de Résultat'!D22-'Compte de Résultat'!D21 -> 14850 | D10: ='Compte de Résultat'!E22-'Compte de Résultat'!E21 -> 56802 | E10: ='Compte de Résultat'!F22-'Compte de Résultat'!F21 -> 96372
B11: % marge EBITDA | C11: =C10/C6 -> 0.13141593 | D11: =D10/D6 -> 0.22904032 | E11: =E10/E6 -> 0.23110791
B12: EBIT | C12: ='Compte de Résultat'!D22 -> 13016.667 | D12: ='Compte de Résultat'!E22 -> 56135.333 | E12: ='Compte de Résultat'!F22 -> 95538.667
B13: Effectif moyen | C13: =+Personnel!Q19 -> 1 | D13: =+Personnel!AF19 -> 2 | E13: =+Personnel!AU19 -> 3
B14: Trésorerie fin d'année | C14: ='Prévisions mensuelles'!O129 -> 31630.157 | D14: ='Prévisions mensuelles'!AB129 -> 72051.14 | E14: ='Prévisions mensuelles'!AO129 -> 137165.29
B15: Plus bas de trésorerie | C15: =MIN('Prévisions mensuelles'!D129:O129) -> 25516.667 | D15: =MIN('Prévisions mensuelles'!Q129:AB129) -> 27467.521 | E15: =MIN('Prévisions mensuelles'!AD129:AO129) -> 69813.478
B16: Fonds propres | C16: =Bilan!D24 -> 20434.592 | D16: =Bilan!E24 -> 66330.177 | E16: =Bilan!F24 -> 141881.91
B17: BFR | C17: =+Bilan!D43 -> 1137.7682 | D17: =+Bilan!E43 -> 1279.0369 | E17: =+Bilan!F43 -> 6049.95
B18: Variation du BFR (N/N-1) | C18: =+'Plan de Financement'!D8 -> 1137.7682 | D18: =+'Plan de Financement'!E8 -> 141.26871 | E18: =+'Plan de Financement'!F8 -> 4770.9132

Sheet Bilan
B2: Bilan
B3: en € | C3: 46022 | D3: =EOMONTH(C3,12) -> 46387 | E3: =EOMONTH(D3,12) -> 46752 | F3: =EOMONTH(E3,12) -> 47118
C4: 12m | D4: 12m | E4: 12m | F4: 12m
B6: Immobilisations incorporelles | D6: =C6+'Prévisions mensuelles'!C79 -> 0 | E6: =D6+'Prévisions mensuelles'!P79 -> 0 | F6: =E6+'Prévisions mensuelles'!AC79 -> 0
B7: Immobilisations corporelles | D7: =+C7+SUM('Prévisions mensuelles'!C80:C83) -> 5500 | E7: =+D7+SUM('Prévisions mensuelles'!P80:P83) -> 7500 | F7: =+E7+SUM('Prévisions mensuelles'!AC80:AC83) -> 10000
B8: Amortissements cumulés | D8: =C8+'Compte de Résultat'!D21 -> -1833.3333 | E8: =D8+'Compte de Résultat'!E21 -> -2500 | F8: =E8+'Compte de Résultat'!F21 -> -3333.3333
B9: Autres immobilisations financières | D9: =C9+'Prévisions mensuelles'!C84 -> 0 | E9: =D9+'Prévisions mensuelles'!P84 -> 0 | F9: =E9+'Prévisions mensuelles'!AC84 -> 0
B10: Actif immobilisé | C10: =SUM(C6:C9) -> 0 | D10: =SUM(D6:D9) -> 3666.6667 | E10: =SUM(E6:E9) -> 5000 | F10: =SUM(F6:F9) -> 6666.6667
B12: Clients | D12: =$C12+SUMIFS('Prévisions mensuelles'!36:36,'Prévisions mensuelles'!$1:$1,"<="&D$3)*1.2-SUMIFS('Prévisions mensuelles'!$113:$113,'Prévisions mensuelles'!$1:$1,"<="&D$3) -> 11300 | E12: =$C12+SUMIFS('Prévisions mensuelles'!36:36,'Prévisions mensuelles'!$1:$1,"<="&E$3)*1.2-SUMIFS('Prévisions mensuelles'!$113:$113,'Prévisions mensuelles'!$1:$1,"<="&E$3) -> 24800 | F12: =$C12+SUMIFS('Prévisions mensuelles'!36:36,'Prévisions mensuelles'!$1:$1,"<="&F$3)*1.2-SUMIFS('Prévisions mensuelles'!$113:$113,'Prévisions mensuelles'!$1:$1,"<="&F$3) -> 41700
B13: Impôt sur les sociétés | D13: =C13+IF(SUMIFS('Prévisions mensuelles'!$70:$70,'Prévisions mensuelles'!$1:$1,"<="&D$3)-SUMIFS('Prévisions mensuelles'!$125:$125,'Prévisions mensuelles'!$1:$1,"<="&D$3)>0,0,SUMIFS('Prévisions mensuelles'!$70:$70,'Prévisions mensuelles'!$1:$1,"<="&D$3)-SUMIFS('Prévisions mensuelles'!$125:$125,'Prévisions mensuelles'!$1:$1,"<="&D$3)) -> 0 | E13: =$C13+IF(SUMIFS('Prévisions mensuelles'!$70:$70,'Prévisions mensuelles'!$1:$1,"<="&E$3)-SUMIFS('Prévisions mensuelles'!$125:$125,'Prévisions mensuelles'!$1:$1,"<="&E$3)>0,0,SUMIFS('Prévisions mensuelles'!$70:$70,'Prévisions mensuelles'!$1:$1,"<="&E$3)-SUMIFS('Prévisions mensuelles'!$125:$125,'Prévisions mensuelles'!$1:$1,"<="&E$3)) -> 0 | F13: =$C13+IF(SUMIFS('Prévisions mensuelles'!$70:$70,'Prévisions mensuelles'!$1:$1,"<="&F$3)-SUMIFS('Prévisions mensuelles'!$125:$125,'Prévisions mensuelles'!$1:$1,"<="&F$3)>0,0,SUMIFS('Prévisions mensuelles'!$70:$70,'Prévisions mensuelles'!$1:$1,"<="&F$3)-SUMIFS('Prévisions mensuelles'!$125:$125,'Prévisions mensuelles'!$1:$1,"<="&F$3)) -> 0
B14: TVA | D14: =-SUMIFS('Prévisions mensuelles'!140:140,'Prévisions mensuelles'!1:1,D$3) -> 0 | E14: =-SUMIFS('Prévisions mensuelles'!140:140,'Prévisions mensuelles'!1:1,E$3) -> 0 | F14: =-SUMIFS('Prévisions mensuelles'!140:140,'Prévisions mensuelles'!1:1,F$3) -> 0
B15: Trésorerie | D15: =IF('Prévisions mensuelles'!C129>0,'Prévisions mensuelles'!C129,0) -> 31630.157 | E15: =IF('Prévisions mensuelles'!P129>0,'Prévisions mensuelles'!P129,0) -> 72051.14 | F15: =IF('Prévisions mensuelles'!AC129>0,'Prévisions mensuelles'!AC129,0) -> 137165.29
B16: Charges constatées d'avance | D16: =C16+0 -> 0 | E16: =D16+0 -> 0 | F16: =E16+0 -> 0
B17: Actif circulant | C17: =SUM(C12:C16) -> 0 | D17: =SUM(D12:D16) -> 42930.157 | E17: =SUM(E12:E16) -> 96851.14 | F17: =SUM(F12:F16) -> 178865.29
B18: TOTAL ACTIF | C18: =C10+C17 -> 0 | D18: =D10+D17 -> 46596.823 | E18: =E10+E17 -> 101851.14 | F18: =F10+F17 -> 185531.96
B20: Capital | D20: =C20+'Prévisions mensuelles'!C112 -> 10000 | E20: =D20+'Prévisions mensuelles'!P112 -> 10000 | F20: =E20+'Prévisions mensuelles'!E112 -> 10000
B21: Réserves | D21: =C21+C22 -> 0 | E21: =D21+D22 -> 10434.592 | F21: =E21+E22 -> 56330.177
B22: Résultat de l'exercice | D22: ='Compte de Résultat'!D31 -> 10434.592 | E22: ='Compte de Résultat'!E31 -> 45895.585 | F22: ='Compte de Résultat'!F31 -> 75551.735
B23: Provisions réglementées | D23: =C23-'Compte de Résultat'!D29 -> 0 | E23: =D23-'Compte de Résultat'!E29 -> 0 | F23: =E23-'Compte de Résultat'!F29 -> 0
B24: Capitaux propres | C24: =SUM(C20:C23) -> 0 | D24: =SUM(D20:D23) -> 20434.592 | E24: =SUM(E20:E23) -> 66330.177 | F24: =SUM(F20:F23) -> 141881.91
B26: Emprunts auprès des banques | D26: =C26+SUMIFS('Prévisions mensuelles'!$115:$115,'Prévisions mensuelles'!$1:$1,"<="&D$3)-SUMIFS('Prévisions mensuelles'!$118:$118,'Prévisions mensuelles'!$1:$1,"<="&D$3) -> 16000 | E26: =$C26+SUMIFS('Prévisions mensuelles'!$115:$115,'Prévisions mensuelles'!$1:$1,"<="&E$3)-SUMIFS('Prévisions mensuelles'!$118:$118,'Prévisions mensuelles'!$1:$1,"<="&E$3) -> 12000 | F26: =$C26+SUMIFS('Prévisions mensuelles'!$115:$115,'Prévisions mensuelles'!$1:$1,"<="&F$3)-SUMIFS('Prévisions mensuelles'!$118:$118,'Prévisions mensuelles'!$1:$1,"<="&F$3) -> 8000
B27: Concours bancaires courants | D27: =C27+IF('Prévisions mensuelles'!C129<0,-'Prévisions mensuelles'!C129,0) -> 0 | E27: =D27+IF('Prévisions mensuelles'!P129<0,-'Prévisions mensuelles'!P129,0) -> 0 | F27: =E27+IF('Prévisions mensuelles'!Q129<0,-'Prévisions mensuelles'!Q129,0) -> 0
B28: Comptes courants | D28: =C28 -> 0 | E28: =D28 -> 0 | F28: =E28 -> 0
B29: Fournisseurs | D29: =C29+SUMIFS('Prévisions mensuelles'!$42:$42,'Prévisions mensuelles'!$1:$1,"<="&D$3)*1.2+SUMIFS('Prévisions mensuelles'!$53:$53,'Prévisions mensuelles'!$1:$1,"<="&D$3)*1.2+SUMIFS('Prévisions mensuelles'!$54:$54,'Prévisions mensuelles'!$1:$1,"<="&D$3)*1.2-SUMIFS('Prévisions mensuelles'!$120:$120,'Prévisions mensuelles'!$1:$1,"<="&D$3) -> 1870 | E29: =$C29+SUMIFS('Prévisions mensuelles'!$42:$42,'Prévisions mensuelles'!$1:$1,"<="&E$3)*1.2+SUMIFS('Prévisions mensuelles'!$53:$53,'Prévisions mensuelles'!$1:$1,"<="&E$3)*1.2+SUMIFS('Prévisions mensuelles'!$54:$54,'Prévisions mensuelles'!$1:$1,"<="&E$3)*1.2-SUMIFS('Prévisions mensuelles'!$120:$120,'Prévisions mensuelles'!$1:$1,"<="&E$3) -> 1970 | F29: =$C29+SUMIFS('Prévisions mensuelles'!$42:$42,'Prévisions mensuelles'!$1:$1,"<="&F$3)*1.2+SUMIFS('Prévisions mensuelles'!$53:$53,'Prévisions mensuelles'!$1:$1,"<="&F$3)*1.2+SUMIFS('Prévisions mensuelles'!$54:$54,'Prévisions mensuelles'!$1:$1,"<="&F$3)*1.2-SUMIFS('Prévisions mensuelles'!$120:$120,'Prévisions mensuelles'!$1:$1,"<="&F$3) -> 2170
B30: Fournisseurs immos | D30: =SUMIFS('Prévisions mensuelles'!$85:$85,'Prévisions mensuelles'!$1:$1,"<="&D$3)*1.2-SUMIFS('Prévisions mensuelles'!$119:$119,'Prévisions mensuelles'!$1:$1,"<="&D$3) -> 550 | E30: =SUMIFS('Prévisions mensuelles'!$85:$85,'Prévisions mensuelles'!$1:$1,"<="&E$3)*1.2-SUMIFS('Prévisions mensuelles'!$119:$119,'Prévisions mensuelles'!$1:$1,"<="&E$3) -> 200 | F30: =SUMIFS('Prévisions mensuelles'!$85:$85,'Prévisions mensuelles'!$1:$1,"<="&F$3)*1.2-SUMIFS('Prévisions mensuelles'!$119:$119,'Prévisions mensuelles'!$1:$1,"<="&F$3) -> 250
B31: Dettes sociales | D31: =C31+'Prévisions mensuelles'!Q123 -> 2537.5 | E31: =$C31+'Prévisions mensuelles'!AD123 -> 5655.5 | F31: =$C31+'Prévisions mensuelles'!AE123 -> 9848
B32: Impôt sur les sociétés | D32: =C32+IF(SUMIFS('Prévisions mensuelles'!$70:$70,'Prévisions mensuelles'!$1:$1,"<="&D$3)-SUMIFS('Prévisions mensuelles'!$125:$125,'Prévisions mensuelles'!$1:$1,"<="&D$3)<0,0,SUMIFS('Prévisions mensuelles'!$70:$70,'Prévisions mensuelles'!$1:$1,"<="&D$3)-SUMIFS('Prévisions mensuelles'!$125:$125,'Prévisions mensuelles'!$1:$1,"<="&D$3)) -> 1841.3985 | E32: =$C32+IF(SUMIFS('Prévisions mensuelles'!$70:$70,'Prévisions mensuelles'!$1:$1,"<="&E$3)-SUMIFS('Prévisions mensuelles'!$125:$125,'Prévisions mensuelles'!$1:$1,"<="&E$3)<0,0,SUMIFS('Prévisions mensuelles'!$70:$70,'Prévisions mensuelles'!$1:$1,"<="&E$3)-SUMIFS('Prévisions mensuelles'!$125:$125,'Prévisions mensuelles'!$1:$1,"<="&E$3)) -> 7790.4631 | F32: =$C32+IF(SUMIFS('Prévisions mensuelles'!$70:$70,'Prévisions mensuelles'!$1:$1,"<="&F$3)-SUMIFS('Prévisions mensuelles'!$125:$125,'Prévisions mensuelles'!$1:$1,"<="&F$3)<0,0,SUMIFS('Prévisions mensuelles'!$70:$70,'Prévisions mensuelles'!$1:$1,"<="&F$3)-SUMIFS('Prévisions mensuelles'!$125:$125,'Prévisions mensuelles'!$1:$1,"<="&F$3)) -> 9885.3833
B33: TVA | D33: =C33+SUMIFS('Prévisions mensuelles'!$141:$141,'Prévisions mensuelles'!$1:$1,D$3)+SUMIFS('Prévisions mensuelles'!$143:$143,'Prévisions mensuelles'!$1:$1,D$3)+'Prévisions mensuelles'!C143 -> 3363.3333 | E33: =$D33+SUMIFS('Prévisions mensuelles'!$141:$141,'Prévisions mensuelles'!$1:$1,E$3)+SUMIFS('Prévisions mensuelles'!$143:$143,'Prévisions mensuelles'!$1:$1,E$3)+'Prévisions mensuelles'!P143-'Prévisions mensuelles'!O126 -> 7905 | F33: =$E33+SUMIFS('Prévisions mensuelles'!$141:$141,'Prévisions mensuelles'!$1:$1,F$3)+SUMIFS('Prévisions mensuelles'!$143:$143,'Prévisions mensuelles'!$1:$1,F$3)+'Prévisions mensuelles'!AC143-'Prévisions mensuelles'!AB141 -> 13496.667
B34: Autres dettes sociales et fiscales | D34: 0 | E34: =$C34+0 -> 0 | F34: =$C34+0 -> 0
B35: Autres dettes (avoirs) | D35: =C35 -> 0 | E35: =D35 -> 0 | F35: =E35 -> 0
B36: Produits constatés d'avance | D36: =C36+'Prévisions mensuelles'!D37 -> 0 | E36: =D36+'Prévisions mensuelles'!E37 -> 0 | F36: =E36+'Prévisions mensuelles'!F37 -> 0
B37: Ecart
B38: Total des dettes | C38: =SUM(C26:C37) -> 0 | D38: =SUM(D26:D37) -> 26162.232 | E38: =SUM(E26:E37) -> 35520.963 | F38: =SUM(F26:F37) -> 43650.05
B39: TOTAL PASSIF | C39: =C24+C38 -> 0 | D39: =D24+D38 -> 46596.823 | E39: =E24+E38 -> 101851.14 | F39: =F24+F38 -> 185531.96
B41: Ctrl | C41: =C18-C39 -> 0 | D41: =D18-D39 -> 0 | E41: =E18-E39 -> 0 | F41: =F18-F39 -> 0
B43: BFR | C43: =SUM(C12:C14,C16)-SUM(C29:C36) -> 0 | D43: =SUM(D12:D14,D16)-SUM(D29:D36) -> 1137.7682 | E43: =SUM(E12:E14,E16)-SUM(E29:E36) -> 1279.0369 | F43: =SUM(F12:F14,F16)-SUM(F29:F36) -> 6049.95
B44: Var. BFR | D44: =D43-C43 -> 1137.7682 | E44: =E43-D43 -> 141.26871 | F44: =F43-E43 -> 4770.9132

Sheet Plan de Financement
B2: Plan de financement
B3: en k€ | C3: =Bilan!C3 -> 46022 | D3: =Bilan!D3 -> 46387 | E3: =Bilan!E3 -> 46752 | F3: =Bilan!F3 -> 47118
C4: =Bilan!C4 -> 12m | D4: =Bilan!D4 -> 12m | E4: =Bilan!E4 -> 12m | F4: =Bilan!F4 -> 12m
B6: Distribution de dividendes
B7: Investissements | D7: =+'Prévisions mensuelles'!C85 -> 5500 | E7: =+'Prévisions mensuelles'!P85 -> 2000 | F7: ='Prévisions mensuelles'!AC85 -> 2500
B8: Var. BFR d'exploitation | D8: =IF(Bilan!D44<0,0,Bilan!D44) -> 1137.7682 | E8: =IF(Bilan!E44<0,0,Bilan!E44) -> 141.26871 | F8: =IF(Bilan!F44<0,0,Bilan!F44) -> 4770.9132
B9: Remboursement d'emprunts | D9: ='Prévisions mensuelles'!C118 -> 4000 | E9: ='Prévisions mensuelles'!P118 -> 4000 | F9: ='Prévisions mensuelles'!AC118 -> 4000
B10: Total des besoins | D10: =SUM(D7:D9) -> 10637.768 | E10: =SUM(E7:E9) -> 6141.2687 | F10: =SUM(F7:F9) -> 11270.913
B12: Capacité d'autofinancement | D12: ='Compte de Résultat'!D31-'Compte de Résultat'!D21-'Compte de Résultat'!D29 -> 12267.925 | E12: ='Compte de Résultat'!E31-'Compte de Résultat'!E21-'Compte de Résultat'!E29 -> 46562.252 | F12: ='Compte de Résultat'!F31-'Compte de Résultat'!F21-'Compte de Résultat'!F29 -> 76385.068
B13: Var. BFR d'exploitation | D13: =IF(Bilan!D44<0,-Bilan!D44,0) -> 0 | E13: =IF(Bilan!E44<0,-Bilan!E44,0) -> 0 | F13: =IF(Bilan!F44<0,-Bilan!F44,0) -> 0
B14: Augmentation de capital | D14: ='Prévisions mensuelles'!C112 -> 10000 | E14: ='Prévisions mensuelles'!P112 -> 0 | F14: ='Prévisions mensuelles'!AC112 -> 0
B15: Nouveaux emprunts | D15: ='Prévisions mensuelles'!C115 -> 20000 | E15: 0 | F15: ='Prévisions mensuelles'!AC115 -> 0
B16: Autres | D16: =Bilan!D37 -> 0 | E16: =Bilan!E37 -> 0 | F16: =Bilan!F37-E16 -> 0
B17: Total des ressources | D17: =SUM(D12:D15) -> 42267.925 | E17: =SUM(E12:E16) -> 46562.252 | F17: =SUM(F12:F16) -> 76385.068
B18: Variation de trésorerie | D18: =D17-D10 -> 31630.157 | E18: =E17-E10 -> 40420.983 | F18: =F17-F10 -> 65114.155
B19: Trésorerie fin de période | C19: 0 | D19: =D18+C19 -> 31630.157 | E19: =E18+D19 -> 72051.14 | F19: =F18+E19 -> 137165.29
B21: Ctrl | C21: =C19-Bilan!C15 -> 0 | D21: =D19-Bilan!D15 -> -5.4569682e-11 | E21: =E19-Bilan!E15 -> 0 | F21: =F19-Bilan!F15 -> 0

Sheet Compte de Résultat
B2: Compte de résultat
B3: en k€ | C3: =Bilan!C3 -> 46022 | D3: =Bilan!D3 -> 46387 | E3: =Bilan!E3 -> 46752 | F3: =Bilan!F3 -> 47118
C4: =Bilan!C4 -> 12m | D4: =Bilan!D4 -> 12m | E4: =Bilan!E4 -> 12m | F4: =Bilan!F4 -> 12m
B6: Revenus | D6: =+'Prévisions mensuelles'!C36 -> 113000 | E6: =+'Prévisions mensuelles'!P36 -> 248000 | F6: =+'Prévisions mensuelles'!AC36 -> 417000
B7: Chiffre d'affaires | D7: =SUM(D6:D6) -> 113000 | E7: =SUM(E6:E6) -> 248000 | F7: =SUM(F6:F6) -> 417000
B9: Subventions
B11: Charges directes | D11: =-('Prévisions mensuelles'!C42) -> -7200 | E11: =-('Prévisions mensuelles'!P42) -> -7200 | F11: =-('Prévisions mensuelles'!AC42) -> -7200
B12: Charges externes | D12: =-'Prévisions mensuelles'!C53-D13 -> -11500 | E12: =-'Prévisions mensuelles'!P53-E13 -> -12500 | F12: =-'Prévisions mensuelles'!AC53-F13 -> -14500
B13: Soldes de crédit-bail | D13: 0 | E13: 0 | F13: 0
B14: Impôts & taxes | D14: =-'Prévisions mensuelles'!C56 -> -600 | E14: =-'Prévisions mensuelles'!P56 -> -600 | F14: =-'Prévisions mensuelles'!AC56 -> -600
B15: Charges de personnel | D15: =-'Prévisions mensuelles'!C57-'Prévisions mensuelles'!C58 -> -53850 | E15: =-'Prévisions mensuelles'!P57-'Prévisions mensuelles'!P58 -> -125898 | F15: =-'Prévisions mensuelles'!AC57-'Prévisions mensuelles'!AC58 -> -218328
B16: Rémunération gérant | D16: =-'Prévisions mensuelles'!C55 -> -25000 | E16: =-'Prévisions mensuelles'!P55 -> -45000 | F16: =-'Prévisions mensuelles'!AC55 -> -80000
B17: Redevances | D17: =-'Prévisions mensuelles'!C54 -> 0 | E17: =-'Prévisions mensuelles'!P54 -> 0 | F17: =-'Prévisions mensuelles'!AC54 -> 0
B18: EBITDA | C18: =C7+C9+SUM(C11:C16) -> 0 | D18: =D7+D9+SUM(D11:D16) -> 14850 | E18: =E7+E9+SUM(E11:E16) -> 56802 | F18: =F7+F9+SUM(F11:F16) -> 96372
B19: EBITDA en % | D19: =D18/D$7 -> 0.13141593 | E19: =E18/E$7 -> 0.22904032 | F19: =F18/F$7 -> 0.23110791
B21: Dotations aux amortissements | D21: =-'Prévisions mensuelles'!C59 -> -1833.3333 | E21: =-'Prévisions mensuelles'!P59 -> -666.66667 | F21: =-'Prévisions mensuelles'!AC59 -> -833.33333
B22: Résultat d'exploitation (EBIT) | C22: =C18+C21 -> 0 | D22: =D18+D21 -> 13016.667 | E22: =E18+E21 -> 56135.333 | F22: =F18+F21 -> 95538.667
B23: EBIT en % | D23: =D22/D$7 -> 0.11519174 | E23: =E22/E$7 -> 0.22635215 | F23: =F22/F$7 -> 0.22910951
B25: Résultat financier | D25: =-'Prévisions mensuelles'!C64 -> -740.67657 | E25: =-'Prévisions mensuelles'!P64 -> -607.8867 | F25: =-'Prévisions mensuelles'!AC64 -> -469.68677
B26: Résultat courant | C26: =C22+C25 -> 0 | D26: =D22+D25 -> 12275.99 | E26: =E22+E25 -> 55527.447 | F26: =F22+F25 -> 95068.98
B27: Résultat courant en % | D27: =D26/D$7 -> 0.10863708 | E27: =E26/E$7 -> 0.22390099 | F27: =F26/F$7 -> 0.22798317
B29: Résultat exceptionnel | D29: =-'Prévisions mensuelles'!C69 -> 0 | E29: =-'Prévisions mensuelles'!P69 -> 0 | F29: =-'Prévisions mensuelles'!AC69 -> 0
B30: Impôt sur les bénéfices | D30: =-'Prévisions mensuelles'!C70 -> -1841.3985 | E30: =-'Prévisions mensuelles'!P70 -> -9631.8617 | F30: =-'Prévisions mensuelles'!AC70 -> -19517.245
B31: Résultat net | C31: =C26+SUM(C29:C30) -> 0 | D31: =D26+SUM(D29:D30) -> 10434.592 | E31: =E26+SUM(E29:E30) -> 45895.585 | F31: =F26+SUM(F29:F30) -> 75551.735
B32: Résultat net en % | D32: =D31/D7 -> 0.092341518 | E32: =E31/E7 -> 0.18506284 | F32: =F31/F7 -> 0.18117922
B36: Ctrl | D36: =D31-'Prévisions mensuelles'!C72 -> 0 | E36: =E31-'Prévisions mensuelles'!P72 -> 0 | F36: =F31-'Prévisions mensuelles'!AC72 -> 0

Sheet Plan de trésorerie
B1: Plan de trésorerie
B3: Date | D3: 46053 | E3: 46081 | F3: 46112 | G3: 46142 | H3: 46173 | I3: 46203 | J3: 46234 | K3: 46265 | L3: 46295 | M3: 46326 | N3: 46356 | O3: 46387 | Q3: 46418 | R3: 46446 | S3: 46477 | T3: 46507 | U3: 46538 | V3: 46568 | W3: 46599 | X3: 46630 | Y3: 46660 | Z3: 46691 | AA3: 46721 | AB3: 46752 | AD3: 46783 | AE3: 46812 | AF3: 46843 | AG3: 46873 | AH3: 46904 | AI3: 46934 | AJ3: 46965 | AK3: 46996 | AL3: 47026 | AM3: 47057 | AN3: 47087 | AO3: 47118
B5: I - Trésorerie initiale | D5: =+'Prévisions mensuelles'!D109 -> 0 | E5: =+'Prévisions mensuelles'!E109 -> 25516.667 | F5: =+'Prévisions mensuelles'!F109 -> 27376.722 | G5: =+'Prévisions mensuelles'!G109 -> 28161.003 | H5: =+'Prévisions mensuelles'!H109 -> 28542.845 | I5: =+'Prévisions mensuelles'!I109 -> 28925.585 | J5: =+'Prévisions mensuelles'!J109 -> 29309.226 | K5: =+'Prévisions mensuelles'!K109 -> 29693.771 | ... AO5: =+'Prévisions mensuelles'!AO109 -> 132117.65
B7: II - Recettes | C7: =+'Prévisions mensuelles'!C111 -> 154300 | D7: =+'Prévisions mensuelles'!D111 -> 30000 | E7: =+'Prévisions mensuelles'!E111 -> 11300 | F7: =+'Prévisions mensuelles'!F111 -> 11300 | G7: =+'Prévisions mensuelles'!G111 -> 11300 | H7: =+'Prévisions mensuelles'!H111 -> 11300 | I7: =+'Prévisions mensuelles'!I111 -> 11300 | J7: =+'Prévisions mensuelles'!J111 -> 11300 | ... AO7: =+'Prévisions mensuelles'!AO111 -> 41700
B8: Apport en capital | C8: =+'Prévisions mensuelles'!C112 -> 10000 | D8: =+'Prévisions mensuelles'!D112 -> 10000 | E8: =+'Prévisions mensuelles'!E112 -> 0 | F8: =+'Prévisions mensuelles'!F112 -> 0 | G8: =+'Prévisions mensuelles'!G112 -> 0 | H8: =+'Prévisions mensuelles'!H112 -> 0 | I8: =+'Prévisions mensuelles'!I112 -> 0 | J8: =+'Prévisions mensuelles'!J112 -> 0 | ... AO8: =+'Prévisions mensuelles'!AO112 -> 0
B9: Encaissement clients TTC | C9: =+'Prévisions mensuelles'!C113 -> 124300 | D9: =+'Prévisions mensuelles'!D113 -> 0 | E9: =+'Prévisions mensuelles'!E113 -> 11300 | F9: =+'Prévisions mensuelles'!F113 -> 11300 | G9: =+'Prévisions mensuelles'!G113 -> 11300 | H9: =+'Prévisions mensuelles'!H113 -> 11300 | I9: =+'Prévisions mensuelles'!I113 -> 11300 | J9: =+'Prévisions mensuelles'!J113 -> 11300 | ... AO9: =+'Prévisions mensuelles'!AO113 -> 41700
B10: Remboursement crédit TVA | C10: =+'Prévisions mensuelles'!C114 -> 0 | D10: =+'Prévisions mensuelles'!D114 -> 0 | E10: =+'Prévisions mensuelles'!E114 -> 0 | F10: =+'Prévisions mensuelles'!F114 -> 0 | G10: =+'Prévisions mensuelles'!G114 -> 0 | H10: =+'Prévisions mensuelles'!H114 -> 0 | I10: =+'Prévisions mensuelles'!I114 -> 0 | J10: =+'Prévisions mensuelles'!J114 -> 0 | ... AO10: =+'Prévisions mensuelles'!AO114 -> 0
B11: Nouveaux crédits bancaires | C11: =+'Prévisions mensuelles'!C115 -> 20000 | D11: =+'Prévisions mensuelles'!D115 -> 20000 | E11: =+'Prévisions mensuelles'!E115 -> 0 | F11: =+'Prévisions mensuelles'!F115 -> 0 | G11: =+'Prévisions mensuelles'!G115 -> 0 | H11: =+'Prévisions mensuelles'!H115 -> 0 | I11: =+'Prévisions mensuelles'!I115 -> 0 | J11: =+'Prévisions mensuelles'!J115 -> 0 | ... AO11: =+'Prévisions mensuelles'!AO115 -> 0
B13: III - Dépenses | C13: =+'Prévisions mensuelles'!C117 -> 122669.84 | D13: =+'Prévisions mensuelles'!D117 -> 4483.3333 | E13: =+'Prévisions mensuelles'!E117 -> 9439.9444 | F13: =+'Prévisions mensuelles'!F117 -> 10515.719 | G13: =+'Prévisions mensuelles'!G117 -> 10918.158 | H13: =+'Prévisions mensuelles'!H117 -> 10917.26 | I13: =+'Prévisions mensuelles'!I117 -> 10916.359 | J13: =+'Prévisions mensuelles'!J117 -> 10915.455 | ... AO13: =+'Prévisions mensuelles'!AO117 -> 36652.358
B14: Remboursement de crédit | C14: =+'Prévisions mensuelles'!C118 -> 4000 | D14: =+'Prévisions mensuelles'!D118 -> 333.33333 | E14: =+'Prévisions mensuelles'!E118 -> 333.33333 | F14: =+'Prévisions mensuelles'!F118 -> 333.33333 | G14: =+'Prévisions mensuelles'!G118 -> 333.33333 | H14: =+'Prévisions mensuelles'!H118 -> 333.33333 | I14: =+'Prévisions mensuelles'!I118 -> 333.33333 | J14: =+'Prévisions mensuelles'!J118 -> 333.33333 | ... AO14: =+'Prévisions mensuelles'!AO118 -> 333.33333
B15: Investissements | C15: =+'Prévisions mensuelles'!C119 -> 6050 | D15: =+'Prévisions mensuelles'!D119 -> 0 | E15: =+'Prévisions mensuelles'!E119 -> 550 | F15: =+'Prévisions mensuelles'!F119 -> 550 | G15: =+'Prévisions mensuelles'!G119 -> 550 | H15: =+'Prévisions mensuelles'!H119 -> 550 | I15: =+'Prévisions mensuelles'!I119 -> 550 | J15: =+'Prévisions mensuelles'!J119 -> 550 | ... AO15: =+'Prévisions mensuelles'!AO119 -> 250
B16: Charges directes et externes TTC | C16: =+'Prévisions mensuelles'!C120 -> 20570 | D16: =+'Prévisions mensuelles'!D120 -> 0 | E16: =+'Prévisions mensuelles'!E120 -> 1870 | F16: =+'Prévisions mensuelles'!F120 -> 1870 | G16: =+'Prévisions mensuelles'!G120 -> 1870 | H16: =+'Prévisions mensuelles'!H120 -> 1870 | I16: =+'Prévisions mensuelles'!I120 -> 1870 | J16: =+'Prévisions mensuelles'!J120 -> 1870 | ... AO16: =+'Prévisions mensuelles'!AO120 -> 2170
B17: Impôts & taxes | C17: =+'Prévisions mensuelles'!C121 -> 600 | D17: =+'Prévisions mensuelles'!D121 -> 50 | E17: =+'Prévisions mensuelles'!E121 -> 50 | F17: =+'Prévisions mensuelles'!F121 -> 50 | G17: =+'Prévisions mensuelles'!G121 -> 50 | H17: =+'Prévisions mensuelles'!H121 -> 50 | I17: =+'Prévisions mensuelles'!I121 -> 50 | J17: =+'Prévisions mensuelles'!J121 -> 50 | ... AO17: =+'Prévisions mensuelles'!AO121 -> 50
B18: Salaires | C18: =+'Prévisions mensuelles'!C122 -> 48400 | D18: =+'Prévisions mensuelles'!D122 -> 4033.3333 | E18: =+'Prévisions mensuelles'!E122 -> 4033.3333 | F18: =+'Prévisions mensuelles'!F122 -> 4033.3333 | G18: =+'Prévisions mensuelles'!G122 -> 4033.3333 | H18: =+'Prévisions mensuelles'!H122 -> 4033.3333 | I18: =+'Prévisions mensuelles'!I122 -> 4033.3333 | J18: =+'Prévisions mensuelles'!J122 -> 4033.3333 | ... AO18: =+'Prévisions mensuelles'!AO122 -> 15012.667
B19: Charges sociales | C19: =+'Prévisions mensuelles'!C123 -> 27912.5 | D19: =+'Prévisions mensuelles'!D123 -> 0 | E19: =+'Prévisions mensuelles'!E123 -> 2537.5 | F19: =+'Prévisions mensuelles'!F123 -> 2537.5 | G19: =+'Prévisions mensuelles'!G123 -> 2537.5 | H19: =+'Prévisions mensuelles'!H123 -> 2537.5 | I19: =+'Prévisions mensuelles'!I123 -> 2537.5 | J19: =+'Prévisions mensuelles'!J123 -> 2537.5 | ... AO19: =+'Prévisions mensuelles'!AO123 -> 9848
... B25: IV - Trésorerie finale | C25: =+'Prévisions mensuelles'!C129 -> 31630.157 | D25: =+'Prévisions mensuelles'!D129 -> 25516.667 | E25: =+'Prévisions mensuelles'!E129 -> 27376.722 | F25: =+'Prévisions mensuelles'!F129 -> 28161.003 | G25: =+'Prévisions mensuelles'!G129 -> 28542.845 | H25: =+'Prévisions mensuelles'!H129 -> 28925.585 | I25: =+'Prévisions mensuelles'!I129 -> 29309.226 | J25: =+'Prévisions mensuelles'!J129 -> 29693.771 | ... AO25: =+'Prévisions mensuelles'!AO129 -> 137165.29

Sheet Prévisions mensuelles
D1: =EOMONTH(D3,0) -> 46053 | E1: =EOMONTH(E3,0) -> 46081 | F1: =EOMONTH(F3,0) -> 46112 | G1: =EOMONTH(G3,0) -> 46142 | H1: =EOMONTH(H3,0) -> 46173 | I1: =EOMONTH(I3,0) -> 46203 | J1: =EOMONTH(J3,0) -> 46234 | K1: =EOMONTH(K3,0) -> 46265 | ... O1: =EOMONTH(O3,0) -> 46387 | Q1: =EOMONTH(Q3,0) -> 46418 | R1: =EOMONTH(R3,0) -> 46446 | S1: =EOMONTH(S3,0) -> 46477 | T1: =EOMONTH(T3,0) -> 46507 | U1: =EOMONTH(U3,0) -> 46538 | V1: =EOMONTH(V3,0) -> 46568 | W1: =EOMONTH(W3,0) -> 46599 | X1: =EOMONTH(X3,0) -> 46630 | ... AB1: =EOMONTH(AB3,0) -> 46752 | AD1: =EOMONTH(AD3,0) -> 46783 | AE1: =EOMONTH(AE3,0) -> 46812 | AF1: =EOMONTH(AF3,0) -> 46843 | AG1: =EOMONTH(AG3,0) -> 46873 | AH1: =EOMONTH(AH3,0) -> 46904 | AI1: =EOMONTH(AI3,0) -> 46934 | AJ1: =EOMONTH(AJ3,0) -> 46965 | AK1: =EOMONTH(AK3,0) -> 46996 | ... AO1: =EOMONTH(AO3,0) -> 47118
B2: 1) Budget des ventes
D3: 46053 | E3: 46081 | F3: 46112 | G3: 46142 | H3: 46173 | I3: 46203 | J3: 46234 | K3: 46265 | L3: 46295 | M3: 46326 | N3: 46356 | O3: 46387 | Q3: 46418 | R3: 46446 | S3: 46477 | T3: 46507 | U3: 46538 | V3: 46568 | W3: 46599 | X3: 46630 | Y3: 46660 | Z3: 46691 | AA3: 46721 | AB3: 46752 | AD3: 46783 | AE3: 46811 | AF3: 46843 | AG3: 46873 | AH3: 46904 | AI3: 46934 | AJ3: 46965 | AK3: 46996 | AL3: 47026 | AM3: 47057 | AN3: 47087 | AO3: 47118
B5: a) Expertise-comptable
B7: Chiffre d'affaires | C7: =SAISIE!C8 -> 80000 | D7: =SAISIE!$C$8/12 -> 6666.6667 | E7: =SAISIE!$C$8/12 -> 6666.6667 | F7: =SAISIE!$C$8/12 -> 6666.6667 | G7: =SAISIE!$C$8/12 -> 6666.6667 | H7: =SAISIE!$C$8/12 -> 6666.6667 | I7: =SAISIE!$C$8/12 -> 6666.6667 | J7: =SAISIE!$C$8/12 -> 6666.6667 | K7: =SAISIE!$C$8/12 -> 6666.6667 | ... O7: =SAISIE!$C$8/12 -> 6666.6667 | P7: =SAISIE!D8 -> 160000 | Q7: =SAISIE!$D$8/12 -> 13333.333 | R7: =SAISIE!$D$8/12 -> 13333.333 | S7: =SAISIE!$D$8/12 -> 13333.333 | T7: =SAISIE!$D$8/12 -> 13333.333 | U7: =SAISIE!$D$8/12 -> 13333.333 | V7: =SAISIE!$D$8/12 -> 13333.333 | W7: =SAISIE!$D$8/12 -> 13333.333 | X7: =SAISIE!$D$8/12 -> 13333.333 | ... AB7: =SAISIE!$D$8/12 -> 13333.333 | AC7: =SAISIE!E8 -> 240000 | AD7: =SAISIE!$E$8/12 -> 20000 | AE7: =SAISIE!$E$8/12 -> 20000 | AF7: =SAISIE!$E$8/12 -> 20000 | AG7: =SAISIE!$E$8/12 -> 20000 | AH7: =SAISIE!$E$8/12 -> 20000 | AI7: =SAISIE!$E$8/12 -> 20000 | AJ7: =SAISIE!$E$8/12 -> 20000 | AK7: =SAISIE!$E$8/12 -> 20000 | ... AO7: =SAISIE!$E$8/12 -> 20000
C8: 0.5
B9: b) CAC
B11: Chiffre d'affaires | C11: =SAISIE!C9 -> 0 | D11: =SAISIE!$C$9/12 -> 0 | E11: =SAISIE!$C$9/12 -> 0 | F11: =SAISIE!$C$9/12 -> 0 | G11: =SAISIE!$C$9/12 -> 0 | H11: =SAISIE!$C$9/12 -> 0 | I11: =SAISIE!$C$9/12 -> 0 | J11: =SAISIE!$C$9/12 -> 0 | K11: =SAISIE!$C$9/12 -> 0 | ... O11: =SAISIE!$C$9/12 -> 0 | P11: =SAISIE!D9 -> 36000 | Q11: =SAISIE!$D$9/12 -> 3000 | R11: =SAISIE!$D$9/12 -> 3000 | S11: =SAISIE!$D$9/12 -> 3000 | T11: =SAISIE!$D$9/12 -> 3000 | U11: =SAISIE!$D$9/12 -> 3000 | V11: =SAISIE!$D$9/12 -> 3000 | W11: =SAISIE!$D$9/12 -> 3000 | X11: =SAISIE!$D$9/12 -> 3000 | ... AB11: =SAISIE!$D$9/12 -> 3000 | AC11: =SAISIE!E9 -> 72000 | AD11: =SAISIE!$E$9/12 -> 6000 | AE11: =SAISIE!$E$9/12 -> 6000 | AF11: =SAISIE!$E$9/12 -> 6000 | AG11: =SAISIE!$E$9/12 -> 6000 | AH11: =SAISIE!$E$9/12 -> 6000 | AI11: =SAISIE!$E$9/12 -> 6000 | AJ11: =SAISIE!$E$9/12 -> 6000 | AK11: =SAISIE!$E$9/12 -> 6000 | ... AO11: =SAISIE!$E$9/12 -> 6000
C12: 0.11666667
B13: c) Social
B15: Chiffre d'affaires | C15: =SAISIE!C10 -> 5000 | D15: =SAISIE!$C$10/12 -> 416.66667 | E15: =SAISIE!$C$10/12 -> 416.66667 | F15: =SAISIE!$C$10/12 -> 416.66667 | G15: =SAISIE!$C$10/12 -> 416.66667 | H15: =SAISIE!$C$10/12 -> 416.66667 | I15: =SAISIE!$C$10/12 -> 416.66667 | J15: =SAISIE!$C$10/12 -> 416.66667 | K15: =SAISIE!$C$10/12 -> 416.66667 | ... O15: =SAISIE!$C$10/12 -> 416.66667 | P15: =SAISIE!D10 -> 10000 | Q15: =SAISIE!$D$10/12 -> 833.33333 | R15: =SAISIE!$D$10/12 -> 833.33333 | S15: =SAISIE!$D$10/12 -> 833.33333 | T15: =SAISIE!$D$10/12 -> 833.33333 | U15: =SAISIE!$D$10/12 -> 833.33333 | V15: =SAISIE!$D$10/12 -> 833.33333 | W15: =SAISIE!$D$10/12 -> 833.33333 | X15: =SAISIE!$D$10/12 -> 833.33333 | ... AB15: =SAISIE!$D$10/12 -> 833.33333 | AC15: =SAISIE!E10 -> 15000 | AD15: =SAISIE!$E$10/12 -> 1250 | AE15: =SAISIE!$E$10/12 -> 1250 | AF15: =SAISIE!$E$10/12 -> 1250 | AG15: =SAISIE!$E$10/12 -> 1250 | AH15: =SAISIE!$E$10/12 -> 1250 | AI15: =SAISIE!$E$10/12 -> 1250 | AJ15: =SAISIE!$E$10/12 -> 1250 | AK15: =SAISIE!$E$10/12 -> 1250 | ... AO15: =SAISIE!$E$10/12 -> 1250
C16: 0.11666667
B17: d) Juridique
B19: Chiffre d'affaires | C19: =SAISIE!C11 -> 3000 | D19: =SAISIE!$C$11/12 -> 250 | E19: =SAISIE!$C$11/12 -> 250 | F19: =SAISIE!$C$11/12 -> 250 | G19: =SAISIE!$C$11/12 -> 250 | H19: =SAISIE!$C$11/12 -> 250 | I19: =SAISIE!$C$11/12 -> 250 | J19: =SAISIE!$C$11/12 -> 250 | K19: =SAISIE!$C$11/12 -> 250 | ... O19: =SAISIE!$C$11/12 -> 250 | P19: =SAISIE!D11 -> 6000 | Q19: =SAISIE!$D$11/12 -> 500 | R19: =SAISIE!$D$11/12 -> 500 | S19: =SAISIE!$D$11/12 -> 500 | T19: =SAISIE!$D$11/12 -> 500 | U19: =SAISIE!$D$11/12 -> 500 | V19: =SAISIE!$D$11/12 -> 500 | W19: =SAISIE!$D$11/12 -> 500 | X19: =SAISIE!$D$11/12 -> 500 | ... AB19: =SAISIE!$D$11/12 -> 500 | AC19: =SAISIE!E11 -> 18000 | AD19: =SAISIE!$E$11/12 -> 1500 | AE19: =SAISIE!$E$11/12 -> 1500 | AF19: =SAISIE!$E$11/12 -> 1500 | AG19: =SAISIE!$E$11/12 -> 1500 | AH19: =SAISIE!$E$11/12 -> 1500 | AI19: =SAISIE!$E$11/12 -> 1500 | AJ19: =SAISIE!$E$11/12 -> 1500 | AK19: =SAISIE!$E$11/12 -> 1500 | ... AO19: =SAISIE!$E$11/12 -> 1500
C20: 0.16666667
B21: e) DAF externalisé
B23: Chiffre d'affaires | C23: =SAISIE!C12 -> 25000 | D23: =SAISIE!$C$12/12 -> 2083.3333 | E23: =SAISIE!$C$12/12 -> 2083.3333 | F23: =SAISIE!$C$12/12 -> 2083.3333 | G23: =SAISIE!$C$12/12 -> 2083.3333 | H23: =SAISIE!$C$12/12 -> 2083.3333 | I23: =SAISIE!$C$12/12 -> 2083.3333 | J23: =SAISIE!$C$12/12 -> 2083.3333 | K23: =SAISIE!$C$12/12 -> 2083.3333 | ... O23: =SAISIE!$C$12/12 -> 2083.3333 | P23: =SAISIE!D12 -> 36000 | Q23: =SAISIE!$D$12/12 -> 3000 | R23: =SAISIE!$D$12/12 -> 3000 | S23: =SAISIE!$D$12/12 -> 3000 | T23: =SAISIE!$D$12/12 -> 3000 | U23: =SAISIE!$D$12/12 -> 3000 | V23: =SAISIE!$D$12/12 -> 3000 | W23: =SAISIE!$D$12/12 -> 3000 | X23: =SAISIE!$D$12/12 -> 3000 | ... AB23: =SAISIE!$D$12/12 -> 3000 | AC23: =SAISIE!E12 -> 72000 | AD23: =SAISIE!$E$12/12 -> 6000 | AE23: =SAISIE!$E$12/12 -> 6000 | AF23: =SAISIE!$E$12/12 -> 6000 | AG23: =SAISIE!$E$12/12 -> 6000 | AH23: =SAISIE!$E$12/12 -> 6000 | AI23: =SAISIE!$E$12/12 -> 6000 | AJ23: =SAISIE!$E$12/12 -> 6000 | AK23: =SAISIE!$E$12/12 -> 6000 | ... AO23: =SAISIE!$E$12/12 -> 6000
B26: 2) Budget d'exploitation
D28: 46053 | E28: 46081 | F28: 46112 | G28: 46142 | H28: 46173 | I28: 46203 | J28: 46234 | K28: 46265 | L28: 46295 | M28: 46326 | N28: 46356 | O28: 46387 | Q28: 46418 | R28: 46446 | S28: 46477 | T28: 46507 | U28: 46538 | V28: 46568 | W28: 46599 | X28: 46630 | Y28: 46660 | Z28: 46691 | AA28: 46721 | AB28: 46752 | AD28: 46783 | AE28: 46811 | AF28: 46839 | AG28: 46867 | AH28: 46895 | AI28: 46923 | AJ28: 46951 | AK28: 46979 | AL28: 47007 | AM28: 47035 | AN28: 47063 | AO28: 47091
B30: =+B5 -> a) Expertise-comptable | C30: =+C7 -> 80000 | D30: =+D7 -> 6666.6667 | E30: =+E7 -> 6666.6667 | F30: =+F7 -> 6666.6667 | G30: =+G7 -> 6666.6667 | H30: =+H7 -> 6666.6667 | I30: =+I7 -> 6666.6667 | J30: =+J7 -> 6666.6667 | ... AO30: =+AO7 -> 20000
B31: =+B9 -> b) CAC | C31: =+C11 -> 0 | D31: =+D11 -> 0 | E31: =+E11 -> 0 | F31: =+F11 -> 0 | G31: =+G11 -> 0 | H31: =+H11 -> 0 | I31: =+I11 -> 0 | J31: =+J11 -> 0 | ... AO31: =+AO11 -> 6000
B32: =+B13 -> c) Social | C32: =+C15 -> 5000 | D32: =+D15 -> 416.66667 | E32: =+E15 -> 416.66667 | F32: =+F15 -> 416.66667 | G32: =+G15 -> 416.66667 | H32: =+H15 -> 416.66667 | I32: =+I15 -> 416.66667 | J32: =+J15 -> 416.66667 | ... AO32: =+AO15 -> 1250
B33: =+B17 -> d) Juridique | C33: =+C19 -> 3000 | D33: =+D19 -> 250 | E33: =+E19 -> 250 | F33: =+F19 -> 250 | G33: =+G19 -> 250 | H33: =+H19 -> 250 | I33: =+I19 -> 250 | J33: =+J19 -> 250 | ... AO33: =+AO19 -> 1500
B34: =+B21 -> e) DAF externalisé | C34: =+C23 -> 25000 | D34: =+D23 -> 2083.3333 | E34: =+E23 -> 2083.3333 | F34: =+F23 -> 2083.3333 | G34: =+G23 -> 2083.3333 | H34: =+H23 -> 2083.3333 | I34: =+I23 -> 2083.3333 | J34: =+J23 -> 2083.3333 | ... AO34: =+AO23 -> 6000
B36: Chiffre d'affaires | C36: =SUM(C30:C35) -> 113000 | D36: =SUM(D30:D35) -> 9416.6667 | E36: =SUM(E30:E35) -> 9416.6667 | F36: =SUM(F30:F35) -> 9416.6667 | G36: =SUM(G30:G35) -> 9416.6667 | H36: =SUM(H30:H35) -> 9416.6667 | I36: =SUM(I30:I35) -> 9416.6667 | J36: =SUM(J30:J35) -> 9416.6667 | ... AO36: =SUM(AO30:AO35) -> 34750
B37: *PCA n-1 | C37: =SUM(D37:O37) -> 0 | D37: =Bilan!C36 -> 0
B39: Marge directe | D39: =+(D36-D42)/D36 -> 0.93628319 | E39: =+(E36-E42)/E36 -> 0.93628319 | F39: =+(F36-F42)/F36 -> 0.93628319 | G39: =+(G36-G42)/G36 -> 0.93628319 | H39: =+(H36-H42)/H36 -> 0.93628319 | I39: =+(I36-I42)/I36 -> 0.93628319 | J39: =+(J36-J42)/J36 -> 0.93628319 | K39: =+(K36-K42)/K36 -> 0.93628319 | ... O39: =+(O36-O42)/O36 -> 0.93628319 | Q39: =+(Q36-Q42)/Q36 -> 0.97096774 | R39: =+(R36-R42)/R36 -> 0.97096774 | S39: =+(S36-S42)/S36 -> 0.97096774 | T39: =+(T36-T42)/T36 -> 0.97096774 | U39: =+(U36-U42)/U36 -> 0.97096774 | V39: =+(V36-V42)/V36 -> 0.97096774 | W39: =+(W36-W42)/W36 -> 0.97096774 | X39: =+(X36-X42)/X36 -> 0.97096774 | ... AB39: =+(AB36-AB42)/AB36 -> 0.97096774 | AD39: =+(AD36-AD42)/AD36 -> 0.98273381 | AE39: =+(AE36-AE42)/AE36 -> 0.98273381 | AF39: =+(AF36-AF42)/AF36 -> 0.98273381 | AG39: =+(AG36-AG42)/AG36 -> 0.98273381 | AH39: =+(AH36-AH42)/AH36 -> 0.98273381 | AI39: =+(AI36-AI42)/AI36 -> 0.98273381 | AJ39: =+(AJ36-AJ42)/AJ36 -> 0.98273381 | AK39: =+(AK36-AK42)/AK36 -> 0.98273381 | ... AO39: =+(AO36-AO42)/AO36 -> 0.98273381
B40: Logiciels | C40: =SAISIE!C16 -> 6000 | D40: =SAISIE!$C$16/12 -> 500 | E40: =SAISIE!$C$16/12 -> 500 | F40: =SAISIE!$C$16/12 -> 500 | G40: =SAISIE!$C$16/12 -> 500 | H40: =SAISIE!$C$16/12 -> 500 | I40: =SAISIE!$C$16/12 -> 500 | J40: =SAISIE!$C$16/12 -> 500 | K40: =SAISIE!$C$16/12 -> 500 | ... O40: =SAISIE!$C$16/12 -> 500 | P40: =SAISIE!D16 -> 6000 | Q40: =SAISIE!$D$16/12 -> 500 | R40: =SAISIE!$D$16/12 -> 500 | S40: =SAISIE!$D$16/12 -> 500 | T40: =SAISIE!$D$16/12 -> 500 | U40: =SAISIE!$D$16/12 -> 500 | V40: =SAISIE!$D$16/12 -> 500 | W40: =SAISIE!$D$16/12 -> 500 | X40: =SAISIE!$D$16/12 -> 500 | ... AB40: =SAISIE!$D$16/12 -> 500 | AC40: =SAISIE!E16 -> 6000 | AD40: =SAISIE!$E$16/12 -> 500 | AE40: =SAISIE!$E$16/12 -> 500 | AF40: =SAISIE!$E$16/12 -> 500 | AG40: =SAISIE!$E$16/12 -> 500 | AH40: =SAISIE!$E$16/12 -> 500 | AI40: =SAISIE!$E$16/12 -> 500 | AJ40: =SAISIE!$E$16/12 -> 500 | AK40: =SAISIE!$E$16/12 -> 500 | ... AO40: =SAISIE!$E$16/12 -> 500
B41: Marketing / PUB / investissement | C41: =SAISIE!C17 -> 1200 | D41: =SAISIE!$C$17/12 -> 100 | E41: =SAISIE!$C$17/12 -> 100 | F41: =SAISIE!$C$17/12 -> 100 | G41: =SAISIE!$C$17/12 -> 100 | H41: =SAISIE!$C$17/12 -> 100 | I41: =SAISIE!$C$17/12 -> 100 | J41: =SAISIE!$C$17/12 -> 100 | K41: =SAISIE!$C$17/12 -> 100 | ... O41: =SAISIE!$C$17/12 -> 100 | P41: =SAISIE!D17 -> 1200 | Q41: =SAISIE!$D$17/12 -> 100 | R41: =SAISIE!$D$17/12 -> 100 | S41: =SAISIE!$D$17/12 -> 100 | T41: =SAISIE!$D$17/12 -> 100 | U41: =SAISIE!$D$17/12 -> 100 | V41: =SAISIE!$D$17/12 -> 100 | W41: =SAISIE!$D$17/12 -> 100 | X41: =SAISIE!$D$17/12 -> 100 | ... AB41: =SAISIE!$D$17/12 -> 100 | AC41: =SAISIE!E17 -> 1200 | AD41: =SAISIE!$E$17/12 -> 100 | AE41: =SAISIE!$E$17/12 -> 100 | AF41: =SAISIE!$E$17/12 -> 100 | AG41: =SAISIE!$E$17/12 -> 100 | AH41: =SAISIE!$E$17/12 -> 100 | AI41: =SAISIE!$E$17/12 -> 100 | AJ41: =SAISIE!$E$17/12 -> 100 | AK41: =SAISIE!$E$17/12 -> 100 | ... AO41: =SAISIE!$E$17/12 -> 100
B42: Charges directes | C42: =SUM(C40:C41) -> 7200 | D42: =SUM(D40:D41) -> 600 | E42: =SUM(E40:E41) -> 600 | F42: =SUM(F40:F41) -> 600 | G42: =SUM(G40:G41) -> 600 | H42: =SUM(H40:H41) -> 600 | I42: =SUM(I40:I41) -> 600 | J42: =SUM(J40:J41) -> 600 | ... O42: =SUM(O40:O41) -> 600 | P42: =SUM(Q42:AB42) -> 7200 | Q42: =SUM(Q40:Q41) -> 600 | R42: =SUM(R40:R41) -> 600 | S42: =SUM(S40:S41) -> 600 | T42: =SUM(T40:T41) -> 600 | U42: =SUM(U40:U41) -> 600 | V42: =SUM(V40:V41) -> 600 | W42: =SUM(W40:W41) -> 600 | X42: =SUM(X40:X41) -> 600 | ... AB42: =SUM(AB40:AB41) -> 600 | AC42: =SUM(AD42:AO42) -> 7200 | AD42: =SUM(AD40:AD41) -> 600 | AE42: =SUM(AE40:AE41) -> 600 | AF42: =SUM(AF40:AF41) -> 600 | AG42: =SUM(AG40:AG41) -> 600 | AH42: =SUM(AH40:AH41) -> 600 | AI42: =SUM(AI40:AI41) -> 600 | AJ42: =SUM(AJ40:AJ41) -> 600 | AK42: =SUM(AK40:AK41) -> 600 | ... AO42: =SUM(AO40:AO41) -> 600
B43: Ordre | C43: =SAISIE!C21 -> 500 | D43: =SAISIE!$C$21/12 -> 41.666667 | E43: =SAISIE!$C$21/12 -> 41.666667 | F43: =SAISIE!$C$21/12 -> 41.666667 | G43: =SAISIE!$C$21/12 -> 41.666667 | H43: =SAISIE!$C$21/12 -> 41.666667 | I43: =SAISIE!$C$21/12 -> 41.666667 | J43: =SAISIE!$C$21/12 -> 41.666667 | K43: =SAISIE!$C$21/12 -> 41.666667 | ... O43: =SAISIE!$C$21/12 -> 41.666667 | P43: =SAISIE!D21 -> 500 | Q43: =SAISIE!$D$21/12 -> 41.666667 | R43: =SAISIE!$D$21/12 -> 41.666667 | S43: =SAISIE!$D$21/12 -> 41.666667 | T43: =SAISIE!$D$21/12 -> 41.666667 | U43: =SAISIE!$D$21/12 -> 41.666667 | V43: =SAISIE!$D$21/12 -> 41.666667 | W43: =SAISIE!$D$21/12 -> 41.666667 | X43: =SAISIE!$D$21/12 -> 41.666667 | ... AB43: =SAISIE!$D$21/12 -> 41.666667 | AC43: =SAISIE!E21 -> 500 | AD43: =SAISIE!$E$21/12 -> 41.666667 | AE43: =SAISIE!$E$21/12 -> 41.666667 | AF43: =SAISIE!$E$21/12 -> 41.666667 | AG43: =SAISIE!$E$21/12 -> 41.666667 | AH43: =SAISIE!$E$21/12 -> 41.666667 | AI43: =SAISIE!$E$21/12 -> 41.666667 | AJ43: =SAISIE!$E$21/12 -> 41.666667 | AK43: =SAISIE!$E$21/12 -> 41.666667 | ... AO43: =SAISIE!$E$21/12 -> 41.666667
B44: Assurances | C44: =SAISIE!C22 -> 2000 | D44: =SAISIE!$C$22/12 -> 166.66667 | E44: =SAISIE!$C$22/12 -> 166.66667 | F44: =SAISIE!$C$22/12 -> 166.66667 | G44: =SAISIE!$C$22/12 -> 166.66667 | H44: =SAISIE!$C$22/12 -> 166.66667 | I44: =SAISIE!$C$22/12 -> 166.66667 | J44: =SAISIE!$C$22/12 -> 166.66667 | K44: =SAISIE!$C$22/12 -> 166.66667 | ... O44: =SAISIE!$C$22/12 -> 166.66667 | P44: =SAISIE!D22 -> 3000 | Q44: =SAISIE!$D$22/12 -> 250 | R44: =SAISIE!$D$22/12 -> 250 | S44: =SAISIE!$D$22/12 -> 250 | T44: =SAISIE!$D$22/12 -> 250 | U44: =SAISIE!$D$22/12 -> 250 | V44: =SAISIE!$D$22/12 -> 250 | W44: =SAISIE!$D$22/12 -> 250 | X44: =SAISIE!$D$22/12 -> 250 | ... AB44: =SAISIE!$D$22/12 -> 250 | AC44: =SAISIE!E22 -> 5000 | AD44: =SAISIE!$E$22/12 -> 416.66667 | AE44: =SAISIE!$E$22/12 -> 416.66667 | AF44: =SAISIE!$E$22/12 -> 416.66667 | AG44: =SAISIE!$E$22/12 -> 416.66667 | AH44: =SAISIE!$E$22/12 -> 416.66667 | AI44: =SAISIE!$E$22/12 -> 416.66667 | AJ44: =SAISIE!$E$22/12 -> 416.66667 | AK44: =SAISIE!$E$22/12 -> 416.66667 | ... AO44: =SAISIE!$E$22/12 -> 416.66667
B45: Loyers crédit-bail | C45: =SAISIE!C23 -> 0 | D45: =SAISIE!$C$23/12 -> 0 | E45: =SAISIE!$C$23/12 -> 0 | F45: =SAISIE!$C$23/12 -> 0 | G45: =SAISIE!$C$23/12 -> 0 | H45: =SAISIE!$C$23/12 -> 0 | I45: =SAISIE!$C$23/12 -> 0 | J45: =SAISIE!$C$23/12 -> 0 | K45: =SAISIE!$C$23/12 -> 0 | ... O45: =SAISIE!$C$23/12 -> 0 | P45: =SAISIE!D23 -> 0 | Q45: =SAISIE!$D$23/12 -> 0 | R45: =SAISIE!$D$23/12 -> 0 | S45: =SAISIE!$D$23/12 -> 0 | T45: =SAISIE!$D$23/12 -> 0 | U45: =SAISIE!$D$23/12 -> 0 | V45: =SAISIE!$D$23/12 -> 0 | W45: =SAISIE!$D$23/12 -> 0 | X45: =SAISIE!$D$23/12 -> 0 | ... AB45: =SAISIE!$D$23/12 -> 0 | AC45: =SAISIE!E23 -> 0 | AD45: =SAISIE!$E$23/12 -> 0 | AE45: =SAISIE!$E$23/12 -> 0 | AF45: =SAISIE!$E$23/12 -> 0 | AG45: =SAISIE!$E$23/12 -> 0 | AH45: =SAISIE!$E$23/12 -> 0 | AI45: =SAISIE!$E$23/12 -> 0 | AJ45: =SAISIE!$E$23/12 -> 0 | AK45: =SAISIE!$E$23/12 -> 0 | ... AO45: =SAISIE!$E$23/12 -> 0
B46: Location bureaux coworking | C46: =SAISIE!C24 -> 1200 | D46: =SAISIE!$C$24/12 -> 100 | E46: =SAISIE!$C$24/12 -> 100 | F46: =SAISIE!$C$24/12 -> 100 | G46: =SAISIE!$C$24/12 -> 100 | H46: =SAISIE!$C$24/12 -> 100 | I46: =SAISIE!$C$24/12 -> 100 | J46: =SAISIE!$C$24/12 -> 100 | K46: =SAISIE!$C$24/12 -> 100 | ... O46: =SAISIE!$C$24/12 -> 100 | P46: =SAISIE!D24 -> 1200 | Q46: =SAISIE!$D$24/12 -> 100 | R46: =SAISIE!$D$24/12 -> 100 | S46: =SAISIE!$D$24/12 -> 100 | T46: =SAISIE!$D$24/12 -> 100 | U46: =SAISIE!$D$24/12 -> 100 | V46: =SAISIE!$D$24/12 -> 100 | W46: =SAISIE!$D$24/12 -> 100 | X46: =SAISIE!$D$24/12 -> 100 | ... AB46: =SAISIE!$D$24/12 -> 100 | AC46: =SAISIE!E24 -> 1200 | AD46: =SAISIE!$E$24/12 -> 100 | AE46: =SAISIE!$E$24/12 -> 100 | AF46: =SAISIE!$E$24/12 -> 100 | AG46: =SAISIE!$E$24/12 -> 100 | AH46: =SAISIE!$E$24/12 -> 100 | AI46: =SAISIE!$E$24/12 -> 100 | AJ46: =SAISIE!$E$24/12 -> 100 | AK46: =SAISIE!$E$24/12 -> 100 | ... AO46: =SAISIE!$E$24/12 -> 100
B47: Frais de production | C47: =SAISIE!C25 -> 600 | D47: =SAISIE!$C$25/12 -> 50 | E47: =SAISIE!$C$25/12 -> 50 | F47: =SAISIE!$C$25/12 -> 50 | G47: =SAISIE!$C$25/12 -> 50 | H47: =SAISIE!$C$25/12 -> 50 | I47: =SAISIE!$C$25/12 -> 50 | J47: =SAISIE!$C$25/12 -> 50 | K47: =SAISIE!$C$25/12 -> 50 | ... O47: =SAISIE!$C$25/12 -> 50 | P47: =SAISIE!D25 -> 600 | Q47: =SAISIE!$D$25/12 -> 50 | R47: =SAISIE!$D$25/12 -> 50 | S47: =SAISIE!$D$25/12 -> 50 | T47: =SAISIE!$D$25/12 -> 50 | U47: =SAISIE!$D$25/12 -> 50 | V47: =SAISIE!$D$25/12 -> 50 | W47: =SAISIE!$D$25/12 -> 50 | X47: =SAISIE!$D$25/12 -> 50 | ... AB47: =SAISIE!$D$25/12 -> 50 | AC47: =SAISIE!E25 -> 600 | AD47: =SAISIE!$E$25/12 -> 50 | AE47: =SAISIE!$E$25/12 -> 50 | AF47: =SAISIE!$E$25/12 -> 50 | AG47: =SAISIE!$E$25/12 -> 50 | AH47: =SAISIE!$E$25/12 -> 50 | AI47: =SAISIE!$E$25/12 -> 50 | AJ47: =SAISIE!$E$25/12 -> 50 | AK47: =SAISIE!$E$25/12 -> 50 | ... AO47: =SAISIE!$E$25/12 -> 50
B48: Honoraires | C48: =SAISIE!C26 -> 2400 | D48: =SAISIE!$C$26/12 -> 200 | E48: =SAISIE!$C$26/12 -> 200 | F48: =SAISIE!$C$26/12 -> 200 | G48: =SAISIE!$C$26/12 -> 200 | H48: =SAISIE!$C$26/12 -> 200 | I48: =SAISIE!$C$26/12 -> 200 | J48: =SAISIE!$C$26/12 -> 200 | K48: =SAISIE!$C$26/12 -> 200 | ... O48: =SAISIE!$C$26/12 -> 200 | P48: =SAISIE!D26 -> 2400 | Q48: =SAISIE!$D$26/12 -> 200 | R48: =SAISIE!$D$26/12 -> 200 | S48: =SAISIE!$D$26/12 -> 200 | T48: =SAISIE!$D$26/12 -> 200 | U48: =SAISIE!$D$26/12 -> 200 | V48: =SAISIE!$D$26/12 -> 200 | W48: =SAISIE!$D$26/12 -> 200 | X48: =SAISIE!$D$26/12 -> 200 | ... AB48: =SAISIE!$D$26/12 -> 200 | AC48: =SAISIE!E26 -> 2400 | AD48: =SAISIE!$E$26/12 -> 200 | AE48: =SAISIE!$E$26/12 -> 200 | AF48: =SAISIE!$E$26/12 -> 200 | AG48: =SAISIE!$E$26/12 -> 200 | AH48: =SAISIE!$E$26/12 -> 200 | AI48: =SAISIE!$E$26/12 -> 200 | AJ48: =SAISIE!$E$26/12 -> 200 | AK48: =SAISIE!$E$26/12 -> 200 | ... AO48: =SAISIE!$E$26/12 -> 200
B49: Publicité | C49: =SAISIE!C27 -> 600 | D49: =SAISIE!$C$27/12 -> 50 | E49: =SAISIE!$C$27/12 -> 50 | F49: =SAISIE!$C$27/12 -> 50 | G49: =SAISIE!$C$27/12 -> 50 | H49: =SAISIE!$C$27/12 -> 50 | I49: =SAISIE!$C$27/12 -> 50 | J49: =SAISIE!$C$27/12 -> 50 | K49: =SAISIE!$C$27/12 -> 50 | ... O49: =SAISIE!$C$27/12 -> 50 | P49: =SAISIE!D27 -> 600 | Q49: =SAISIE!$D$27/12 -> 50 | R49: =SAISIE!$D$27/12 -> 50 | S49: =SAISIE!$D$27/12 -> 50 | T49: =SAISIE!$D$27/12 -> 50 | U49: =SAISIE!$D$27/12 -> 50 | V49: =SAISIE!$D$27/12 -> 50 | W49: =SAISIE!$D$27/12 -> 50 | X49: =SAISIE!$D$27/12 -> 50 | ... AB49: =SAISIE!$D$27/12 -> 50 | AC49: =SAISIE!E27 -> 600 | AD49: =SAISIE!$E$27/12 -> 50 | AE49: =SAISIE!$E$27/12 -> 50 | AF49: =SAISIE!$E$27/12 -> 50 | AG49: =SAISIE!$E$27/12 -> 50 | AH49: =SAISIE!$E$27/12 -> 50 | AI49: =SAISIE!$E$27/12 -> 50 | AJ49: =SAISIE!$E$27/12 -> 50 | AK49: =SAISIE!$E$27/12 -> 50 | ... AO49: =SAISIE!$E$27/12 -> 50
B50: Frais de déplacement | C50: =SAISIE!C28 -> 1200 | D50: =SAISIE!$C$28/12 -> 100 | E50: =SAISIE!$C$28/12 -> 100 | F50: =SAISIE!$C$28/12 -> 100 | G50: =SAISIE!$C$28/12 -> 100 | H50: =SAISIE!$C$28/12 -> 100 | I50: =SAISIE!$C$28/12 -> 100 | J50: =SAISIE!$C$28/12 -> 100 | K50: =SAISIE!$C$28/12 -> 100 | ... O50: =SAISIE!$C$28/12 -> 100 | P50: =SAISIE!D28 -> 1200 | Q50: =SAISIE!$D$28/12 -> 100 | R50: =SAISIE!$D$28/12 -> 100 | S50: =SAISIE!$D$28/12 -> 100 | T50: =SAISIE!$D$28/12 -> 100 | U50: =SAISIE!$D$28/12 -> 100 | V50: =SAISIE!$D$28/12 -> 100 | W50: =SAISIE!$D$28/12 -> 100 | X50: =SAISIE!$D$28/12 -> 100 | ... AB50: =SAISIE!$D$28/12 -> 100 | AC50: =SAISIE!E28 -> 1200 | AD50: =SAISIE!$E$28/12 -> 100 | AE50: =SAISIE!$E$28/12 -> 100 | AF50: =SAISIE!$E$28/12 -> 100 | AG50: =SAISIE!$E$28/12 -> 100 | AH50: =SAISIE!$E$28/12 -> 100 | AI50: =SAISIE!$E$28/12 -> 100 | AJ50: =SAISIE!$E$28/12 -> 100 | AK50: =SAISIE!$E$28/12 -> 100 | ... AO50: =SAISIE!$E$28/12 -> 100
B51: Frais missions | C51: =SAISIE!C29 -> 1800 | D51: =SAISIE!$C$29/12 -> 150 | E51: =SAISIE!$C$29/12 -> 150 | F51: =SAISIE!$C$29/12 -> 150 | G51: =SAISIE!$C$29/12 -> 150 | H51: =SAISIE!$C$29/12 -> 150 | I51: =SAISIE!$C$29/12 -> 150 | J51: =SAISIE!$C$29/12 -> 150 | K51: =SAISIE!$C$29/12 -> 150 | ... O51: =SAISIE!$C$29/12 -> 150 | P51: =SAISIE!D29 -> 1800 | Q51: =SAISIE!$D$29/12 -> 150 | R51: =SAISIE!$D$29/12 -> 150 | S51: =SAISIE!$D$29/12 -> 150 | T51: =SAISIE!$D$29/12 -> 150 | U51: =SAISIE!$D$29/12 -> 150 | V51: =SAISIE!$D$29/12 -> 150 | W51: =SAISIE!$D$29/12 -> 150 | X51: =SAISIE!$D$29/12 -> 150 | ... AB51: =SAISIE!$D$29/12 -> 150 | AC51: =SAISIE!E29 -> 1800 | AD51: =SAISIE!$E$29/12 -> 150 | AE51: =SAISIE!$E$29/12 -> 150 | AF51: =SAISIE!$E$29/12 -> 150 | AG51: =SAISIE!$E$29/12 -> 150 | AH51: =SAISIE!$E$29/12 -> 150 | AI51: =SAISIE!$E$29/12 -> 150 | AJ51: =SAISIE!$E$29/12 -> 150 | AK51: =SAISIE!$E$29/12 -> 150 | ... AO51: =SAISIE!$E$29/12 -> 150
B52: Divers | C52: =SAISIE!C30 -> 1200 | D52: =SAISIE!$C$30/12 -> 100 | E52: =SAISIE!$C$30/12 -> 100 | F52: =SAISIE!$C$30/12 -> 100 | G52: =SAISIE!$C$30/12 -> 100 | H52: =SAISIE!$C$30/12 -> 100 | I52: =SAISIE!$C$30/12 -> 100 | J52: =SAISIE!$C$30/12 -> 100 | K52: =SAISIE!$C$30/12 -> 100 | ... O52: =SAISIE!$C$30/12 -> 100 | P52: =SAISIE!D30 -> 1200 | Q52: =SAISIE!$D$30/12 -> 100 | R52: =SAISIE!$D$30/12 -> 100 | S52: =SAISIE!$D$30/12 -> 100 | T52: =SAISIE!$D$30/12 -> 100 | U52: =SAISIE!$D$30/12 -> 100 | V52: =SAISIE!$D$30/12 -> 100 | W52: =SAISIE!$D$30/12 -> 100 | X52: =SAISIE!$D$30/12 -> 100 | ... AB52: =SAISIE!$D$30/12 -> 100 | AC52: =SAISIE!E30 -> 1200 | AD52: =SAISIE!$E$30/12 -> 100 | AE52: =SAISIE!$E$30/12 -> 100 | AF52: =SAISIE!$E$30/12 -> 100 | AG52: =SAISIE!$E$30/12 -> 100 | AH52: =SAISIE!$E$30/12 -> 100 | AI52: =SAISIE!$E$30/12 -> 100 | AJ52: =SAISIE!$E$30/12 -> 100 | AK52: =SAISIE!$E$30/12 -> 100 | ... AO52: =SAISIE!$E$30/12 -> 100
B53: Charges externes | C53: =SUM(C43:C52) -> 11500 | D53: =SUM(D43:D52) -> 958.33333 | E53: =SUM(E43:E52) -> 958.33333 | F53: =SUM(F43:F52) -> 958.33333 | G53: =SUM(G43:G52) -> 958.33333 | H53: =SUM(H43:H52) -> 958.33333 | I53: =SUM(I43:I52) -> 958.33333 | J53: =SUM(J43:J52) -> 958.33333 | ... AO53: =SUM(AO43:AO52) -> 1208.3333
B55: Rémunération EC | C55: =SAISIE!C34 -> 25000 | D55: =SAISIE!$C$34/12 -> 2083.3333 | E55: =SAISIE!$C$34/12 -> 2083.3333 | F55: =SAISIE!$C$34/12 -> 2083.3333 | G55: =SAISIE!$C$34/12 -> 2083.3333 | H55: =SAISIE!$C$34/12 -> 2083.3333 | I55: =SAISIE!$C$34/12 -> 2083.3333 | J55: =SAISIE!$C$34/12 -> 2083.3333 | K55: =SAISIE!$C$34/12 -> 2083.3333 | ... O55: =SAISIE!$C$34/12 -> 2083.3333 | P55: =SAISIE!D34 -> 45000 | Q55: =SAISIE!$D$34/12 -> 3750 | R55: =SAISIE!$D$34/12 -> 3750 | S55: =SAISIE!$D$34/12 -> 3750 | T55: =SAISIE!$D$34/12 -> 3750 | U55: =SAISIE!$D$34/12 -> 3750 | V55: =SAISIE!$D$34/12 -> 3750 | W55: =SAISIE!$D$34/12 -> 3750 | X55: =SAISIE!$D$34/12 -> 3750 | ... AB55: =SAISIE!$D$34/12 -> 3750 | AC55: =SAISIE!E34 -> 80000 | AD55: =SAISIE!$E$34/12 -> 6666.6667 | AE55: =SAISIE!$E$34/12 -> 6666.6667 | AF55: =SAISIE!$E$34/12 -> 6666.6667 | AG55: =SAISIE!$E$34/12 -> 6666.6667 | AH55: =SAISIE!$E$34/12 -> 6666.6667 | AI55: =SAISIE!$E$34/12 -> 6666.6667 | AJ55: =SAISIE!$E$34/12 -> 6666.6667 | AK55: =SAISIE!$E$34/12 -> 6666.6667 | ... AO55: =SAISIE!$E$34/12 -> 6666.6667
B56: Impôts et taxes | C56: =SAISIE!C57 -> 600 | D56: =SAISIE!$C$57/12 -> 50 | E56: =SAISIE!$C$57/12 -> 50 | F56: =SAISIE!$C$57/12 -> 50 | G56: =SAISIE!$C$57/12 -> 50 | H56: =SAISIE!$C$57/12 -> 50 | I56: =SAISIE!$C$57/12 -> 50 | J56: =SAISIE!$C$57/12 -> 50 | K56: =SAISIE!$C$57/12 -> 50 | ... O56: =SAISIE!$C$57/12 -> 50 | P56: =SAISIE!D57 -> 600 | Q56: =SAISIE!$D$57/12 -> 50 | R56: =SAISIE!$D$57/12 -> 50 | S56: =SAISIE!$D$57/12 -> 50 | T56: =SAISIE!$D$57/12 -> 50 | U56: =SAISIE!$D$57/12 -> 50 | V56: =SAISIE!$D$57/12 -> 50 | W56: =SAISIE!$D$57/12 -> 50 | X56: =SAISIE!$D$57/12 -> 50 | ... AB56: =SAISIE!$D$57/12 -> 50 | AC56: =SAISIE!E57 -> 600 | AD56: =SAISIE!$E$57/12 -> 50 | AE56: =SAISIE!$E$57/12 -> 50 | AF56: =SAISIE!$E$57/12 -> 50 | AG56: =SAISIE!$E$57/12 -> 50 | AH56: =SAISIE!$E$57/12 -> 50 | AI56: =SAISIE!$E$57/12 -> 50 | AJ56: =SAISIE!$E$57/12 -> 50 | AK56: =SAISIE!$E$57/12 -> 50 | ... AO56: =SAISIE!$E$57/12 -> 50
B57: Salaires | C57: =SUM(D57:O57) -> 30000 | D57: =+Personnel!F17 -> 2500 | E57: =Personnel!G17 -> 2500 | F57: =Personnel!H17 -> 2500 | G57: =Personnel!I17 -> 2500 | H57: =Personnel!J17 -> 2500 | I57: =Personnel!K17 -> 2500 | J57: =Personnel!L17 -> 2500 | K57: =Personnel!M17 -> 2500 | L57: =Personnel!N17 -> 2500 | ... O57: =Personnel!Q17 -> 2500 | P57: =SUM(Q57:AB57) -> 74400 | Q57: =Personnel!U17 -> 6200 | R57: =Personnel!V17 -> 6200 | S57: =Personnel!W17 -> 6200 | T57: =Personnel!X17 -> 6200 | U57: =Personnel!Y17 -> 6200 | V57: =Personnel!Z17 -> 6200 | W57: =Personnel!AA17 -> 6200 | X57: =Personnel!AB17 -> 6200 | ... AB57: =Personnel!AF17 -> 6200 | AC57: =SUM(AD57:AO57) -> 128400 | AD57: =Personnel!AJ17 -> 10700 | AE57: =Personnel!AK17 -> 10700 | AF57: =Personnel!AL17 -> 10700 | AG57: =Personnel!AM17 -> 10700 | AH57: =Personnel!AN17 -> 10700 | AI57: =Personnel!AO17 -> 10700 | AJ57: =Personnel!AP17 -> 10700 | AK57: =Personnel!AQ17 -> 10700 | ... AO57: =Personnel!AU17 -> 10700
B58: Charges sociales | C58: =SUM(D58:O58) -> 23850 | D58: =D57*42%+SAISIE!$C$34/12*SAISIE!$C$61 -> 1987.5 | E58: =E57*42%+SAISIE!$C$34/12*SAISIE!$C$61 -> 1987.5 | F58: =F57*42%+SAISIE!$C$34/12*SAISIE!$C$61 -> 1987.5 | G58: =G57*42%+SAISIE!$C$34/12*SAISIE!$C$61 -> 1987.5 | H58: =H57*42%+SAISIE!$C$34/12*SAISIE!$C$61 -> 1987.5 | I58: =I57*42%+SAISIE!$C$34/12*SAISIE!$C$61 -> 1987.5 | J58: =J57*42%+SAISIE!$C$34/12*SAISIE!$C$61 -> 1987.5 | K58: =K57*42%+SAISIE!$C$34/12*SAISIE!$C$61 -> 1987.5 | ... O58: =O57*42%+SAISIE!$C$34/12*SAISIE!$C$61 -> 1987.5 | P58: =SUM(Q58:AB58) -> 51498 | Q58: =Q57*42%+SAISIE!$D$34/12*SAISIE!$D$61 -> 4291.5 | R58: =R57*42%+SAISIE!$D$34/12*SAISIE!$D$61 -> 4291.5 | S58: =S57*42%+SAISIE!$D$34/12*SAISIE!$D$61 -> 4291.5 | T58: =T57*42%+SAISIE!$D$34/12*SAISIE!$D$61 -> 4291.5 | U58: =U57*42%+SAISIE!$D$34/12*SAISIE!$D$61 -> 4291.5 | V58: =V57*42%+SAISIE!$D$34/12*SAISIE!$D$61 -> 4291.5 | W58: =W57*42%+SAISIE!$D$34/12*SAISIE!$D$61 -> 4291.5 | X58: =X57*42%+SAISIE!$D$34/12*SAISIE!$D$61 -> 4291.5 | ... AB58: =AB57*42%+SAISIE!$D$34/12*SAISIE!$D$61 -> 4291.5 | AC58: =SUM(AD58:AO58) -> 89928 | AD58: =AD57*42%+SAISIE!$E$34/12*SAISIE!$E$61 -> 7494 | AE58: =AE57*42%+SAISIE!$E$34/12*SAISIE!$E$61 -> 7494 | AF58: =AF57*42%+SAISIE!$E$34/12*SAISIE!$E$61 -> 7494 | AG58: =AG57*42%+SAISIE!$E$34/12*SAISIE!$E$61 -> 7494 | AH58: =AH57*42%+SAISIE!$E$34/12*SAISIE!$E$61 -> 7494 | AI58: =AI57*42%+SAISIE!$E$34/12*SAISIE!$E$61 -> 7494 | AJ58: =AJ57*42%+SAISIE!$E$34/12*SAISIE!$E$61 -> 7494 | AK58: =AK57*42%+SAISIE!$E$34/12*SAISIE!$E$61 -> 7494 | ... AO58: =AO57*42%+SAISIE!$E$34/12*SAISIE!$E$61 -> 7494
B59: Dotation amortissements | C59: =SUM(D59:O59) -> 1833.3333 | D59: =D87 -> 152.77778 | E59: =E87 -> 152.77778 | F59: =F87 -> 152.77778 | G59: =G87 -> 152.77778 | H59: =H87 -> 152.77778 | I59: =I87 -> 152.77778 | J59: =J87 -> 152.77778 | K59: =K87 -> 152.77778 | ... O59: =O87 -> 152.77778 | P59: =SUM(Q59:AB59) -> 666.66667 | Q59: =Q87 -> 55.555556 | R59: =R87 -> 55.555556 | S59: =S87 -> 55.555556 | T59: =T87 -> 55.555556 | U59: =U87 -> 55.555556 | V59: =V87 -> 55.555556 | W59: =W87 -> 55.555556 | X59: =X87 -> 55.555556 | ... AB59: =AB87 -> 55.555556 | AC59: =SUM(AD59:AO59) -> 833.33333 | AD59: =AD87 -> 69.444444 | AE59: =AE87 -> 69.444444 | AF59: =AF87 -> 69.444444 | AG59: =AG87 -> 69.444444 | AH59: =AH87 -> 69.444444 | AI59: =AI87 -> 69.444444 | AJ59: =AJ87 -> 69.444444 | AK59: =AK87 -> 69.444444 | ... AO59: =AO87 -> 69.444444
B60: Total des charges | C60: =SUM(C53,C55:C59)+C42 -> 99983.333 | D60: =SUM(D53,D55:D59)+D42 -> 8331.9444 | E60: =SUM(E53,E55:E59)+E42 -> 8331.9444 | F60: =SUM(F53,F55:F59)+F42 -> 8331.9444 | G60: =SUM(G53,G55:G59)+G42 -> 8331.9444 | H60: =SUM(H53,H55:H59)+H42 -> 8331.9444 | I60: =SUM(I53,I55:I59)+I42 -> 8331.9444 | J60: =SUM(J53,J55:J59)+J42 -> 8331.9444 | ... AO60: =SUM(AO53,AO55:AO59)+AO42 -> 26788.444
B62: Résultat d'exploitation | C62: =C36+C37-C60 -> 13016.667 | D62: =D36+D37-D60 -> 1084.7222 | E62: =E36-E60 -> 1084.7222 | F62: =F36-F60 -> 1084.7222 | G62: =G36-G60 -> 1084.7222 | H62: =H36-H60 -> 1084.7222 | I62: =I36-I60 -> 1084.7222 | J62: =J36-J60 -> 1084.7222 | K62: =K36-K60 -> 1084.7222 | L62: =L36-L60 -> 1084.7222 | ... AO62: =AO36-AO60 -> 7961.5556
B64: Frais financiers | C64: =SUM(D64:O64) -> 740.67657 | D64: =D171+D185+D199 -> 66.666667 | E64: =E171+E185+E199 -> 65.777778 | F64: =F171+F185+F199 -> 64.885926 | G64: =G171+G185+G199 -> 63.991101 | H64: =H171+H185+H199 -> 63.093294 | I64: =I171+I185+I199 -> 62.192494 | J64: =J171+J185+J199 -> 61.288691 | K64: =K171+K185+K199 -> 60.381875 | ... O64: =O171+O185+O199 -> 56.724285 | P64: =SUM(Q64:AB64) -> 607.8867 | Q64: =Q171+Q185+Q199 -> 55.802255 | R64: =R171+R185+R199 -> 54.877152 | S64: =S171+S185+S199 -> 53.948964 | T64: =T171+T185+T199 -> 53.017683 | U64: =U171+U185+U199 -> 52.083298 | V64: =V171+V185+V199 -> 51.145798 | W64: =W171+W185+W199 -> 50.205172 | X64: =X171+X185+X199 -> 49.261412 | ... AB64: =AB171+AB185+AB199 -> 45.454806 | AC64: =SUM(AD64:AO64) -> 469.68677 | AD64: =AD171+AD185+AD199 -> 44.495211 | AE64: =AE171+AE185+AE199 -> 43.532417 | AF64: =AF171+AF185+AF199 -> 42.566414 | AG64: =AG171+AG185+AG199 -> 41.597191 | AH64: =AH171+AH185+AH199 -> 40.624737 | AI64: =AI171+AI185+AI199 -> 39.649042 | AJ64: =AJ171+AJ185+AJ199 -> 38.670094 | AK64: =AK171+AK185+AK199 -> 37.687883 | ... AO64: =AO171+AO185+AO199 -> 33.726191
B66: Résultat courant | C66: =C62-C64 -> 12275.99 | D66: =D62-D64 -> 1018.0556 | E66: =E62-E64 -> 1018.9444 | F66: =F62-F64 -> 1019.8363 | G66: =G62-G64 -> 1020.7311 | H66: =H62-H64 -> 1021.6289 | I66: =I62-I64 -> 1022.5297 | J66: =J62-J64 -> 1023.4335 | ... AO66: =AO62-AO64 -> 7927.8294
B67: Taux rentabilité avant IS | C67: =IF(C$36=0,"NA",C66/C$36) -> 0.10863708 | D67: =IF(D$36=0,"NA",D66/D$36) -> 0.10811209 | E67: =IF(E$36=0,"NA",E66/E$36) -> 0.10820649 | F67: =IF(F$36=0,"NA",F66/F$36) -> 0.1083012 | G67: =IF(G$36=0,"NA",G66/G$36) -> 0.10839623 | H67: =IF(H$36=0,"NA",H66/H$36) -> 0.10849157 | I67: =IF(I$36=0,"NA",I66/I$36) -> 0.10858723 | J67: =IF(J$36=0,"NA",J66/J$36) -> 0.10868321 | ... AO67: =IF(AO$36=0,"NA",AO66/AO$36) -> 0.22813897
B69: Résultat exceptionnel | C69: =SUM(D69:O69) -> 0 | D69: =-(D89+D91) -> 0 | E69: =-(E89+E91) -> 0 | F69: =-(F89+F91) -> 0 | G69: =-(G89+G91) -> 0 | H69: =-(H89+H91) -> 0 | I69: =-(I89+I91) -> 0 | J69: =-(J89+J91) -> 0 | K69: =-(K89+K91) -> 0 | ... O69: =-(O89+O91) -> 0 | P69: =SUM(Q69:AB69) -> 0 | Q69: =-(Q89+Q91) -> 0 | R69: =-(R89+R91) -> 0 | S69: =-(S89+S91) -> 0 | T69: =-(T89+T91) -> 0 | U69: =-(U89+U91) -> 0 | V69: =-(V89+V91) -> 0 | W69: =-(W89+W91) -> 0 | X69: =-(X89+X91) -> 0 | ... AB69: =-(AB89+AB91) -> 0 | AC69: =SUM(AD69:AO69) -> 0 | AD69: =-(AD89+AD91) -> 0 | AE69: =-(AE89+AE91) -> 0 | AF69: =-(AF89+AF91) -> 0 | AG69: =-(AG89+AG91) -> 0 | AH69: =-(AH89+AH91) -> 0 | AI69: =-(AI89+AI91) -> 0 | AJ69: =-(AJ89+AJ91) -> 0 | AK69: =-(AK89+AK91) -> 0 | ... AO69: =-(AO89+AO91) -> 0
B70: Impôt sur les bénéfices | C70: =C152 -> 1841.3985 | D70: =D66/$C$66*$C$70 -> 152.70833 | E70: =E66/$C$66*$C$70 -> 152.84167 | F70: =F66/$C$66*$C$70 -> 152.97544 | G70: =G66/$C$66*$C$70 -> 153.10967 | H70: =H66/$C$66*$C$70 -> 153.24434 | I70: =I66/$C$66*$C$70 -> 153.37946 | J70: =J66/$C$66*$C$70 -> 153.51503 | K70: =K66/$C$66*$C$70 -> 153.65105 | ... O70: =O66/$C$66*$C$70 -> 154.19969 | P70: =P152 -> 9631.8617 | Q70: =$P$70*Q66/$P$66 -> 801.76267 | R70: =$P$70*R66/$P$66 -> 801.92314 | S70: =$P$70*S66/$P$66 -> 802.08415 | T70: =$P$70*T66/$P$66 -> 802.24569 | U70: =$P$70*U66/$P$66 -> 802.40777 | V70: =$P$70*V66/$P$66 -> 802.57039 | W70: =$P$70*W66/$P$66 -> 802.73355 | X70: =$P$70*X66/$P$66 -> 802.89726 | ... AB70: =$P$70*AB66/$P$66 -> 803.55756 | AC70: =AC152 -> 19517.245 | AD70: =AD66/$AC$66*$AC$70 -> 1625.3378 | AE70: =AE66/$AC$66*$AC$70 -> 1625.5355 | AF70: =AF66/$AC$66*$AC$70 -> 1625.7338 | AG70: =AG66/$AC$66*$AC$70 -> 1625.9327 | AH70: =AH66/$AC$66*$AC$70 -> 1626.1324 | AI70: =AI66/$AC$66*$AC$70 -> 1626.3327 | AJ70: =AJ66/$AC$66*$AC$70 -> 1626.5337 | AK70: =AK66/$AC$66*$AC$70 -> 1626.7353 | ... AO70: =AO66/$AC$66*$AC$70 -> 1627.5486
B72: Résultat net | C72: =SUM(D72:O72) -> 10434.592 | D72: =D66-D69-D70 -> 865.34722 | E72: =E66-E69-E70 -> 866.10278 | F72: =F66-F69-F70 -> 866.86085 | G72: =G66-G69-G70 -> 867.62145 | H72: =H66-H69-H70 -> 868.38459 | I72: =I66-I69-I70 -> 869.15027 | J72: =J66-J69-J70 -> 869.9185 | K72: =K66-K69-K70 -> 870.68929 | ... O72: =O66-O69-O70 -> 873.79825 | P72: =SUM(Q72:AB72) -> 45895.585 | Q72: =Q66-Q69-Q70 -> 3820.3795 | R72: =R66-R69-R70 -> 3821.1441 | S72: =S66-S69-S70 -> 3821.9113 | T72: =T66-T69-T70 -> 3822.6811 | U72: =U66-U69-U70 -> 3823.4534 | V72: =V66-V69-V70 -> 3824.2283 | W72: =W66-W69-W70 -> 3825.0057 | X72: =X66-X69-X70 -> 3825.7858 | ... AB72: =AB66-AB69-AB70 -> 3828.9321 | AC72: =SUM(AD72:AO72) -> 75551.735 | AD72: =AD66-AD69-AD70 -> 6291.7225 | AE72: =AE66-AE69-AE70 -> 6292.4877 | AF72: =AF66-AF69-AF70 -> 6293.2554 | AG72: =AG66-AG69-AG70 -> 6294.0256 | AH72: =AH66-AH69-AH70 -> 6294.7984 | AI72: =AI66-AI69-AI70 -> 6295.5738 | AJ72: =AJ66-AJ69-AJ70 -> 6296.3518 | AK72: =AK66-AK69-AK70 -> 6297.1324 | ... AO72: =AO66-AO69-AO70 -> 6300.2807
B73: Taux de rentabilité net | C73: =IF(C$36=0,"NA",C72/C$36) -> 0.092341518 | D73: =IF(D$36=0,"NA",D72/D$36) -> 0.09189528 | E73: =IF(E$36=0,"NA",E72/E$36) -> 0.091975516 | F73: =IF(F$36=0,"NA",F72/F$36) -> 0.09205602 | G73: =IF(G$36=0,"NA",G72/G$36) -> 0.092136791 | H73: =IF(H$36=0,"NA",H72/H$36) -> 0.092217832 | I73: =IF(I$36=0,"NA",I72/I$36) -> 0.092299144 | J73: =IF(J$36=0,"NA",J72/J$36) -> 0.092380726 | ... AO73: =IF(AO$36=0,"NA",AO72/AO$36) -> 0.18130304
B75: 3) Budget d'investissement
D77: 46053 | E77: 46081 | F77: 46112 | G77: 46142 | H77: 46173 | I77: 46203 | J77: 46234 | K77: 46265 | L77: 46295 | M77: 46326 | N77: 46356 | O77: 46387 | Q77: 46418 | R77: 46446 | S77: 46477 | T77: 46507 | U77: 46538 | V77: 46568 | W77: 46599 | X77: 46630 | Y77: 46660 | Z77: 46691 | AA77: 46721 | AB77: 46752 | AD77: 46783 | AE77: 46811 | AF77: 46839 | AG77: 46867 | AH77: 46895 | AI77: 46923 | AJ77: 46951 | AK77: 46979 | AL77: 47007 | AM77: 47035 | AN77: 47063 | AO77: 47091
C78: 180000 | P78: 96000 | AC78: 160000
B79: R&D | C79: =SAISIE!C41 -> 0 | D79: =SAISIE!$C$41/12 -> 0 | E79: =SAISIE!$C$41/12 -> 0 | F79: =SAISIE!$C$41/12 -> 0 | G79: =SAISIE!$C$41/12 -> 0 | H79: =SAISIE!$C$41/12 -> 0 | I79: =SAISIE!$C$41/12 -> 0 | J79: =SAISIE!$C$41/12 -> 0 | K79: =SAISIE!$C$41/12 -> 0 | ... O79: =SAISIE!$C$41/12 -> 0 | P79: =SAISIE!D41 -> 0 | Q79: =SAISIE!$D$41/12 -> 0 | R79: =SAISIE!$D$41/12 -> 0 | S79: =SAISIE!$D$41/12 -> 0 | T79: =SAISIE!$D$41/12 -> 0 | U79: =SAISIE!$D$41/12 -> 0 | V79: =SAISIE!$D$41/12 -> 0 | W79: =SAISIE!$D$41/12 -> 0 | X79: =SAISIE!$D$41/12 -> 0 | ... AB79: =SAISIE!$D$41/12 -> 0 | AC79: =SAISIE!E41 -> 0 | AD79: =SAISIE!$E$41/12 -> 0 | AE79: =SAISIE!$E$41/12 -> 0 | AF79: =SAISIE!$E$41/12 -> 0 | AG79: =SAISIE!$E$41/12 -> 0 | AH79: =SAISIE!$E$41/12 -> 0 | AI79: =SAISIE!$E$41/12 -> 0 | AJ79: =SAISIE!$E$41/12 -> 0 | AK79: =SAISIE!$E$41/12 -> 0 | ... AO79: =SAISIE!$E$41/12 -> 0
B80: Matériel de transport | C80: =SAISIE!C42 -> 0 | D80: =SAISIE!$C$42/12 -> 0 | E80: =SAISIE!$C$42/12 -> 0 | F80: =SAISIE!$C$42/12 -> 0 | G80: =SAISIE!$C$42/12 -> 0 | H80: =SAISIE!$C$42/12 -> 0 | I80: =SAISIE!$C$42/12 -> 0 | J80: =SAISIE!$C$42/12 -> 0 | K80: =SAISIE!$C$42/12 -> 0 | ... O80: =SAISIE!$C$42/12 -> 0 | P80: =SAISIE!D42 -> 0 | Q80: =SAISIE!$D$42/12 -> 0 | R80: =SAISIE!$D$42/12 -> 0 | S80: =SAISIE!$D$42/12 -> 0 | T80: =SAISIE!$D$42/12 -> 0 | U80: =SAISIE!$D$42/12 -> 0 | V80: =SAISIE!$D$42/12 -> 0 | W80: =SAISIE!$D$42/12 -> 0 | X80: =SAISIE!$D$42/12 -> 0 | ... AB80: =SAISIE!$D$42/12 -> 0 | AC80: =SAISIE!E42 -> 0 | AD80: =SAISIE!$E$42/12 -> 0 | AE80: =SAISIE!$E$42/12 -> 0 | AF80: =SAISIE!$E$42/12 -> 0 | AG80: =SAISIE!$E$42/12 -> 0 | AH80: =SAISIE!$E$42/12 -> 0 | AI80: =SAISIE!$E$42/12 -> 0 | AJ80: =SAISIE!$E$42/12 -> 0 | AK80: =SAISIE!$E$42/12 -> 0 | ... AO80: =SAISIE!$E$42/12 -> 0
B81: Matériel & outillage | C81: =SAISIE!C43 -> 1500 | D81: =SAISIE!$C$43/12 -> 125 | E81: =SAISIE!$C$43/12 -> 125 | F81: =SAISIE!$C$43/12 -> 125 | G81: =SAISIE!$C$43/12 -> 125 | H81: =SAISIE!$C$43/12 -> 125 | I81: =SAISIE!$C$43/12 -> 125 | J81: =SAISIE!$C$43/12 -> 125 | K81: =SAISIE!$C$43/12 -> 125 | ... O81: =SAISIE!$C$43/12 -> 125 | P81: =SAISIE!D43 -> 500 | Q81: =SAISIE!$D$43/12 -> 41.666667 | R81: =SAISIE!$D$43/12 -> 41.666667 | S81: =SAISIE!$D$43/12 -> 41.666667 | T81: =SAISIE!$D$43/12 -> 41.666667 | U81: =SAISIE!$D$43/12 -> 41.666667 | V81: =SAISIE!$D$43/12 -> 41.666667 | W81: =SAISIE!$D$43/12 -> 41.666667 | X81: =SAISIE!$D$43/12 -> 41.666667 | ... AB81: =SAISIE!$D$43/12 -> 41.666667 | AC81: =SAISIE!E43 -> 500 | AD81: =SAISIE!$E$43/12 -> 41.666667 | AE81: =SAISIE!$E$43/12 -> 41.666667 | AF81: =SAISIE!$E$43/12 -> 41.666667 | AG81: =SAISIE!$E$43/12 -> 41.666667 | AH81: =SAISIE!$E$43/12 -> 41.666667 | AI81: =SAISIE!$E$43/12 -> 41.666667 | AJ81: =SAISIE!$E$43/12 -> 41.666667 | AK81: =SAISIE!$E$43/12 -> 41.666667 | ... AO81: =SAISIE!$E$43/12 -> 41.666667
B82: Informatique | C82: =SAISIE!C44 -> 4000 | D82: =SAISIE!$C$44/12 -> 333.33333 | E82: =SAISIE!$C$44/12 -> 333.33333 | F82: =SAISIE!$C$44/12 -> 333.33333 | G82: =SAISIE!$C$44/12 -> 333.33333 | H82: =SAISIE!$C$44/12 -> 333.33333 | I82: =SAISIE!$C$44/12 -> 333.33333 | J82: =SAISIE!$C$44/12 -> 333.33333 | K82: =SAISIE!$C$44/12 -> 333.33333 | ... O82: =SAISIE!$C$44/12 -> 333.33333 | P82: =SAISIE!D44 -> 1500 | Q82: =SAISIE!$D$44/12 -> 125 | R82: =SAISIE!$D$44/12 -> 125 | S82: =SAISIE!$D$44/12 -> 125 | T82: =SAISIE!$D$44/12 -> 125 | U82: =SAISIE!$D$44/12 -> 125 | V82: =SAISIE!$D$44/12 -> 125 | W82: =SAISIE!$D$44/12 -> 125 | X82: =SAISIE!$D$44/12 -> 125 | ... AB82: =SAISIE!$D$44/12 -> 125 | AC82: =SAISIE!E44 -> 2000 | AD82: =SAISIE!$E$44/12 -> 166.66667 | AE82: =SAISIE!$E$44/12 -> 166.66667 | AF82: =SAISIE!$E$44/12 -> 166.66667 | AG82: =SAISIE!$E$44/12 -> 166.66667 | AH82: =SAISIE!$E$44/12 -> 166.66667 | AI82: =SAISIE!$E$44/12 -> 166.66667 | AJ82: =SAISIE!$E$44/12 -> 166.66667 | AK82: =SAISIE!$E$44/12 -> 166.66667 | ... AO82: =SAISIE!$E$44/12 -> 166.66667
B83: Mobilier | C83: =SUM(D83:O83) -> 0 | D83: 0 | E83: 0 | F83: 0 | G83: 0 | H83: 0 | I83: 0 | J83: 0 | K83: 0 | L83: 0 | M83: 0 | N83: 0 | O83: 0 | P83: =SUM(Q83:AB83) -> 0 | AC83: =SUM(AD83:AO83) -> 0
B84: Dépôt loyer (3 mois) | C84: =SUM(D84:O84) -> 0 | D84: 0 | E84: 0 | F84: 0 | G84: 0 | H84: 0 | I84: 0 | J84: 0 | K84: 0 | L84: 0 | M84: 0 | N84: 0 | O84: 0 | P84: =SUM(Q84:AB84) -> 0 | AC84: =SUM(AD84:AO84) -> 0
B85: Total investissements | C85: =SUM(D85:O85) -> 5500 | D85: =SUM(D79:D84) -> 458.33333 | E85: =SUM(E79:E84) -> 458.33333 | F85: =SUM(F79:F84) -> 458.33333 | G85: =SUM(G79:G84) -> 458.33333 | H85: =SUM(H79:H84) -> 458.33333 | I85: =SUM(I79:I84) -> 458.33333 | J85: =SUM(J79:J84) -> 458.33333 | K85: =SUM(K79:K84) -> 458.33333 | ... O85: =SUM(O79:O84) -> 458.33333 | P85: =SUM(Q85:AB85) -> 2000 | Q85: =SUM(Q79:Q84) -> 166.66667 | R85: =SUM(R79:R84) -> 166.66667 | S85: =SUM(S79:S84) -> 166.66667 | T85: =SUM(T79:T84) -> 166.66667 | U85: =SUM(U79:U84) -> 166.66667 | V85: =SUM(V79:V84) -> 166.66667 | W85: =SUM(W79:W84) -> 166.66667 | X85: =SUM(X79:X84) -> 166.66667 | ... AB85: =SUM(AB79:AB84) -> 166.66667 | AC85: =SUM(AD85:AO85) -> 2500 | AD85: =SUM(AD79:AD84) -> 208.33333 | AE85: =SUM(AE79:AE84) -> 208.33333 | AF85: =SUM(AF79:AF84) -> 208.33333 | AG85: =SUM(AG79:AG84) -> 208.33333 | AH85: =SUM(AH79:AH84) -> 208.33333 | AI85: =SUM(AI79:AI84) -> 208.33333 | AJ85: =SUM(AJ79:AJ84) -> 208.33333 | AK85: =SUM(AK79:AK84) -> 208.33333 | ... AO85: =SUM(AO79:AO84) -> 208.33333
B87: Amortissements comptables | C87: =SUM(D87:O87) -> 1833.3333 | D87: =+D85/3 -> 152.77778 | E87: =+E85/3 -> 152.77778 | F87: =+F85/3 -> 152.77778 | G87: =+G85/3 -> 152.77778 | H87: =+H85/3 -> 152.77778 | I87: =+I85/3 -> 152.77778 | J87: =+J85/3 -> 152.77778 | K87: =+K85/3 -> 152.77778 | ... AO87: =+AO85/3 -> 69.444444
B88: Amortissements fiscaux | C88: =SUM(D88:O88) -> 1833.3333 | D88: =+D87 -> 152.77778 | E88: =+E87 -> 152.77778 | F88: =+F87 -> 152.77778 | G88: =+G87 -> 152.77778 | H88: =+H87 -> 152.77778 | I88: =+I87 -> 152.77778 | J88: =+J87 -> 152.77778 | K88: =+K87 -> 152.77778 | ... AO88: =+AO87 -> 69.444444
B89: Amortissements dérogatoires | C89: =C87-C88 -> 0 | P89: =P87-P88 -> 0 | AC89: =AC87-AC88 -> 0
B91: Reprise amortissements dérogatoires | C91: =SUM(D91:O91) -> 0 | P91: =SUM(Q91:AB91) -> 0 | AC91: =SUM(AD91:AO91) -> 0
B93: # acquisitions
B95: 4) Budget des impôts et taxes
D97: 46053 | E97: 46081 | F97: 46112 | G97: 46142 | H97: 46173 | I97: 46203 | J97: 46234 | K97: 46265 | L97: 46295 | M97: 46326 | N97: 46356 | O97: 46387 | Q97: 46418 | R97: 46446 | S97: 46477 | T97: 46507 | U97: 46538 | V97: 46568 | W97: 46599 | X97: 46630 | Y97: 46660 | Z97: 46691 | AA97: 46721 | AB97: 46752 | AD97: 46783 | AE97: 46811 | AF97: 46839 | AG97: 46867 | AH97: 46895 | AI97: 46923 | AJ97: 46951 | AK97: 46979 | AL97: 47007 | AM97: 47035 | AN97: 47063 | AO97: 47091
B99: CET | C99: =SUM(D99:O99) -> 0 | P99: =SUM(Q99:AB99) -> 0 | AC99: =SUM(AD99:AO99) -> 0
B100: Taxe foncière | C100: =SUM(D100:O100) -> 0 | P100: =SUM(Q100:AB100) -> 0 | AC100: =SUM(AD100:AO100) -> 0
B101: Droits d'enregistrement | C101: =SUM(D101:O101) -> 0 | P101: =SUM(Q101:AB101) -> 0 | AC101: =SUM(AD101:AO101) -> 0
B102: Autres taxes | C102: =SUM(D102:O102) -> 0 | P102: =SUM(Q102:AB102) -> 0 | AC102: =SUM(AD102:AO102) -> 0
B103: Total des impôts et taxes | C103: =SUM(C99:C102) -> 0 | D103: =SUM(D99:D102) -> 0 | E103: =SUM(E99:E102) -> 0 | F103: =SUM(F99:F102) -> 0 | G103: =SUM(G99:G102) -> 0 | H103: =SUM(H99:H102) -> 0 | I103: =SUM(I99:I102) -> 0 | J103: =SUM(J99:J102) -> 0 | ... AO103: =SUM(AO99:AO102) -> 0
B105: 5) Budget de trésorerie
D107: 46053 | E107: 46081 | F107: 46112 | G107: 46142 | H107: 46173 | I107: 46203 | J107: 46234 | K107: 46265 | L107: 46295 | M107: 46326 | N107: 46356 | O107: 46387 | Q107: 46418 | R107: 46446 | S107: 46477 | T107: 46507 | U107: 46538 | V107: 46568 | W107: 46599 | X107: 46630 | Y107: 46660 | Z107: 46691 | AA107: 46721 | AB107: 46752 | AD107: 46783 | AE107: 46811 | AF107: 46839 | AG107: 46867 | AH107: 46895 | AI107: 46923 | AJ107: 46951 | AK107: 46979 | AL107: 47007 | AM107: 47035 | AN107: 47063 | AO107: 47091
B109: I - Trésorerie initiale | D109: 0 | E109: =D129 -> 25516.667 | F109: =E129 -> 27376.722 | G109: =F129 -> 28161.003 | H109: =G129 -> 28542.845 | I109: =H129 -> 28925.585 | J109: =I129 -> 29309.226 | K109: =J129 -> 29693.771 | L109: =K129 -> 30079.222 | ... O109: =N129 -> 31241.048 | P109: =Q109 -> 31630.157 | Q109: =O129 -> 31630.157 | R109: =Q129 -> 27467.521 | S109: =R129 -> 33896.144 | T109: =S129 -> 38075.695 | U109: =T129 -> 42256.177 | V109: =U129 -> 44596.196 | W109: =V129 -> 47857.851 | X109: =W129 -> 52041.145 | Y109: =X129 -> 56225.384 | ... AB109: =AA129 -> 68323.444 | AC109: =AD109 -> 72051.14 | AD109: =AB129 -> 72051.14 | AE109: =AD129 -> 69813.478 | AF109: =AE129 -> 80075.945 | AG109: =AF129 -> 85114.747 | AH109: =AG129 -> 92562.483 | AI109: =AH129 -> 92220.729 | AJ109: =AI129 -> 97262.447 | AK109: =AJ129 -> 104713.11 | AL109: =AK129 -> 112164.76 | ... AO109: =AN129 -> 132117.65
B111: II - Recettes | C111: =SUM(D111:O111) -> 154300 | D111: =SUM(D112:D115) -> 30000 | E111: =SUM(E112:E115) -> 11300 | F111: =SUM(F112:F115) -> 11300 | G111: =SUM(G112:G115) -> 11300 | H111: =SUM(H112:H115) -> 11300 | I111: =SUM(I112:I115) -> 11300 | J111: =SUM(J112:J115) -> 11300 | K111: =SUM(K112:K115) -> 11300 | ... O111: =SUM(O112:O115) -> 11300 | P111: =SUM(Q111:AB111) -> 284100 | Q111: =SUM(Q112:Q115) -> 11300 | R111: =SUM(R112:R115) -> 24800 | S111: =SUM(S112:S115) -> 24800 | T111: =SUM(T112:T115) -> 24800 | U111: =SUM(U112:U115) -> 24800 | V111: =SUM(V112:V115) -> 24800 | W111: =SUM(W112:W115) -> 24800 | X111: =SUM(X112:X115) -> 24800 | ... AB111: =SUM(AB112:AB115) -> 24800 | AC111: =SUM(AD111:AO111) -> 483500 | AD111: =SUM(AD112:AD115) -> 24800 | AE111: =SUM(AE112:AE115) -> 41700 | AF111: =SUM(AF112:AF115) -> 41700 | AG111: =SUM(AG112:AG115) -> 41700 | AH111: =SUM(AH112:AH115) -> 41700 | AI111: =SUM(AI112:AI115) -> 41700 | AJ111: =SUM(AJ112:AJ115) -> 41700 | AK111: =SUM(AK112:AK115) -> 41700 | ... AO111: =SUM(AO112:AO115) -> 41700
B112: Apport en capital | C112: =SUM(D112:O112) -> 10000 | D112: =+SAISIE!C49 -> 10000 | P112: =SUM(Q112:AB112) -> 0 | AC112: =SUM(AD112:AO112) -> 0
B113: Encaissement clients TTC | C113: =SUM(D113:O113) -> 124300 | D113: 0 | E113: =D36*1.2 -> 11300 | F113: =E36*1.2 -> 11300 | G113: =F36*1.2 -> 11300 | H113: =G36*1.2 -> 11300 | I113: =H36*1.2 -> 11300 | J113: =I36*1.2 -> 11300 | K113: =J36*1.2 -> 11300 | L113: =K36*1.2 -> 11300 | ... O113: =N36*1.2 -> 11300 | P113: =SUM(Q113:AB113) -> 284100 | Q113: =O36*1.2 -> 11300 | R113: =Q36*1.2 -> 24800 | S113: =R36*1.2 -> 24800 | T113: =S36*1.2 -> 24800 | U113: =T36*1.2 -> 24800 | V113: =U36*1.2 -> 24800 | W113: =V36*1.2 -> 24800 | X113: =W36*1.2 -> 24800 | Y113: =X36*1.2 -> 24800 | ... AB113: =AA36*1.2 -> 24800 | AC113: =SUM(AD113:AO113) -> 483500 | AD113: =+AB36*1.2 -> 24800 | AE113: =+AD36*1.2 -> 41700 | AF113: =+AE36*1.2 -> 41700 | AG113: =+AF36*1.2 -> 41700 | AH113: =+AG36*1.2 -> 41700 | AI113: =+AH36*1.2 -> 41700 | AJ113: =+AI36*1.2 -> 41700 | AK113: =+AJ36*1.2 -> 41700 | AL113: =+AK36*1.2 -> 41700 | ... AO113: =+AN36*1.2 -> 41700
B114: Remboursement crédit TVA | C114: =SUM(D114:O114) -> 0 | F114: =D138 -> 0 | G114: =E138 -> 0 | H114: =F138 -> 0 | I114: =G138 -> 0 | J114: =H138 -> 0 | K114: =I138 -> 0 | L114: =J138 -> 0 | M114: =K138 -> 0 | ... O114: =M138 -> 0 | P114: =SUM(Q114:AB114) -> 0 | Q114: =O138 -> 0 | R114: =Q138 -> 0 | S114: =R138 -> 0 | T114: =S138 -> 0 | U114: =T138 -> 0 | V114: =U138 -> 0 | W114: =U138 -> 0 | X114: =V138 -> 0 | Y114: =W138 -> 0 | Z114: =X138 -> 0 | AA114: =Y138 -> 0 | AB114: =Z138 -> 0 | AC114: =SUM(AD114:AO114) -> 0 | AD114: =AA138 -> 0 | AE114: =AB138 -> 0 | AF114: =AD138 -> 0 | AG114: =AE138 -> 0 | AH114: =AF138 -> 0 | AI114: =AG138 -> 0 | AJ114: =AH138 -> 0 | AK114: =AI138 -> 0 | AL114: =AJ138 -> 0 | AM114: =AK138 -> 0 | ... AO114: =AM138 -> 0
B115: Nouveaux crédits bancaires | C115: =SUM(D115:O115) -> 20000 | D115: 20000 | P115: =SUM(Q115:AB115) -> 0 | AC115: =SUM(AD115:AO115) -> 0
B117: III - Dépenses | C117: =SUM(D117:O117) -> 122669.84 | D117: =SUM(D118:D126) -> 4483.3333 | E117: =SUM(E118:E126) -> 9439.9444 | F117: =SUM(F118:F126) -> 10515.719 | G117: =SUM(G118:G126) -> 10918.158 | H117: =SUM(H118:H126) -> 10917.26 | I117: =SUM(I118:I126) -> 10916.359 | J117: =SUM(J118:J126) -> 10915.455 | K117: =SUM(K118:K126) -> 10914.549 | ... O117: =SUM(O118:O126) -> 10910.891 | P117: =SUM(Q117:AB117) -> 243679.02 | Q117: =SUM(Q118:Q126) -> 15462.636 | R117: =SUM(R118:R126) -> 18371.377 | S117: =SUM(S118:S126) -> 20620.449 | T117: =SUM(T118:T126) -> 20619.518 | U117: =SUM(U118:U126) -> 22459.982 | V117: =SUM(V118:V126) -> 21538.345 | W117: =SUM(W118:W126) -> 20616.705 | X117: =SUM(X118:X126) -> 20615.761 | ... AB117: =SUM(AB118:AB126) -> 21072.304 | AC117: =SUM(AD117:AO117) -> 418385.84 | AD117: =SUM(AD118:AD126) -> 27037.662 | AE117: =SUM(AE118:AE126) -> 31437.532 | AF117: =SUM(AF118:AF126) -> 36661.198 | AG117: =SUM(AG118:AG126) -> 34252.264 | AH117: =SUM(AH118:AH126) -> 42041.755 | AI117: =SUM(AI118:AI126) -> 36658.281 | AJ117: =SUM(AJ118:AJ126) -> 34249.337 | AK117: =SUM(AK118:AK126) -> 34248.355 | ... AO117: =SUM(AO118:AO126) -> 36652.358
B118: Remboursement de crédit | C118: =SUM(D118:O118) -> 4000 | D118: =+D169+D183 -> 333.33333 | E118: =+E169+E183 -> 333.33333 | F118: =+F169+F183 -> 333.33333 | G118: =+G169+G183 -> 333.33333 | H118: =+H169+H183 -> 333.33333 | I118: =+I169+I183 -> 333.33333 | J118: =+J169+J183 -> 333.33333 | K118: =+K169+K183 -> 333.33333 | ... O118: =+O169+O183 -> 333.33333 | P118: =SUM(Q118:AB118) -> 4000 | Q118: =+Q169+Q183 -> 333.33333 | R118: =+R169+R183 -> 333.33333 | S118: =+S169+S183 -> 333.33333 | T118: =+T169+T183 -> 333.33333 | U118: =+U169+U183 -> 333.33333 | V118: =+V169+V183 -> 333.33333 | W118: =+W169+W183 -> 333.33333 | X118: =+X169+X183 -> 333.33333 | ... AB118: =+AB169+AB183 -> 333.33333 | AC118: =SUM(AD118:AO118) -> 4000 | AD118: =+AD169+AD183 -> 333.33333 | AE118: =+AE169+AE183 -> 333.33333 | AF118: =+AF169+AF183 -> 333.33333 | AG118: =+AG169+AG183 -> 333.33333 | AH118: =+AH169+AH183 -> 333.33333 | AI118: =+AI169+AI183 -> 333.33333 | AJ118: =+AJ169+AJ183 -> 333.33333 | AK118: =+AK169+AK183 -> 333.33333 | ... AO118: =+AO169+AO183 -> 333.33333
B119: Investissements | C119: =SUM(D119:O119) -> 6050 | E119: =D85*1.2 -> 550 | F119: =E85*1.2 -> 550 | G119: =F85*1.2 -> 550 | H119: =G85*1.2 -> 550 | I119: =H85*1.2 -> 550 | J119: =I85*1.2 -> 550 | K119: =J85*1.2 -> 550 | L119: =K85*1.2 -> 550 | ... O119: =N85*1.2 -> 550 | P119: =SUM(Q119:AB119) -> 2750 | Q119: =O85*1.2 -> 550 | R119: =Q85*1.2 -> 200 | S119: =R85*1.2 -> 200 | T119: =S85*1.2 -> 200 | U119: =T85*1.2 -> 200 | V119: =U85*1.2 -> 200 | W119: =V85*1.2 -> 200 | X119: =W85*1.2 -> 200 | Y119: =X85*1.2 -> 200 | ... AB119: =AA85*1.2 -> 200 | AC119: =SUM(AD119:AO119) -> 2950 | AD119: =AB85*1.2 -> 200 | AE119: =AD85*1.2 -> 250 | AF119: =AE85*1.2 -> 250 | AG119: =AF85*1.2 -> 250 | AH119: =AG85*1.2 -> 250 | AI119: =AH85*1.2 -> 250 | AJ119: =AI85*1.2 -> 250 | AK119: =AJ85*1.2 -> 250 | AL119: =AK85*1.2 -> 250 | ... AO119: =AN85*1.2 -> 250
B120: Charges directes et externes TTC | C120: =SUM(D120:O120) -> 20570 | D120: =Bilan!C29 -> 0 | E120: =(D42+D53+D54)*1.2 -> 1870 | F120: =(E42+E53+E54)*1.2 -> 1870 | G120: =(F42+F53+F54)*1.2 -> 1870 | H120: =(G42+G53+G54)*1.2 -> 1870 | I120: =(H42+H53+H54)*1.2 -> 1870 | J120: =(I42+I53+I54)*1.2 -> 1870 | K120: =(J42+J53+J54)*1.2 -> 1870 | L120: =(K42+K53+K54)*1.2 -> 1870 | ... O120: =(N42+N53+N54)*1.2 -> 1870 | P120: =SUM(Q120:AB120) -> 23540 | Q120: =(O42+O53+O54)*1.2 -> 1870 | R120: =(Q42+Q53+Q54)*1.2 -> 1970 | S120: =(R42+R53+R54)*1.2 -> 1970 | T120: =(S42+S53+S54)*1.2 -> 1970 | U120: =(T42+T53+T54)*1.2 -> 1970 | V120: =(U42+U53+U54)*1.2 -> 1970 | W120: =(V42+V53+V54)*1.2 -> 1970 | X120: =(W42+W53+W54)*1.2 -> 1970 | Y120: =(X42+X53+X54)*1.2 -> 1970 | ... AB120: =(AA42+AA53+AA54)*1.2 -> 1970 | AC120: =SUM(AD120:AO120) -> 25840 | AD120: =(AB42+AB53+AB54)*1.2 -> 1970 | AE120: =(AD42+AD53+AD54)*1.2 -> 2170 | AF120: =(AE42+AE53+AE54)*1.2 -> 2170 | AG120: =(AF42+AF53+AF54)*1.2 -> 2170 | AH120: =(AG42+AG53+AG54)*1.2 -> 2170 | AI120: =(AH42+AH53+AH54)*1.2 -> 2170 | AJ120: =(AI42+AI53+AI54)*1.2 -> 2170 | AK120: =(AJ42+AJ53+AJ54)*1.2 -> 2170 | AL120: =(AK42+AK53+AK54)*1.2 -> 2170 | ... AO120: =(AN42+AN53+AN54)*1.2 -> 2170
B121: Impôts & taxes | C121: =SUM(D121:O121) -> 600 | D121: =D56 -> 50 | E121: =E56 -> 50 | F121: =F56 -> 50 | G121: =G56 -> 50 | H121: =H56 -> 50 | I121: =I56 -> 50 | J121: =J56 -> 50 | K121: =K56 -> 50 | ... O121: =O56 -> 50 | P121: =SUM(Q121:AB121) -> 600 | Q121: =Q56 -> 50 | R121: =R56 -> 50 | S121: =S56 -> 50 | T121: =T56 -> 50 | U121: =U56 -> 50 | V121: =V56 -> 50 | W121: =W56 -> 50 | X121: =X56 -> 50 | ... AB121: =AB56 -> 50 | AC121: =SUM(AD121:AO121) -> 600 | AD121: =AD56 -> 50 | AE121: =AE56 -> 50 | AF121: =AF56 -> 50 | AG121: =AG56 -> 50 | AH121: =AH56 -> 50 | AI121: =AI56 -> 50 | AJ121: =AJ56 -> 50 | AK121: =AK56 -> 50 | ... AO121: =AO56 -> 50
B122: Salaires | C122: =SUM(D122:O122) -> 48400 | D122: =D57*0.78+D55 -> 4033.3333 | E122: =E57*0.78+E55 -> 4033.3333 | F122: =F57*0.78+F55 -> 4033.3333 | G122: =G57*0.78+G55 -> 4033.3333 | H122: =H57*0.78+H55 -> 4033.3333 | I122: =I57*0.78+I55 -> 4033.3333 | J122: =J57*0.78+J55 -> 4033.3333 | K122: =K57*0.78+K55 -> 4033.3333 | ... O122: =O57*0.78+O55 -> 4033.3333 | P122: =SUM(Q122:AB122) -> 103032 | Q122: =Q57*0.78+Q55 -> 8586 | R122: =R57*0.78+R55 -> 8586 | S122: =S57*0.78+S55 -> 8586 | T122: =T57*0.78+T55 -> 8586 | U122: =U57*0.78+U55 -> 8586 | V122: =V57*0.78+V55 -> 8586 | W122: =W57*0.78+W55 -> 8586 | X122: =X57*0.78+X55 -> 8586 | ... AB122: =AB57*0.78+AB55 -> 8586 | AC122: =SUM(AD122:AO122) -> 180152 | AD122: =AD57*0.78+AD55 -> 15012.667 | AE122: =AE57*0.78+AE55 -> 15012.667 | AF122: =AF57*0.78+AF55 -> 15012.667 | AG122: =AG57*0.78+AG55 -> 15012.667 | AH122: =AH57*0.78+AH55 -> 15012.667 | AI122: =AI57*0.78+AI55 -> 15012.667 | AJ122: =AJ57*0.78+AJ55 -> 15012.667 | AK122: =AK57*0.78+AK55 -> 15012.667 | ... AO122: =AO57*0.78+AO55 -> 15012.667
B123: Charges sociales | C123: =SUM(D123:O123) -> 27912.5 | E123: =D57*22%+D58 -> 2537.5 | F123: =E57*22%+E58 -> 2537.5 | G123: =F57*22%+F58 -> 2537.5 | H123: =G57*22%+G58 -> 2537.5 | I123: =H57*22%+H58 -> 2537.5 | J123: =I57*22%+I58 -> 2537.5 | K123: =J57*22%+J58 -> 2537.5 | L123: =K57*22%+K58 -> 2537.5 | ... O123: =N57*22%+N58 -> 2537.5 | P123: =SUM(Q123:AB123) -> 64748 | Q123: =O57*22%+O58 -> 2537.5 | R123: =Q57*22%+Q58 -> 5655.5 | S123: =R57*22%+R58 -> 5655.5 | T123: =S57*22%+S58 -> 5655.5 | U123: =T57*22%+T58 -> 5655.5 | V123: =U57*22%+U58 -> 5655.5 | W123: =V57*22%+V58 -> 5655.5 | X123: =W57*22%+W58 -> 5655.5 | Y123: =X57*22%+X58 -> 5655.5 | ... AB123: =AA57*22%+AA58 -> 5655.5 | AC123: =SUM(AD123:AO123) -> 113983.5 | AD123: =AB57*22%+AB58 -> 5655.5 | AE123: =AD57*22%+AD58 -> 9848 | AF123: =AE57*22%+AE58 -> 9848 | AG123: =AF57*22%+AF58 -> 9848 | AH123: =AG57*22%+AG58 -> 9848 | AI123: =AH57*22%+AH58 -> 9848 | AJ123: =AI57*22%+AI58 -> 9848 | AK123: =AJ57*22%+AJ58 -> 9848 | AL123: =AK57*22%+AK58 -> 9848 | ... AO123: =AN57*22%+AN58 -> 9848
B124: Charges financières | C124: =SUM(D124:O124) -> 740.67657 | D124: =D64 -> 66.666667 | E124: =E64 -> 65.777778 | F124: =F64 -> 64.885926 | G124: =G64 -> 63.991101 | H124: =H64 -> 63.093294 | I124: =I64 -> 62.192494 | J124: =J64 -> 61.288691 | K124: =K64 -> 60.381875 | ... O124: =O64 -> 56.724285 | P124: =SUM(Q124:AB124) -> 607.8867 | Q124: =Q64 -> 55.802255 | R124: =R64 -> 54.877152 | S124: =S64 -> 53.948964 | T124: =T64 -> 53.017683 | U124: =U64 -> 52.083298 | V124: =V64 -> 51.145798 | W124: =W64 -> 50.205172 | X124: =X64 -> 49.261412 | ... AB124: =AB64 -> 45.454806 | AC124: =SUM(AD124:AO124) -> 469.68677 | AD124: =AD64 -> 44.495211 | AE124: =AE64 -> 43.532417 | AF124: =AF64 -> 42.566414 | AG124: =AG64 -> 41.597191 | AH124: =AH64 -> 40.624737 | AI124: =AI64 -> 39.649042 | AJ124: =AJ64 -> 38.670094 | AK124: =AK64 -> 37.687883 | ... AO124: =AO64 -> 33.726191
B125: Impôt sur les bénéfices | C125: =SUM(D125:O125) -> 0 | P125: =SUM(Q125:AB125) -> 3682.797 | U125: =C70 -> 1841.3985 | V125: =C70/2 -> 920.69926 | Y125: =C70/4 -> 460.34963 | AB125: =C70/4 -> 460.34963 | AC125: =SUM(AD125:AO125) -> 17422.325 | AF125: =$P$70/4 -> 2407.9654 | AH125: =P70-C70 -> 7790.4631 | AI125: =$P$70/4 -> 2407.9654 | AL125: =$P$70/4 -> 2407.9654 | AO125: =$P$70/4 -> 2407.9654
B126: TVA à décaisser | C126: =SUM(D126:O126) -> 14396.667 | E126: =D141 -> 0 | F126: =E141 -> 1076.6667 | G126: =F141 -> 1480 | H126: =G141 -> 1480 | I126: =H141 -> 1480 | J126: =I141 -> 1480 | K126: =J141 -> 1480 | L126: =K141 -> 1480 | ... O126: =N141 -> 1480 | P126: =SUM(Q126:AB126) -> 40718.333 | Q126: =O141 -> 1480 | R126: =Q141 -> 1521.6667 | S126: =R141 -> 3771.6667 | T126: =S141 -> 3771.6667 | U126: =T141 -> 3771.6667 | V126: =U141 -> 3771.6667 | W126: =V141 -> 3771.6667 | X126: =W141 -> 3771.6667 | Y126: =X141 -> 3771.6667 | ... AB126: =AA141 -> 3771.6667 | AC126: =SUM(AD126:AO126) -> 72968.333 | AD126: =AB141 -> 3771.6667 | AE126: =AD141 -> 3730 | AF126: =AE141 -> 6546.6667 | AG126: =AF141 -> 6546.6667 | AH126: =AG141 -> 6546.6667 | AI126: =AH141 -> 6546.6667 | AJ126: =AI141 -> 6546.6667 | AK126: =AJ141 -> 6546.6667 | AL126: =AK141 -> 6546.6667 | ... AO126: =AN141 -> 6546.6667
B128: Variation de trésorerie | C128: =C111-C117 -> 31630.157 | D128: =D111-D117 -> 25516.667 | E128: =E111-E117 -> 1860.0556 | F128: =F111-F117 -> 784.28074 | G128: =G111-G117 -> 381.84223 | H128: =H111-H117 -> 382.74004 | I128: =I111-I117 -> 383.64084 | J128: =J111-J117 -> 384.54464 | ... AO128: =AO111-AO117 -> 5047.6417
B129: IV - Trésorerie finale | C129: =O129 -> 31630.157 | D129: =D109+D111-D117 -> 25516.667 | E129: =E109+E111-E117 -> 27376.722 | F129: =F109+F111-F117 -> 28161.003 | G129: =G109+G111-G117 -> 28542.845 | H129: =H109+H111-H117 -> 28925.585 | I129: =I109+I111-I117 -> 29309.226 | J129: =J109+J111-J117 -> 29693.771 | K129: =K109+K111-K117 -> 30079.222 | ... O129: =O109+O111-O117 -> 31630.157 | P129: =AB129 -> 72051.14 | Q129: =Q109+Q111-Q117 -> 27467.521 | R129: =R109+R111-R117 -> 33896.144 | S129: =S109+S111-S117 -> 38075.695 | T129: =T109+T111-T117 -> 42256.177 | U129: =U109+U111-U117 -> 44596.196 | V129: =V109+V111-V117 -> 47857.851 | W129: =W109+W111-W117 -> 52041.145 | X129: =X109+X111-X117 -> 56225.384 | ... AB129: =AB109+AB111-AB117 -> 72051.14 | AC129: =AO129 -> 137165.29 | AD129: =AD109+AD111-AD117 -> 69813.478 | AE129: =AE109+AE111-AE117 -> 80075.945 | AF129: =AF109+AF111-AF117 -> 85114.747 | AG129: =AG109+AG111-AG117 -> 92562.483 | AH129: =AH109+AH111-AH117 -> 92220.729 | AI129: =AI109+AI111-AI117 -> 97262.447 | AJ129: =AJ109+AJ111-AJ117 -> 104713.11 | AK129: =AK109+AK111-AK117 -> 112164.76 | ... AO129: =AO109+AO111-AO117 -> 137165.29
B131: 6) Budget de TVA
D133: 46053 | E133: 46081 | F133: 46112 | G133: 46142 | H133: 46173 | I133: 46203 | J133: 46234 | K133: 46265 | L133: 46295 | M133: 46326 | N133: 46356 | O133: 46387 | Q133: 46418 | R133: 46446 | S133: 46477 | T133: 46507 | U133: 46538 | V133: 46568 | W133: 46599 | X133: 46630 | Y133: 46660 | Z133: 46691 | AA133: 46721 | AB133: 46752 | AD133: 46783 | AE133: 46811 | AF133: 46839 | AG133: 46867 | AH133: 46895 | AI133: 46923 | AJ133: 46951 | AK133: 46979 | AL133: 47007 | AM133: 47035 | AN133: 47063 | AO133: 47091
B135: TVA collectée ventes | C135: =SUM(D135:O135) -> 20716.667 | E135: =E113/6 -> 1883.3333 | F135: =F113/6 -> 1883.3333 | G135: =G113/6 -> 1883.3333 | H135: =H113/6 -> 1883.3333 | I135: =I113/6 -> 1883.3333 | J135: =J113/6 -> 1883.3333 | K135: =K113/6 -> 1883.3333 | L135: =L113/6 -> 1883.3333 | ... O135: =O113/6 -> 1883.3333 | P135: =SUM(Q135:AB135) -> 47350 | Q135: =Q113/6 -> 1883.3333 | R135: =R113/6 -> 4133.3333 | S135: =S113/6 -> 4133.3333 | T135: =T113/6 -> 4133.3333 | U135: =U113/6 -> 4133.3333 | V135: =V113/6 -> 4133.3333 | W135: =W113/6 -> 4133.3333 | X135: =X113/6 -> 4133.3333 | ... AB135: =AB113/6 -> 4133.3333 | AC135: =SUM(AD135:AO135) -> 80583.333 | AD135: =AD113/6 -> 4133.3333 | AE135: =AE113/6 -> 6950 | AF135: =AF113/6 -> 6950 | AG135: =AG113/6 -> 6950 | AH135: =AH113/6 -> 6950 | AI135: =AI113/6 -> 6950 | AJ135: =AJ113/6 -> 6950 | AK135: =AK113/6 -> 6950 | ... AO135: =AO113/6 -> 6950
...

Sheet Personnel
B2: Catégorie | C2: Poste | D2: Date entrée | E2: 2025 | T2: 2026 | AI2: 2027
E3: Salaires bruts annuels | F3: Nombre de salariés | T3: Salaires bruts annuels | U3: Nombre de salariés | AI3: Salaires bruts annuels | AJ3: Nombre de salariés
F4: 46023 | G4: =EOMONTH(F4,1) -> 46081 | H4: =EOMONTH(G4,1) -> 46112 | I4: =EOMONTH(H4,1) -> 46142 | J4: =EOMONTH(I4,1) -> 46173 | K4: =EOMONTH(J4,1) -> 46203 | L4: =EOMONTH(K4,1) -> 46234 | M4: =EOMONTH(L4,1) -> 46265 | N4: =EOMONTH(M4,1) -> 46295 | ... Q4: =EOMONTH(P4,1) -> 46387 | R4: Total brut | U4: 46418 | V4: =EOMONTH(U4,1) -> 46446 | W4: =EOMONTH(V4,1) -> 46477 | X4: =EOMONTH(W4,1) -> 46507 | Y4: =EOMONTH(X4,1) -> 46538 | Z4: =EOMONTH(Y4,1) -> 46568 | AA4: =EOMONTH(Z4,1) -> 46599 | AB4: =EOMONTH(AA4,1) -> 46630 | AC4: =EOMONTH(AB4,1) -> 46660 | ... AF4: =EOMONTH(AE4,1) -> 46752 | AG4: TOTAL | AJ4: 46783 | AK4: =EOMONTH(AJ4,1) -> 46812 | AL4: =EOMONTH(AK4,1) -> 46843 | AM4: =EOMONTH(AL4,1) -> 46873 | AN4: =EOMONTH(AM4,1) -> 46904 | AO4: =EOMONTH(AN4,1) -> 46934 | AP4: =EOMONTH(AO4,1) -> 46965 | AQ4: =EOMONTH(AP4,1) -> 46996 | AR4: =EOMONTH(AQ4,1) -> 47026 | ... AU4: =EOMONTH(AT4,1) -> 47118 | AV4: TOTAL
B6: Cadre | C6: Junior | D6: 46023 | E6: 30000 | F6: =+$E6/12 -> 2500 | G6: =+$E6/12 -> 2500 | H6: =+$E6/12 -> 2500 | I6: =+$E6/12 -> 2500 | J6: =+$E6/12 -> 2500 | K6: =+$E6/12 -> 2500 | L6: =+$E6/12 -> 2500 | M6: =+$E6/12 -> 2500 | ... Q6: =+$E6/12 -> 2500 | R6: =SUM(F6:Q6) -> 30000 | U6: 2900 | V6: 2900 | W6: 2900 | X6: 2900 | Y6: 2900 | Z6: 2900 | AA6: 2900 | AB6: 2900 | AC6: 2900 | AD6: 2900 | AE6: 2900 | AF6: 2900 | AG6: =SUM(U6:AF6) -> 34800 | AJ6: 3300 | AK6: 3300 | AL6: 3300 | AM6: 3300 | AN6: 3300 | AO6: 3300 | AP6: 3300 | AQ6: 3300 | AR6: 3300 | AS6: 3300 | AT6: 3300 | AU6: 3300 | AV6: =SUM(AJ6:AU6) -> 39600
B7: Cadre | C7: Senior | D7: 46388 | R7: =SUM(F7:Q7) -> 0 | U7: 3300 | V7: 3300 | W7: 3300 | X7: 3300 | Y7: 3300 | Z7: 3300 | AA7: 3300 | AB7: 3300 | AC7: 3300 | AD7: 3300 | AE7: 3300 | AF7: 3300 | AG7: =SUM(U7:AF7) -> 39600 | AJ7: 3700 | AK7: 3700 | AL7: 3700 | AM7: 3700 | AN7: 3700 | AO7: 3700 | AP7: 3700 | AQ7: 3700 | AR7: 3700 | AS7: 3700 | AT7: 3700 | AU7: 3700 | AV7: =SUM(AJ7:AU7) -> 44400
B8: Cadre | C8: Senior | D8: 46753 | R8: =SUM(F8:Q8) -> 0 | AG8: =SUM(U8:AF8) -> 0 | AJ8: 3700 | AK8: 3700 | AL8: 3700 | AM8: 3700 | AN8: 3700 | AO8: 3700 | AP8: 3700 | AQ8: 3700 | AR8: 3700 | AS8: 3700 | AT8: 3700 | AU8: 3700 | AV8: =SUM(AJ8:AU8) -> 44400
B9: Cadre | C9: Chef de mission | D9: Hors plan 3 ans | R9: =SUM(F9:Q9) -> 0 | AG9: =SUM(U9:AF9) -> 0 | AV9: =SUM(AJ9:AU9) -> 0
R10: =SUM(F10:Q10) -> 0 | AG10: =SUM(U10:AF10) -> 0 | AV10: =SUM(AJ10:AU10) -> 0
R11: =SUM(F11:Q11) -> 0 | AG11: =SUM(U11:AF11) -> 0 | AV11: =SUM(AJ11:AU11) -> 0
R12: =SUM(F12:Q12) -> 0 | AG12: =SUM(U12:AF12) -> 0 | AV12: =SUM(AJ12:AU12) -> 0
AG13: =SUM(U13:AF13) -> 0 | AV13: =SUM(AJ13:AU13) -> 0
AG14: =SUM(U14:AF14) -> 0 | AV14: =SUM(AJ14:AU14) -> 0
AG15: =SUM(U15:AF15) -> 0 | AV15: =SUM(AJ15:AU15) -> 0
AG16: =SUM(U16:AF16) -> 0 | AV16: =SUM(AJ16:AU16) -> 0
B17: TOTAL | C17: Salaires bruts | F17: =SUM(F6:F16) -> 2500 | G17: =SUM(G6:G16) -> 2500 | H17: =SUM(H6:H16) -> 2500 | I17: =SUM(I6:I16) -> 2500 | J17: =SUM(J6:J16) -> 2500 | K17: =SUM(K6:K16) -> 2500 | L17: =SUM(L6:L16) -> 2500 | M17: =SUM(M6:M16) -> 2500 | ... R17: =SUM(R6:R16) -> 30000 | U17: =SUM(U6:U16) -> 6200 | V17: =SUM(V6:V16) -> 6200 | W17: =SUM(W6:W16) -> 6200 | X17: =SUM(X6:X16) -> 6200 | Y17: =SUM(Y6:Y16) -> 6200 | Z17: =SUM(Z6:Z16) -> 6200 | AA17: =SUM(AA6:AA16) -> 6200 | AB17: =SUM(AB6:AB16) -> 6200 | ... AG17: =SUM(AG6:AG16) -> 74400 | AJ17: =SUM(AJ6:AJ16) -> 10700 | AK17: =SUM(AK6:AK16) -> 10700 | AL17: =SUM(AL6:AL16) -> 10700 | AM17: =SUM(AM6:AM16) -> 10700 | AN17: =SUM(AN6:AN16) -> 10700 | AO17: =SUM(AO6:AO16) -> 10700 | AP17: =SUM(AP6:AP16) -> 10700 | AQ17: =SUM(AQ6:AQ16) -> 10700 | ... AV17: =SUM(AV6:AV16) -> 128400
C19: Total effectif | F19: =COUNTA(F6:F16) -> 1 | G19: =COUNTA(G6:G16) -> 1 | H19: =COUNTA(H6:H16) -> 1 | I19: =COUNTA(I6:I16) -> 1 | J19: =COUNTA(J6:J16) -> 1 | K19: =COUNTA(K6:K16) -> 1 | L19: =COUNTA(L6:L16) -> 1 | M19: =COUNTA(M6:M16) -> 1 | ... Q19: =COUNTA(Q6:Q16) -> 1 | U19: =COUNTA(U6:U16) -> 2 | V19: =COUNTA(V6:V16) -> 2 | W19: =COUNTA(W6:W16) -> 2 | X19: =COUNTA(X6:X16) -> 2 | Y19: =COUNTA(Y6:Y16) -> 2 | Z19: =COUNTA(Z6:Z16) -> 2 | AA19: =COUNTA(AA6:AA16) -> 2 | AB19: =COUNTA(AB6:AB16) -> 2 | ... AF19: =COUNTA(AF6:AF16) -> 2 | AJ19: =COUNTA(AJ6:AJ16) -> 3 | AK19: =COUNTA(AK6:AK16) -> 3 | AL19: =COUNTA(AL6:AL16) -> 3 | AM19: =COUNTA(AM6:AM16) -> 3 | AN19: =COUNTA(AN6:AN16) -> 3 | AO19: =COUNTA(AO6:AO16) -> 3 | AP19: =COUNTA(AP6:AP16) -> 3 | AQ19: =COUNTA(AQ6:AQ16) -> 3 | ... AU19: =COUNTA(AU6:AU16) -> 3
