Workbook

Sheet GUIDE
B1: 📋 GUIDE D'UTILISATION — ANNEXE 22
B2: Grille de suivi de la formation continue — Cabinet 100% numérique
B4: OBJECTIF DE L'OUTIL
B5: Cet outil permet à l'expert-comptable de piloter l'intégralité du processus de formation continue de son cabinet : diagnostic de conformité (Art. 22 Code de déontologie), cartographie des compétences, scoring des priorités, plan d'action budgété avec financement OPCO Atlas, et synthèse imprimable pour le dossier qualité NPMQ. Un seul onglet de saisie alimente automatiquement les 3 onglets suivants.
B9: ARCHITECTURE — FLUX DE DONNÉES
B11: ① SAISIE | D11: ② DIAGNOSTIC | F11: ③ PLAN D'ACTION | H11: ④ FICHE QUALITÉ | J11: ⑤ _REF
B12: Seul onglet modifiable ■ Jaune = saisie manuelle ■ Gris = calcul auto • Paramètres cabinet • Effectif & collaborateurs • Évaluation compétences • Formations réalisées • Formations planifiées • AFEST internes | D12: 100% automatisé — 🔒 Protégé • Conformité Art. 22 CD (120h / 3 ans glissants) • Cartographie compétences • Radar de compétences • TOP 5 priorités formation (scoring multicritère) | F12: 100% automatisé — 🔒 Protégé • Budget formations ext. • Financement OPCO Atlas (PDC + DEC/CAC) • Économies AFEST • Investissement net • Suivi comblement déficit | H12: 100% automatisé — 🔒 Protégé • Fiche cabinet • Conformité par collab. • Taux avant/après plan • Budget consolidé • Checklist pièces (NPMQ §44) • Conclusion dynamique | J12: Documentation technique • Fondement réglementaire • Méthodologie scoring • Sources OPCO Atlas • Taux horaire complet • Données OMECA • Articulation Annexe 23
C14: → | E14: → | G14: → | I14: →
B22: MARCHE À SUIVRE
B24: Étape 1 | D24: Ouvrir l'onglet SAISIE | F24: Renseigner les paramètres du cabinet (section A) : nom, N° OEC, masse salariale, OPCO.
B26: Étape 2 | D26: Saisir l'effectif | F26: Compléter la section B : prénom, nom, grade, contrat, ETP, objectif 3 ans, heures par période.
B28: Étape 3 | D28: Évaluer les compétences | F28: Section C : noter chaque collaborateur de 1 à 5 sur les 16 domaines. Fixer cible, criticité, urgence.
B30: Étape 4 | D30: Saisir les formations | F30: Section D (réalisées) + Section E (planifiées S2) + Section F (AFEST internes).
B32: Étape 5 | D32: Consulter le diagnostic | F32: Onglet DIAGNOSTIC : écarts conformité, cartographie compétences, radar, TOP 5 priorités.
B34: Étape 6 | D34: Lire le plan d'action | F34: Onglet PLAN D'ACTION : budget, OPCO Atlas, économies AFEST, investissement net, comblement.
B36: Étape 7 | D36: Imprimer la fiche qualité | F36: Onglet FICHE QUALITÉ : prêt pour le dossier qualité NPMQ. Signer et dater en bas de page.
B38: ⚠️ PREMIÈRE UTILISATION : avant de saisir vos propres données, effacer l'intégralité des cellules jaunes de l'onglet SAISIE (sections A à F). Les données pré-remplies (Cabinet Digit Expertise, collaborateurs Dupré / Martin / Lambert / Renaud, formations, évaluations) sont des exemples fictifs destinés à illustrer le fonctionnement de l'outil. Une fois les cellules jaunes vidées, les onglets DIAGNOSTIC, PLAN D'ACTION et FICHE QUALITÉ se réinitialiseront automatiquement.
B42: RÉFÉRENCES NORMATIVES CLÉS
B43: Art. 22 Code de déontologie | D43: Formation continue ≈ 120h / 3 ans glissants | H43: Décret 2012-432 mod. 2023-388 — éd. janv. 2026
B44: NPMQ 2025 §21-25 | D44: Compétences, plan formation, évaluation, ressources | H44: Arrêté du 30 mai 2024, applicable 01/01/2025
B45: Art. 148 Code de déontologie | D45: Responsabilité EC sur la compétence de l'équipe | H45: Éd. janv. 2026
B46: Art. L6313-2 Code du travail | D46: AFEST — Formation en situation de travail | H46: Loi n°2018-771 du 5 sept. 2018
B47: Art. L561-32 CMF | D47: Formation LCB-FT annuelle obligatoire | H47: Code monétaire et financier
B48: Règl. (UE) 2024/1689 art. 4 | D48: AI literacy — Obligation depuis février 2025 | H48: AI Act — Parlement européen
B49: Art. L6315-1 Code du travail | D49: Entretien professionnel biennal | H49: Évaluation compétences + besoins formation

Sheet SAISIE
B1: 📋 MODE D'EMPLOI : Saisir uniquement les cellules jaunes de cet onglet → Tout le reste se calcule automatiquement dans les 3 onglets suivants
B2: ANNEXE 22 — GRILLE DE SUIVI FORMATION CONTINUE
B3: Cabinet 100% numérique — ■ Cases jaunes = saisie manuelle • ■ Cases grises = calcul automatique
B4: Art. 22 Code de déontologie (Décret 2012-432 mod. 2023-388 — éd. janv. 2026) • NPMQ 2025 §21-25 • Règl. (UE) 2024/1689 art. 4 — AI literacy
B6: A. MON CABINET
B7: Paramètre | C7: Valeur | K7: Note / Source
B8: Nom du cabinet | C8: Cabinet X | K8: Raison sociale fictive
B9: N° inscription OEC | C9: IDF-XXXXX | K9: Région + numéro
B10: Expert-comptable titulaire | C10: M. Dupré | K10: Responsable qualité NPMQ §21
B11: Masse salariale brute (€/an) | C11: 185000 | K11: Tous contrats (comptes 641)
B12: OPCO de branche | C12: OPCO Atlas | K12: CCN 3020 IDCC 0787 — Accord n°48 du 05/12/2025 (minima +2,9% en 2026)
B13: Plafond PDC annuel OPCO (€ HT) | C13: 2800 | K13: OPCO Atlas 2026 : 2 800€ HT/an (<11 sal.) — opco-atlas.fr MAJ 05/01/2026
B14: Plafond stage DEC/CAC (€/sal/an) | C14: 1000 | K14: OPCO Atlas 2026 : 1 000€ HT/sal/an — opco-atlas.fr MAJ 05/01/2026
B16: EFFECTIF | C16: 4 | D16: ETP | E16: =SUM(F20:F29) -> 3.8 | F16: Taux hor. complet | G16: =IF(E16=0,0,ROUND(C11/(E16*1607)*1.45*1.18,0)) -> 52 | K16: Formule : Masse salariale brute / (ETP × 1 607h) × 1,45 × 1,18. Soit : 185 000€ / (3,8 × 1 607) × 1,45 × 1,18 ≈ 52€/h. Charges patronales 2026 : 43-45% (coef. 1,45 — URSSAF / LFSS 2026, hausse cotis. vieillesse déplaf. 2,02→2,11%). Frais structure : 18% (coef. 1,18 — benchmark OMECA S2 2025 cabinets <10 sal.).
B18: B. MES COLLABORATEURS
B19: Prénom | C19: Nom | D19: Grade | E19: Contrat | F19: ETP | G19: Obj. 3 ans (h) | H19: Heures 2024 | I19: Heures 2025 | J19: Heures S1 2026 | K19: Note
B20: M. | C20: Dupré | D20: Expert-comptable | E20: Gérant TNS | F20: 1 | G20: 120 | H20: 45 | I20: 34.5 | J20: 7 | K20: 120h/3 ans (art. 22 CD éd. janv. 2026). S1 2026 = 7h (LCB-FT 3,5h row 65 + webinaire CROEC-IDF 3,5h row 70). Déficit résiduel comblé après exécution intégrale du plan d'action S2 2026.
B21: Lucas | C21: Martin | D21: Apprenti | E21: Alternance | F21: 0.8 | G21: 40 | H21: 0 | I21: 14 | J21: 3.5 | K21: 40h/an proratisé (apprenti sept. 2025, 0,8 ETP). Non soumis au seuil 60h structurées. Totaux par période = heures homologuées OEC uniquement (17,5h). Les heures non homologuées (onboarding non structuré 7h row 60 + autoformation libre 3h row 69) figurent au registre (section D) mais sont exclues du décompte Art. 22 CD conformément à la règle _REF §8.
B22: Marie | C22: Lambert | D22: Confirmée (5 ans) | E22: CDI | F22: 1 | G22: 120 | H22: 42 | I22: 31.5 | J22: 3.5 | K22: 120h/3 ans. Heures homologuées OEC : 77h/77h = 100%.
B23: Thomas | C23: Renaud | D23: Junior (1 an) | E23: CDI | F23: 1 | G23: 120 | H23: 28 | I23: 17.5 | J23: 3.5 | K23: 120h/3 ans. Heures homologuées OEC : 49h/49h = 100%.
C30: Équipe | K30: Valeur fixe pour les formations collectives (ne pas supprimer)
B31: C. ÉVALUATIONS DES COMPÉTENCES (note 1 à 5) | K31: BARÈME : 1=Découverte (notions théoriques) | 2=Initiation (pratique supervisée) | 3=Pratique courante (autonomie avec contrôle) | 4=Maîtrise (autonomie complète) | 5=Expertise (forme les autres, référent). Évaluation croisée : auto-évaluation collaborateur + validation managériale lors de l'entretien professionnel biennal (art. L6315-1 CT). Méthode : NPMQ 2025 §23 — « évaluation des compétences et besoins en formation ».
B32: Domaine | C32: =IF(SAISIE!C20="","",LEFT(SAISIE!B20,1)&". "&SAISIE!C20) -> M. Dupré | D32: =IF(SAISIE!C21="","",LEFT(SAISIE!B21,1)&". "&SAISIE!C21) -> L. Martin | E32: =IF(SAISIE!C22="","",LEFT(SAISIE!B22,1)&". "&SAISIE!C22) -> M. Lambert | F32: =IF(SAISIE!C23="","",LEFT(SAISIE!B23,1)&". "&SAISIE!C23) -> T. Renaud | G32: Cible | H32: Criticité | I32: Coef. | J32: Urgence | K32: CRITICITÉ : Standard (coef.1) = compétence métier classique | Stratégique (coef.2) = différenciation numérique du cabinet | CRITIQUE (coef.3) = obligation réglementaire ou risque pénal/disciplinaire. URGENCE : 1=amélioration continue (>12 mois) | 2=risque opérationnel identifié (6-12 mois) | 3=échéance réglementaire <6 mois (ex: e-facture sept. 2026, AI literacy fév. 2025). Critères fixés lors de la revue annuelle qualité NPMQ §25.
B33: Comptabilité générale | C33: 4 | D33: 1 | E33: 4 | F33: 2 | G33: 4 | H33: Standard | I33: 1 | J33: 1
B34: TVA & Fiscalité | C34: 4 | D34: 1 | E34: 4 | F34: 2 | G34: 4 | H34: Standard | I34: 1 | J34: 1
B35: Paie & Social | C35: 4 | D35: 1 | E35: 3 | F35: 2 | G35: 3 | H35: Standard | I35: 1 | J35: 1
B36: Comptes annuels | C36: 4 | D36: 1 | E36: 4 | F36: 2 | G36: 4 | H36: Standard | I36: 1 | J36: 1
B37: Révision | C37: 4 | D37: 1 | E37: 4 | F37: 2 | G37: 3 | H37: Standard | I37: 1 | J37: 1
B38: Facture électronique (PA) | C38: 3 | D38: 2 | E38: 2 | F38: 2 | G38: 4 | H38: CRITIQUE | I38: 3 | J38: 3
B39: RGPD & Protection données | C39: 3 | D39: 2 | E39: 2 | F39: 2 | G39: 4 | H39: CRITIQUE | I39: 3 | J39: 2
B40: Cybersécurité | C40: 3 | D40: 2 | E40: 2 | F40: 2 | G40: 4 | H40: CRITIQUE | I40: 3 | J40: 2
B41: LCB-FT / Tracfin | C41: 3 | D41: 2 | E41: 3 | F41: 2 | G41: 4 | H41: CRITIQUE | I41: 3 | J41: 1
B42: Outils SaaS / Cloud | C42: 3 | D42: 3 | E42: 2 | F42: 3 | G42: 3 | H42: Stratégique | I42: 2 | J42: 2
B43: IA & Automatisation | C43: 3 | D43: 2 | E43: 1 | F43: 2 | G43: 4 | H43: CRITIQUE | I43: 3 | J43: 2
B44: Relation client digitale | C44: 4 | D44: 2 | E44: 3 | F44: 2 | G44: 3 | H44: Standard | I44: 1 | J44: 1
... B48: Communication digitale | C48: 3 | D48: 2 | E48: 2 | F48: 2 | G48: 3 | H48: Standard | I48: 1 | J48: 1
B51: D. FORMATIONS RÉALISÉES
B52: Date | C52: Collaborateur (Nom) | D52: Domaine | E52: Intitulé | F52: Organisme | G52: Durée (h) | H52: Coût HT € | I52: Homol. OEC | J52: Art. 22
B53: 2024 (récap.) | C53: Dupré | D53: Multi | E53: LF2024, LCB-FT, Congrès OEC, ANSSI, IFRS (5 formations) | F53: CFPC / CNOEC / Lefebvre Dalloz | G53: 45 | H53: 1490 | I53: Oui | J53: Oui | K53: Formations antérieures justifiées par : attestations OF transmises à l'embauche, historique CPF (moncompteformation.gouv.fr), certificats CFPC/CROEC. Pièces classées en GED cabinet (cf. checklist FICHE QUALITÉ — « Attestations de formation »).
B54: 2024 (récap.) | C54: Lambert | D54: Multi | E54: Compta, TVA intl, Paie, SaaS, LCB-FT, RGPD, Révision IA (7 form.) | F54: CFPC / Lefebvre Dalloz / ENOES | G54: 42 | H54: 2390 | I54: Oui | J54: Oui
B55: 2024 (récap.) | C55: Renaud | D55: Multi | E55: French GAAP, Fiscalité, Prise en main SaaS (3 formations) | F55: ENOES / CFPC / Interne | G55: 28 | H55: 1550 | I55: Oui | J55: Oui | K55: Les 28h incluent 7h de prise en main SaaS initialement non structurée, requalifiée en AFEST interne (art. L6313-2 CT) : objectifs pédagogiques, programme et évaluation formalisés a posteriori lors de l'intégration au cabinet en 09/2025. Conforme NPMQ §22 (formalisation des apprentissages).
B56: Jan.-Août 2025 | C56: Dupré | D56: Multi | E56: E-facture, LF2025, IA intro, Parcours créateur (4 formations) | F56: CFPC / Lefebvre / OEC | G56: 27.5 | H56: 1690 | I56: Oui | J56: Oui
B57: Jan.-Août 2025 | C57: Lambert | D57: Multi | E57: LF2025, E-facture prépa, Arrêté comptes, Cloud collab. (4 form.) | F57: Lefebvre / CFPC / Qualiopi | G57: 24.5 | H57: 1840 | I57: Oui | J57: Oui
B58: Jan.-Août 2025 | C58: Renaud | D58: Multi | E58: Révision comptes, Paie et DSN niveau 1 (2 formations) | F58: ENOES / CFPC | G58: 10.5 | H58: 1000 | I58: Oui | J58: Oui
B59: --- Formations post-création cabinet (sept. 2025 →) ---
B60: 15/09/2025 | C60: Martin | D60: Intégration | E60: Parcours onboarding cabinet | F60: Interne (non structuré) | G60: 7 | H60: 0 | I60: Non | J60: Non *
B61: 10/10/2025 | C61: Lambert | D61: Fiscalité | E61: Actualité LF 2026 | F61: Lefebvre Dalloz | G61: 7 | H61: 890 | I61: Oui | J61: Oui
B62: 15/10/2025 | C62: Dupré | D62: Déontologie | E62: Congrès CROEC 2025 | F62: CROEC Île-de-France | G62: 7 | H62: 0 | I62: Oui | J62: Oui
B63: 05/11/2025 | C63: Martin | D63: Comptabilité | E63: Révision des fondamentaux | F63: ENOES | G63: 14 | H63: 1450 | I63: Oui | J63: Oui
B64: 15/11/2025 | C64: Renaud | D64: E-facture | E64: Réforme FE 2026 | F64: CNOEC (CFPC) | G64: 7 | H64: 350 | I64: Oui | J64: Oui
B65: 12/01/2026 | C65: Dupré | D65: LCB-FT | E65: Vigilance renforcée 2026 | F65: CFPC / CSOEC | G65: 3.5 | H65: 150 | I65: Oui | J65: Oui
B66: 12/01/2026 | C66: Lambert | D66: LCB-FT | E66: Vigilance renforcée 2026 | F66: CFPC / CSOEC | G66: 3.5 | H66: 150 | I66: Oui | J66: Oui
B67: 12/01/2026 | C67: Renaud | D67: LCB-FT | E67: Vigilance renforcée 2026 | F67: CFPC / CSOEC | G67: 3.5 | H67: 150 | I67: Oui | J67: Oui
B68: 12/01/2026 | C68: Martin | D68: LCB-FT | E68: Vigilance renforcée 2026 | F68: CFPC / CSOEC | G68: 3.5 | H68: 150 | I68: Oui | J68: Oui
B69: 25/01/2026 | C69: Martin | D69: IA | E69: Prompt engineering (auto) | F69: Autoformation libre | G69: 3 | H69: 0 | I69: Non | J69: Non *
B70: 10/02/2026 | C70: Dupré | D70: Numérique | E70: Transformation numérique du cabinet EC | F70: CROEC Île-de-France (webinaire gratuit) | G70: 3.5 | H70: 0 | I70: Oui | J70: Oui | K70: Webinaire CROEC-IDF gratuit — Homologué formation continue OEC. Distanciel synchrone.
B73: SOUS-TOTAUX FORMATIONS RÉALISÉES | G73: =SUM(G53:G70) -> 240 | H73: =SUM(H53:H70) -> 13250 | J73: * Non comptabilisable Art. 22 CD
B75: E. FORMATIONS PLANIFIÉES (S2 2026) | K75: CHARGE FORMATION RENAUD : 56h ext. planifiées dont 17,5h distancielles asynchrones (campusAtlas, microlearningAtlas, PIX I) = 0 jour d'absence. Formations synchrones : 38,5h = 5,5 jours sur S2 2026 (soit 1 jour/mois). Compatible avec planning production junior (NPMQ §21 — formation = investissement, pas coût).
B76: Formation | C76: Collaborateur (Nom) | D76: Durée (h) | E76: Coût HT € | F76: Organisme | G76: Domaine | H76: Type gains | I76: Impact estimé | J76: Mois prévu
B77: IA dans l'exercice professionnel | C77: Lambert | D77: 14 | E77: 890 | F77: CFPC (catalogue 2026) | G77: IA | H77: Productivité | I77: ≈ 2h/sem économisées | J77: Sept. | K77: Obligation AI literacy art. 4 Règl. (UE) 2024/1689 — échéance fév. 2025
B78: Cybersécurité des cabinets | C78: Lambert | D78: 7 | E78: 650 | F78: ANSSI / Cybermalveillance | G78: Cyber | H78: Prévention | I78: Réduction risque incident | J78: Oct.
B79: RGPD — Conformité cabinet EC | C79: Renaud | D79: 7 | E79: 1200 | F79: Impact RGPD | G79: RGPD | H79: Conformité | I79: Mise en conformité CNIL | J79: Nov.
B80: E-facture 2026 — Réforme PA | C80: Dupré | D80: 14 | E80: 890 | F80: CFPC (catalogue 2026) | G80: E-facture | H80: Productivité | I80: ≈ 1h/sem économisées | J80: Oct.
B81: LCB-FT vigilance annuelle | C81: Équipe | D81: 3.5 | E81: 600 | F81: CFPC / CSOEC | G81: LCB-FT | H81: Conformité | I81: Obligation Art. L561-32 | J81: Juil.
B82: Déontologie & normes 2026 | C82: Dupré | D82: 7 | E82: 350 | F82: CROEC Île-de-France | G82: Déontologie | H82: Conformité | I82: Mise à jour annuelle | J82: Août
B83: Signature électronique avancée | C83: Renaud | D83: 7 | E83: 450 | F83: Organisme Qualiopi | G83: Signature | H83: Compétence | I83: eIDAS 2.0 / qualification | J83: Nov.
B84: GED & archivage probant | C84: Renaud | D84: 7 | E84: 550 | F84: Organisme Qualiopi | G84: GED | H84: Compétence | I84: NF Z42-013 | J84: Déc.
B85: Comptabilité avancée — Arrêté et consolidation | C85: Renaud | D85: 14 | E85: 890 | F85: CFPC (catalogue 2026) | G85: Comptabilité | H85: Compétence | I85: Révision + comptes annuels | J85: Juil. | K85: Formation distancielle asynchrone : intégrable dans le temps de travail sans absence. Aucun coût d'opportunité production.
B86: Outils SaaS avancés — Automatisation flux | C86: Renaud | D86: 7 | E86: 0 | F86: campusAtlas (100% pris en charge) | G86: SaaS | H86: Productivité | I86: Gratuit Atlas <50 sal. | J86: Oct. | K86: Distanciel asynchrone — campusAtlas 100% (<50 sal.)
B87: Communication digitale — Relation client | C87: Renaud | D87: 7 | E87: 0 | F87: microlearningAtlas | G87: Communication | H87: Compétence | I87: Parcours gratuit 1-49 sal. | J87: Sept. | K87: Distanciel asynchrone — microlearningAtlas gratuit 1-49 sal.
B88: Veille réglementaire IA — AI Act application | C88: Dupré | D88: 7 | E88: 0 | F88: Webinaire CNOEC (gratuit inscrit) | G88: IA | H88: Conformité | I88: Art. 4 Règl. UE 2024/1689 | J88: Sept.
B89: PIX I Atlas — Évaluation compétences numériques | C89: Renaud | D89: 3.5 | E89: 0 | F89: PIX I Atlas (100% gratuit, toutes tailles) | G89: SaaS | H89: Compétence | I89: Gratuit — opco-atlas.fr MAJ 05/01/2026 | J89: Juil. | K89: En ligne, asynchrone — PIX I Atlas opco-atlas.fr
B90: SOUS-TOTAUX FORMATIONS PLANIFIÉES | D90: =SUM(D77:D89) -> 105 | E90: =SUM(E77:E89) -> 6470
B92: F. FORMATIONS INTERNES STRUCTURÉES (AFEST / Tutorat) — 7 sessions | K92: Principe : formations ext. → montée compétences → cascade interne AFEST. Éco. collectives 1× coût catalogue.
B93: AFEST : Art. L6313-2 Code du travail (Loi 2018-771) — Atlas 2026 : 20€ HT/h max 150h dans plafond PDC. microlearningAtlas cybersécurité 100% gratuit 1-49 sal.
B94: Formateur (Nom) | C94: Apprenant (Nom) | D94: Domaine | E94: Durée (h) | F94: Éco. vs externe € * | K94: * « Éco. vs externe » = coût catalogue pour 1 session. Sessions collectives : éco. sur 1ère ligne, 0€ sur les suivantes.
B95: Martin | C95: Lambert | D95: IA & Prompting SaaS — Mentorat inversé | E95: 14 | F95: 890 | K95: Mentorat inversé : compétences IA natives (DSCG option IA). Art. L6313-2 CT.
B96: Lambert | C96: Martin | D96: Révision comptable — Tutorat | E96: 14 | F96: 980 | K96: Tutorat classique : Lambert (5 ans exp.) transmet à Martin (apprenti).
B97: Lambert | C97: Renaud | D97: Fiscalité appliquée — Cas pratiques | E97: 7 | F97: 450 | K97: Lambert (4/5 TVA) forme Renaud (2/5). Cas réels LF 2026.
B98: Lambert | C98: Renaud | D98: IA appliquée — Prompts comptabilité | E98: 7 | F98: 890 | K98: Cascade post-formation : Lambert (1→3/5 après 14h ext. row 77) transmet à Renaud. Art. L6313-2 CT.
B99: Lambert | C99: Dupré | D99: Cybersécurité — Bonnes pratiques cabinet | E99: 3.5 | F99: 325 | K99: Session collective (1→3). Cascade : Lambert (2→3/5 après 7h ext. row 78) forme l'équipe. Éco. 1×.
B100: Lambert | C100: Martin | D100: Cybersécurité — Bonnes pratiques cabinet | E100: 3.5 | F100: 0 | K100: → Même session collective que row 99.
B101: Lambert | C101: Renaud | D101: Cybersécurité — Bonnes pratiques cabinet | E101: 3.5 | F101: 0 | K101: → Même session collective que row 99.
B102: Dupré | C102: Martin | D102: E-facture PA — Cascade post-formation | E102: 3.5 | F102: 225 | K102: Cascade post-formation : Dupré (3→4/5 après 14h ext.) forme l'équipe. Éco. 1×.
B103: Dupré | C103: Lambert | D103: E-facture PA — Cascade post-formation | E103: 3.5 | F103: 0 | K103: → Même session collective que row 102.
B104: Dupré | C104: Renaud | D104: E-facture PA — Cascade post-formation | E104: 3.5 | F104: 0 | K104: → Même session collective que row 102.
B105: Dupré | C105: Martin | D105: Déontologie — Actualités normes 2026 | E105: 3.5 | F105: 175 | K105: Dupré (4/5 déontologie) actualise l'équipe. Éco. 1×.
B106: Dupré | C106: Lambert | D106: Déontologie — Actualités normes 2026 | E106: 3.5 | F106: 0 | K106: → Même session collective que row 105.
B107: Dupré | C107: Renaud | D107: Déontologie — Actualités normes 2026 | E107: 3.5 | F107: 0 | K107: → Même session collective que row 105.
B109: TOTAL ÉCONOMIES FORMATIONS INTERNES | C109: Texte bleu = valeur saisie (input) | E109: =SUM(E95:E107) -> 73.5 | F109: =SUM(F95:F107) -> 3935 | K109: E109 = heures-apprenant cumulées (13 binômes). Charge formateur réelle = 52,5h (7 sessions, cf. row 110).
B110: dont heures-formateur (7 sessions distinctes) | E110: 52.5 | K110: Sessions collectives (rows 99-101, 102-104, 105-107) : 1 session = 1 créneau formateur pour 3 apprenants.

Sheet DIAGNOSTIC
B2: DIAGNOSTIC AUTOMATIQUE — FORMATION CONTINUE
B3: ⚠️ Cet onglet est 100% automatisé depuis l'onglet SAISIE — Ne rien modifier ici
B5: INDICATEURS CLÉS
B6: Effectif ETP | D6: Conformes | F6: Heures manquantes | H6: Taux hor. complet
B7: =SAISIE!E16 -> 3.8 | D7: =COUNTIF(G13:G22,"✅*")&" / "&COUNTIF(B13:B22,"?*") -> 0 / 4 | F7: =ABS(SUMIF(F13:F22,"<0")) -> 170 | H7: ="≈ "&SAISIE!G16&" €/h" -> ≈ 52 €/h
B10: A. CONFORMITÉ FORMATION CONTINUE (Art. 22 Code de déontologie)
B11: Obligation : 120h/3 ans glissants (≈ 40h/an) — Contrôle qualité OEC
B12: Collaborateur | C12: Grade | D12: Total 3 ans (h) | E12: Objectif (h) | F12: Écart (h) | G12: Statut | H12: Action requise
B13: =IF(SAISIE!C20="","",LEFT(SAISIE!B20,1)&". "&SAISIE!C20) -> M. Dupré | C13: =IF(SAISIE!C20="","",SAISIE!D20) -> Expert-comptable | D13: =IF(SAISIE!C20="","",SAISIE!H20+SAISIE!I20+SAISIE!J20) -> 86.5 | E13: =IF(SAISIE!C20="","",SAISIE!G20) -> 120 | F13: =IF(SAISIE!C20="","",D13-E13) -> -33.5 | G13: =IF(SAISIE!C20="","",IF(F13>=0,"✅ Conforme",IF(F13>=-5,"🟠 Vigilance","🔴 Non conforme"))) -> 🔴 Non conforme | H13: =IF(SAISIE!C20="","",IF(F13>=0,"—","Planifier "&TEXT(ABS(F13),"0.#")&"h avant 31/12/2026")) -> Planifier 3.4h avant 31/12/2026
B14: =IF(SAISIE!C21="","",LEFT(SAISIE!B21,1)&". "&SAISIE!C21) -> L. Martin | C14: =IF(SAISIE!C21="","",SAISIE!D21) -> Apprenti | D14: =IF(SAISIE!C21="","",SAISIE!H21+SAISIE!I21+SAISIE!J21) -> 17.5 | E14: =IF(SAISIE!C21="","",SAISIE!G21) -> 40 | F14: =IF(SAISIE!C21="","",D14-E14) -> -22.5 | G14: =IF(SAISIE!C21="","",IF(F14>=0,"✅ Conforme",IF(F14>=-5,"🟠 Vigilance","🔴 Non conforme"))) -> 🔴 Non conforme | H14: =IF(SAISIE!C21="","",IF(F14>=0,"—","Planifier "&TEXT(ABS(F14),"0.#")&"h avant 31/12/2026")) -> Planifier 2.3h avant 31/12/2026
B15: =IF(SAISIE!C22="","",LEFT(SAISIE!B22,1)&". "&SAISIE!C22) -> M. Lambert | C15: =IF(SAISIE!C22="","",SAISIE!D22) -> Confirmée (5 ans) | D15: =IF(SAISIE!C22="","",SAISIE!H22+SAISIE!I22+SAISIE!J22) -> 77 | E15: =IF(SAISIE!C22="","",SAISIE!G22) -> 120 | F15: =IF(SAISIE!C22="","",D15-E15) -> -43 | G15: =IF(SAISIE!C22="","",IF(F15>=0,"✅ Conforme",IF(F15>=-5,"🟠 Vigilance","🔴 Non conforme"))) -> 🔴 Non conforme | H15: =IF(SAISIE!C22="","",IF(F15>=0,"—","Planifier "&TEXT(ABS(F15),"0.#")&"h avant 31/12/2026")) -> Planifier 4.3h avant 31/12/2026
B16: =IF(SAISIE!C23="","",LEFT(SAISIE!B23,1)&". "&SAISIE!C23) -> T. Renaud | C16: =IF(SAISIE!C23="","",SAISIE!D23) -> Junior (1 an) | D16: =IF(SAISIE!C23="","",SAISIE!H23+SAISIE!I23+SAISIE!J23) -> 49 | E16: =IF(SAISIE!C23="","",SAISIE!G23) -> 120 | F16: =IF(SAISIE!C23="","",D16-E16) -> -71 | G16: =IF(SAISIE!C23="","",IF(F16>=0,"✅ Conforme",IF(F16>=-5,"🟠 Vigilance","🔴 Non conforme"))) -> 🔴 Non conforme | H16: =IF(SAISIE!C23="","",IF(F16>=0,"—","Planifier "&TEXT(ABS(F16),"0.#")&"h avant 31/12/2026")) -> Planifier 7.1h avant 31/12/2026
B17: =IF(SAISIE!C24="","",LEFT(SAISIE!B24,1)&". "&SAISIE!C24) | C17: =IF(SAISIE!C24="","",SAISIE!D24) | D17: =IF(SAISIE!C24="","",SAISIE!H24+SAISIE!I24+SAISIE!J24) | E17: =IF(SAISIE!C24="","",SAISIE!G24) | F17: =IF(SAISIE!C24="","",D17-E17) | G17: =IF(SAISIE!C24="","",IF(F17>=0,"✅ Conforme",IF(F17>=-5,"🟠 Vigilance","🔴 Non conforme"))) | H17: =IF(SAISIE!C24="","",IF(F17>=0,"—","Planifier "&TEXT(ABS(F17),"0.#")&"h avant 31/12/2026"))
B18: =IF(SAISIE!C25="","",LEFT(SAISIE!B25,1)&". "&SAISIE!C25) | C18: =IF(SAISIE!C25="","",SAISIE!D25) | D18: =IF(SAISIE!C25="","",SAISIE!H25+SAISIE!I25+SAISIE!J25) | E18: =IF(SAISIE!C25="","",SAISIE!G25) | F18: =IF(SAISIE!C25="","",D18-E18) | G18: =IF(SAISIE!C25="","",IF(F18>=0,"✅ Conforme",IF(F18>=-5,"🟠 Vigilance","🔴 Non conforme"))) | H18: =IF(SAISIE!C25="","",IF(F18>=0,"—","Planifier "&TEXT(ABS(F18),"0.#")&"h avant 31/12/2026"))
B19: =IF(SAISIE!C26="","",LEFT(SAISIE!B26,1)&". "&SAISIE!C26) | C19: =IF(SAISIE!C26="","",SAISIE!D26) | D19: =IF(SAISIE!C26="","",SAISIE!H26+SAISIE!I26+SAISIE!J26) | E19: =IF(SAISIE!C26="","",SAISIE!G26) | F19: =IF(SAISIE!C26="","",D19-E19) | G19: =IF(SAISIE!C26="","",IF(F19>=0,"✅ Conforme",IF(F19>=-5,"🟠 Vigilance","🔴 Non conforme"))) | H19: =IF(SAISIE!C26="","",IF(F19>=0,"—","Planifier "&TEXT(ABS(F19),"0.#")&"h avant 31/12/2026"))
B20: =IF(SAISIE!C27="","",LEFT(SAISIE!B27,1)&". "&SAISIE!C27) | C20: =IF(SAISIE!C27="","",SAISIE!D27) | D20: =IF(SAISIE!C27="","",SAISIE!H27+SAISIE!I27+SAISIE!J27) | E20: =IF(SAISIE!C27="","",SAISIE!G27) | F20: =IF(SAISIE!C27="","",D20-E20) | G20: =IF(SAISIE!C27="","",IF(F20>=0,"✅ Conforme",IF(F20>=-5,"🟠 Vigilance","🔴 Non conforme"))) | H20: =IF(SAISIE!C27="","",IF(F20>=0,"—","Planifier "&TEXT(ABS(F20),"0.#")&"h avant 31/12/2026"))
B21: =IF(SAISIE!C28="","",LEFT(SAISIE!B28,1)&". "&SAISIE!C28) | C21: =IF(SAISIE!C28="","",SAISIE!D28) | D21: =IF(SAISIE!C28="","",SAISIE!H28+SAISIE!I28+SAISIE!J28) | E21: =IF(SAISIE!C28="","",SAISIE!G28) | F21: =IF(SAISIE!C28="","",D21-E21) | G21: =IF(SAISIE!C28="","",IF(F21>=0,"✅ Conforme",IF(F21>=-5,"🟠 Vigilance","🔴 Non conforme"))) | H21: =IF(SAISIE!C28="","",IF(F21>=0,"—","Planifier "&TEXT(ABS(F21),"0.#")&"h avant 31/12/2026"))
B22: =IF(SAISIE!C29="","",LEFT(SAISIE!B29,1)&". "&SAISIE!C29) | C22: =IF(SAISIE!C29="","",SAISIE!D29) | D22: =IF(SAISIE!C29="","",SAISIE!H29+SAISIE!I29+SAISIE!J29) | E22: =IF(SAISIE!C29="","",SAISIE!G29) | F22: =IF(SAISIE!C29="","",D22-E22) | G22: =IF(SAISIE!C29="","",IF(F22>=0,"✅ Conforme",IF(F22>=-5,"🟠 Vigilance","🔴 Non conforme"))) | H22: =IF(SAISIE!C29="","",IF(F22>=0,"—","Planifier "&TEXT(ABS(F22),"0.#")&"h avant 31/12/2026"))
B23: ⚠️ Le taux de conformité est évalué au point d'arrêté (date de saisie). Le cycle triennal glissant (Art. 22 CD) s'achève au 31/12/2026. La conformité intégrale est conditionnée à l'exécution complète du plan d'action (cf. onglet PLAN D'ACTION, section F).
B25: B. CARTOGRAPHIE DES COMPÉTENCES — ÉCARTS vs CIBLE | J25: Moy. équipe | K25: Cible
B26: Domaine | C26: =IF(SAISIE!C20="","",LEFT(SAISIE!B20,1)&". "&SAISIE!C20) -> M. Dupré | D26: =IF(SAISIE!C21="","",LEFT(SAISIE!B21,1)&". "&SAISIE!C21) -> L. Martin | E26: =IF(SAISIE!C22="","",LEFT(SAISIE!B22,1)&". "&SAISIE!C22) -> M. Lambert | F26: =IF(SAISIE!C23="","",LEFT(SAISIE!B23,1)&". "&SAISIE!C23) -> T. Renaud | G26: Cible | H26: Écart moy. | I26: Score prio.
B27: =SAISIE!B33 -> Comptabilité générale | C27: =SAISIE!C33 -> 4 | D27: =SAISIE!D33 -> 1 | E27: =SAISIE!E33 -> 4 | F27: =SAISIE!F33 -> 2 | G27: =SAISIE!G33 -> 4 | H27: =AVERAGE(C27:F27)-G27 -> -1.25 | I27: =IF(H27>=0,0,SAISIE!I33*ABS(H27)*SAISIE!J33+(16-ROW()+27)/10000) -> 1.2516 | J27: =AVERAGE(C27:F27) -> 2.75 | K27: =G27 -> 4
B28: =SAISIE!B34 -> TVA & Fiscalité | C28: =SAISIE!C34 -> 4 | D28: =SAISIE!D34 -> 1 | E28: =SAISIE!E34 -> 4 | F28: =SAISIE!F34 -> 2 | G28: =SAISIE!G34 -> 4 | H28: =AVERAGE(C28:F28)-G28 -> -1.25 | I28: =IF(H28>=0,0,SAISIE!I34*ABS(H28)*SAISIE!J34+(16-ROW()+27)/10000) -> 1.2515 | J28: =AVERAGE(C28:F28) -> 2.75 | K28: =G28 -> 4
B29: =SAISIE!B35 -> Paie & Social | C29: =SAISIE!C35 -> 4 | D29: =SAISIE!D35 -> 1 | E29: =SAISIE!E35 -> 3 | F29: =SAISIE!F35 -> 2 | G29: =SAISIE!G35 -> 3 | H29: =AVERAGE(C29:F29)-G29 -> -0.5 | I29: =IF(H29>=0,0,SAISIE!I35*ABS(H29)*SAISIE!J35+(16-ROW()+27)/10000) -> 0.5014 | J29: =AVERAGE(C29:F29) -> 2.5 | K29: =G29 -> 3
B30: =SAISIE!B36 -> Comptes annuels | C30: =SAISIE!C36 -> 4 | D30: =SAISIE!D36 -> 1 | E30: =SAISIE!E36 -> 4 | F30: =SAISIE!F36 -> 2 | G30: =SAISIE!G36 -> 4 | H30: =AVERAGE(C30:F30)-G30 -> -1.25 | I30: =IF(H30>=0,0,SAISIE!I36*ABS(H30)*SAISIE!J36+(16-ROW()+27)/10000) -> 1.2513 | J30: =AVERAGE(C30:F30) -> 2.75 | K30: =G30 -> 4
B31: =SAISIE!B37 -> Révision | C31: =SAISIE!C37 -> 4 | D31: =SAISIE!D37 -> 1 | E31: =SAISIE!E37 -> 4 | F31: =SAISIE!F37 -> 2 | G31: =SAISIE!G37 -> 3 | H31: =AVERAGE(C31:F31)-G31 -> -0.25 | I31: =IF(H31>=0,0,SAISIE!I37*ABS(H31)*SAISIE!J37+(16-ROW()+27)/10000) -> 0.2512 | J31: =AVERAGE(C31:F31) -> 2.75 | K31: =G31 -> 3
B32: =SAISIE!B38 -> Facture électronique (PA) | C32: =SAISIE!C38 -> 3 | D32: =SAISIE!D38 -> 2 | E32: =SAISIE!E38 -> 2 | F32: =SAISIE!F38 -> 2 | G32: =SAISIE!G38 -> 4 | H32: =AVERAGE(C32:F32)-G32 -> -1.75 | I32: =IF(H32>=0,0,SAISIE!I38*ABS(H32)*SAISIE!J38+(16-ROW()+27)/10000) -> 15.7511 | J32: =AVERAGE(C32:F32) -> 2.25 | K32: =G32 -> 4
B33: =SAISIE!B39 -> RGPD & Protection données | C33: =SAISIE!C39 -> 3 | D33: =SAISIE!D39 -> 2 | E33: =SAISIE!E39 -> 2 | F33: =SAISIE!F39 -> 2 | G33: =SAISIE!G39 -> 4 | H33: =AVERAGE(C33:F33)-G33 -> -1.75 | I33: =IF(H33>=0,0,SAISIE!I39*ABS(H33)*SAISIE!J39+(16-ROW()+27)/10000) -> 10.501 | J33: =AVERAGE(C33:F33) -> 2.25 | K33: =G33 -> 4
B34: =SAISIE!B40 -> Cybersécurité | C34: =SAISIE!C40 -> 3 | D34: =SAISIE!D40 -> 2 | E34: =SAISIE!E40 -> 2 | F34: =SAISIE!F40 -> 2 | G34: =SAISIE!G40 -> 4 | H34: =AVERAGE(C34:F34)-G34 -> -1.75 | I34: =IF(H34>=0,0,SAISIE!I40*ABS(H34)*SAISIE!J40+(16-ROW()+27)/10000) -> 10.5009 | J34: =AVERAGE(C34:F34) -> 2.25 | K34: =G34 -> 4
B35: =SAISIE!B41 -> LCB-FT / Tracfin | C35: =SAISIE!C41 -> 3 | D35: =SAISIE!D41 -> 2 | E35: =SAISIE!E41 -> 3 | F35: =SAISIE!F41 -> 2 | G35: =SAISIE!G41 -> 4 | H35: =AVERAGE(C35:F35)-G35 -> -1.5 | I35: =IF(H35>=0,0,SAISIE!I41*ABS(H35)*SAISIE!J41+(16-ROW()+27)/10000) -> 4.5008 | J35: =AVERAGE(C35:F35) -> 2.5 | K35: =G35 -> 4
B36: =SAISIE!B42 -> Outils SaaS / Cloud | C36: =SAISIE!C42 -> 3 | D36: =SAISIE!D42 -> 3 | E36: =SAISIE!E42 -> 2 | F36: =SAISIE!F42 -> 3 | G36: =SAISIE!G42 -> 3 | H36: =AVERAGE(C36:F36)-G36 -> -0.25 | I36: =IF(H36>=0,0,SAISIE!I42*ABS(H36)*SAISIE!J42+(16-ROW()+27)/10000) -> 1.0007 | J36: =AVERAGE(C36:F36) -> 2.75 | K36: =G36 -> 3
B37: =SAISIE!B43 -> IA & Automatisation | C37: =SAISIE!C43 -> 3 | D37: =SAISIE!D43 -> 2 | E37: =SAISIE!E43 -> 1 | F37: =SAISIE!F43 -> 2 | G37: =SAISIE!G43 -> 4 | H37: =AVERAGE(C37:F37)-G37 -> -2 | I37: =IF(H37>=0,0,SAISIE!I43*ABS(H37)*SAISIE!J43+(16-ROW()+27)/10000) -> 12.0006 | J37: =AVERAGE(C37:F37) -> 2 | K37: =G37 -> 4
B38: =SAISIE!B44 -> Relation client digitale | C38: =SAISIE!C44 -> 4 | D38: =SAISIE!D44 -> 2 | E38: =SAISIE!E44 -> 3 | F38: =SAISIE!F44 -> 2 | G38: =SAISIE!G44 -> 3 | H38: =AVERAGE(C38:F38)-G38 -> -0.25 | I38: =IF(H38>=0,0,SAISIE!I44*ABS(H38)*SAISIE!J44+(16-ROW()+27)/10000) -> 0.2505 | J38: =AVERAGE(C38:F38) -> 2.75 | K38: =G38 -> 3
... B42: =SAISIE!B48 -> Communication digitale | C42: =SAISIE!C48 -> 3 | D42: =SAISIE!D48 -> 2 | E42: =SAISIE!E48 -> 2 | F42: =SAISIE!F48 -> 2 | G42: =SAISIE!G48 -> 3 | H42: =AVERAGE(C42:F42)-G42 -> -0.75 | I42: =IF(H42>=0,0,SAISIE!I48*ABS(H42)*SAISIE!J48+(16-ROW()+27)/10000) -> 0.7501 | J42: =AVERAGE(C42:F42) -> 2.25 | K42: =G42 -> 3
B45: C. TOP 5 PRIORITÉS FORMATION (scoring = Coef. × |Écart| × Urgence)
B46: Rang | C46: Domaine | D46: Score | E46: Écart moy. | F46: Criticité | G46: Urgence | H46: Niveau
B47: 1 | C47: =IFERROR(INDEX($B$27:$B$42,MATCH(LARGE($I$27:$I$42,1),$I$27:$I$42,0)),"—") -> Facture électronique (PA) | D47: =IFERROR(ROUND(LARGE($I$27:$I$42,1),1),0) -> 15.8 | E47: =IFERROR(INDEX($H$27:$H$42,MATCH(LARGE($I$27:$I$42,1),$I$27:$I$42,0)),0) -> -1.75 | F47: =IFERROR(INDEX(SAISIE!$H$33:$H$48,MATCH(LARGE($I$27:$I$42,1),$I$27:$I$42,0)),"—") -> CRITIQUE | G47: =IFERROR(INDEX(SAISIE!$J$33:$J$48,MATCH(LARGE($I$27:$I$42,1),$I$27:$I$42,0)),0) -> 3 | H47: =IF(D47>=8,"🔴 URGENT",IF(D47>=4,"🟠 HAUTE",IF(D47>0,"🟡 MOYENNE","—"))) -> 🔴 URGENT
B48: 2 | C48: =IFERROR(INDEX($B$27:$B$42,MATCH(LARGE($I$27:$I$42,2),$I$27:$I$42,0)),"—") -> IA & Automatisation | D48: =IFERROR(ROUND(LARGE($I$27:$I$42,2),1),0) -> 12 | E48: =IFERROR(INDEX($H$27:$H$42,MATCH(LARGE($I$27:$I$42,2),$I$27:$I$42,0)),0) -> -2 | F48: =IFERROR(INDEX(SAISIE!$H$33:$H$48,MATCH(LARGE($I$27:$I$42,2),$I$27:$I$42,0)),"—") -> CRITIQUE | G48: =IFERROR(INDEX(SAISIE!$J$33:$J$48,MATCH(LARGE($I$27:$I$42,2),$I$27:$I$42,0)),0) -> 2 | H48: =IF(D48>=8,"🔴 URGENT",IF(D48>=4,"🟠 HAUTE",IF(D48>0,"🟡 MOYENNE","—"))) -> 🔴 URGENT
B49: 3 | C49: =IFERROR(INDEX($B$27:$B$42,MATCH(LARGE($I$27:$I$42,3),$I$27:$I$42,0)),"—") -> RGPD & Protection données | D49: =IFERROR(ROUND(LARGE($I$27:$I$42,3),1),0) -> 10.5 | E49: =IFERROR(INDEX($H$27:$H$42,MATCH(LARGE($I$27:$I$42,3),$I$27:$I$42,0)),0) -> -1.75 | F49: =IFERROR(INDEX(SAISIE!$H$33:$H$48,MATCH(LARGE($I$27:$I$42,3),$I$27:$I$42,0)),"—") -> CRITIQUE | G49: =IFERROR(INDEX(SAISIE!$J$33:$J$48,MATCH(LARGE($I$27:$I$42,3),$I$27:$I$42,0)),0) -> 2 | H49: =IF(D49>=8,"🔴 URGENT",IF(D49>=4,"🟠 HAUTE",IF(D49>0,"🟡 MOYENNE","—"))) -> 🔴 URGENT
B50: 4 | C50: =IFERROR(INDEX($B$27:$B$42,MATCH(LARGE($I$27:$I$42,4),$I$27:$I$42,0)),"—") -> Cybersécurité | D50: =IFERROR(ROUND(LARGE($I$27:$I$42,4),1),0) -> 10.5 | E50: =IFERROR(INDEX($H$27:$H$42,MATCH(LARGE($I$27:$I$42,4),$I$27:$I$42,0)),0) -> -1.75 | F50: =IFERROR(INDEX(SAISIE!$H$33:$H$48,MATCH(LARGE($I$27:$I$42,4),$I$27:$I$42,0)),"—") -> CRITIQUE | G50: =IFERROR(INDEX(SAISIE!$J$33:$J$48,MATCH(LARGE($I$27:$I$42,4),$I$27:$I$42,0)),0) -> 2 | H50: =IF(D50>=8,"🔴 URGENT",IF(D50>=4,"🟠 HAUTE",IF(D50>0,"🟡 MOYENNE","—"))) -> 🔴 URGENT
B51: 5 | C51: =IFERROR(INDEX($B$27:$B$42,MATCH(LARGE($I$27:$I$42,5),$I$27:$I$42,0)),"—") -> Signature électronique | D51: =IFERROR(ROUND(LARGE($I$27:$I$42,5),1),0) -> 5 | E51: =IFERROR(INDEX($H$27:$H$42,MATCH(LARGE($I$27:$I$42,5),$I$27:$I$42,0)),0) -> -1.25 | F51: =IFERROR(INDEX(SAISIE!$H$33:$H$48,MATCH(LARGE($I$27:$I$42,5),$I$27:$I$42,0)),"—") -> Stratégique | G51: =IFERROR(INDEX(SAISIE!$J$33:$J$48,MATCH(LARGE($I$27:$I$42,5),$I$27:$I$42,0)),0) -> 2 | H51: =IF(D51>=8,"🔴 URGENT",IF(D51>=4,"🟠 HAUTE",IF(D51>0,"🟡 MOYENNE","—"))) -> 🟠 HAUTE
B53: D. SYNTHÈSE ET ENJEUX
B54: Situation au point d'arrêté : | D54: =D7 -> 0 / 4 | E54: collaborateur(s) conforme(s) sur le cycle triennal en cours
B55: Situation après plan d'action : | D55: =COUNTIF('PLAN D''ACTION'!H64:H67,"✅*")&" / "&COUNTA('PLAN D''ACTION'!B64:B67) -> 4 / 4 | E55: =IF(COUNTIF('PLAN D''ACTION'!H64:H67,"✅*")=COUNTA('PLAN D''ACTION'!B64:B67),"→ Conformité intégrale projetée au 31/12/2026","→ Conformité partielle — actions complémentaires requises") -> → Conformité intégrale projetée au 31/12/2026
B56: Investissement net : | D56: ='PLAN D''ACTION'!D51 -> -1265 | E56: → Gain net : financement OPCO + AFEST > coûts catalogue
B58: Enjeux en cas de non-conformité :
B59: ⚠️ Disciplinaire | D59: Chambre régionale de discipline (Ord. 19 sept. 1945, art. 49 et suiv.) — Manquement à l'Art. 22 CD : avertissement, blâme, suspension temporaire
B60: ⚠️ Contrôle qualité | D60: NPMQ §25 — Contrôle défavorable, plan de mise en conformité imposé par le CROEC
B61: ⚠️ Responsabilité civile | D61: Défaut de compétence du collaborateur = risque de mise en cause RC professionnelle
B62: ⚠️ Perte de marché | D62: Déficit e-facture/IA → incapacité à répondre aux besoins clients dès septembre 2026
B64: Échéances critiques :
B65: Sept. 2026 | D65: Réception e-factures obligatoire (Art. 289 bis CGI) — Toute l'équipe concernée
B66: Fév. 2025 (en cours) | D66: AI literacy applicable (Règl. UE 2024/1689 art. 4) — Sensibilisation à formaliser
B67: 31/12/2026 | D67: Fin du cycle triennal Art. 22 CD — Objectif 120h/collaborateur à atteindre
B68: Annuel | D68: Formation LCB-FT obligatoire (Art. L561-32 CMF) — Chaque collaborateur
B70: Recommandation : | D70: ="Exécuter le plan d'action dans l'ordre des priorités du TOP 5. Priorité n°1 : "&C47&" (score "&TEXT(D47,"0,0")&"). Réactualiser cette grille lors de chaque revue qualité annuelle (NPMQ §25)." -> Exécuter le plan d'action dans l'ordre des priorités du TOP 5. Priorité n°1 : Facture électronique (PA) (score 15,8). Réactualiser cette grille lors de chaque revue qualité annuelle (NPMQ §25).

Sheet PLAN D'ACTION
B2: PLAN D'ACTION & BUDGET FORMATION
B3: ⚠️ Cet onglet est 100% automatisé depuis l'onglet SAISIE — Ne rien modifier ici
B5: A. BUDGET FORMATIONS EXTERNES PLANIFIÉES
B6: Formation | C6: Collaborateur | D6: Durée (h) | E6: Coût HT € | F6: Organisme | G6: Domaine | H6: Type | I6: Comble déficit
B7: =IF(SAISIE!B77="","",SAISIE!B77) -> IA dans l'exercice professionnel | C7: =IF(SAISIE!B77="","",SAISIE!C77) -> Lambert | D7: =IF(SAISIE!B77="","",SAISIE!D77) -> 14 | E7: =IF(SAISIE!B77="","",SAISIE!E77) -> 890 | F7: =IF(SAISIE!B77="","",SAISIE!F77) -> CFPC (catalogue 2026) | G7: =IF(SAISIE!B77="","",SAISIE!G77) -> IA | H7: =IF(SAISIE!B77="","",SAISIE!H77) -> Productivité | I7: IA (Lambert -2.0)
B8: =IF(SAISIE!B78="","",SAISIE!B78) -> Cybersécurité des cabinets | C8: =IF(SAISIE!B78="","",SAISIE!C78) -> Lambert | D8: =IF(SAISIE!B78="","",SAISIE!D78) -> 7 | E8: =IF(SAISIE!B78="","",SAISIE!E78) -> 650 | F8: =IF(SAISIE!B78="","",SAISIE!F78) -> ANSSI / Cybermalveillance | G8: =IF(SAISIE!B78="","",SAISIE!G78) -> Cyber | H8: =IF(SAISIE!B78="","",SAISIE!H78) -> Prévention | I8: Cybersécurité (Lambert -1.75)
B9: =IF(SAISIE!B79="","",SAISIE!B79) -> RGPD — Conformité cabinet EC | C9: =IF(SAISIE!B79="","",SAISIE!C79) -> Renaud | D9: =IF(SAISIE!B79="","",SAISIE!D79) -> 7 | E9: =IF(SAISIE!B79="","",SAISIE!E79) -> 1200 | F9: =IF(SAISIE!B79="","",SAISIE!F79) -> Impact RGPD | G9: =IF(SAISIE!B79="","",SAISIE!G79) -> RGPD | H9: =IF(SAISIE!B79="","",SAISIE!H79) -> Conformité | I9: RGPD (Renaud -1.75)
B10: E-facture 2026 — Réforme PA | C10: =IF(SAISIE!B80="","",SAISIE!C80) -> Dupré | D10: =IF(SAISIE!B80="","",SAISIE!D80) -> 14 | E10: =IF(SAISIE!B80="","",SAISIE!E80) -> 890 | F10: =IF(SAISIE!B80="","",SAISIE!F80) -> CFPC (catalogue 2026) | G10: =IF(SAISIE!B80="","",SAISIE!G80) -> E-facture | H10: =IF(SAISIE!B80="","",SAISIE!H80) -> Productivité | I10: E-facture (Dupré -1.75)
B11: =IF(SAISIE!B81="","",SAISIE!B81) -> LCB-FT vigilance annuelle | C11: =IF(SAISIE!B81="","",SAISIE!C81) -> Équipe | D11: =IF(SAISIE!B81="","",SAISIE!D81) -> 3.5 | E11: =IF(SAISIE!B81="","",SAISIE!E81) -> 600 | F11: =IF(SAISIE!B81="","",SAISIE!F81) -> CFPC / CSOEC | G11: =IF(SAISIE!B81="","",SAISIE!G81) -> LCB-FT | H11: =IF(SAISIE!B81="","",SAISIE!H81) -> Conformité | I11: LCB-FT (Équipe -1.5)
B12: =IF(SAISIE!B82="","",SAISIE!B82) -> Déontologie & normes 2026 | C12: =IF(SAISIE!B82="","",SAISIE!C82) -> Dupré | D12: =IF(SAISIE!B82="","",SAISIE!D82) -> 7 | E12: =IF(SAISIE!B82="","",SAISIE!E82) -> 350 | F12: =IF(SAISIE!B82="","",SAISIE!F82) -> CROEC Île-de-France | G12: =IF(SAISIE!B82="","",SAISIE!G82) -> Déontologie | H12: =IF(SAISIE!B82="","",SAISIE!H82) -> Conformité | I12: Déontologie (Dupré -0.75)
B13: =IF(SAISIE!B83="","",SAISIE!B83) -> Signature électronique avancée | C13: =IF(SAISIE!B83="","",SAISIE!C83) -> Renaud | D13: =IF(SAISIE!B83="","",SAISIE!D83) -> 7 | E13: =IF(SAISIE!B83="","",SAISIE!E83) -> 450 | F13: =IF(SAISIE!B83="","",SAISIE!F83) -> Organisme Qualiopi | G13: =IF(SAISIE!B83="","",SAISIE!G83) -> Signature | H13: =IF(SAISIE!B83="","",SAISIE!H83) -> Compétence | I13: Signature élec. (Renaud -1.25)
B14: =IF(SAISIE!B84="","",SAISIE!B84) -> GED & archivage probant | C14: =IF(SAISIE!B84="","",SAISIE!C84) -> Renaud | D14: =IF(SAISIE!B84="","",SAISIE!D84) -> 7 | E14: =IF(SAISIE!B84="","",SAISIE!E84) -> 550 | F14: =IF(SAISIE!B84="","",SAISIE!F84) -> Organisme Qualiopi | G14: =IF(SAISIE!B84="","",SAISIE!G84) -> GED | H14: =IF(SAISIE!B84="","",SAISIE!H84) -> Compétence | I14: GED (Renaud -0.75)
B15: =IF(SAISIE!B85="","",SAISIE!B85) -> Comptabilité avancée — Arrêté et consolidation | C15: =IF(SAISIE!B85="","",SAISIE!C85) -> Renaud | D15: =IF(SAISIE!B85="","",SAISIE!D85) -> 14 | E15: =IF(SAISIE!B85="","",SAISIE!E85) -> 890 | F15: =IF(SAISIE!B85="","",SAISIE!F85) -> CFPC (catalogue 2026) | G15: =IF(SAISIE!B85="","",SAISIE!G85) -> Comptabilité | H15: =IF(SAISIE!B85="","",SAISIE!H85) -> Compétence | I15: Comptabilité (Renaud -1.25)
B16: =IF(SAISIE!B86="","",SAISIE!B86) -> Outils SaaS avancés — Automatisation flux | C16: =IF(SAISIE!B86="","",SAISIE!C86) -> Renaud | D16: =IF(SAISIE!B86="","",SAISIE!D86) -> 7 | E16: =IF(SAISIE!B86="","",SAISIE!E86) -> 0 | F16: =IF(SAISIE!B86="","",SAISIE!F86) -> campusAtlas (100% pris en charge) | G16: =IF(SAISIE!B86="","",SAISIE!G86) -> SaaS | H16: =IF(SAISIE!B86="","",SAISIE!H86) -> Productivité | I16: SaaS (Renaud -0.25)
B17: =IF(SAISIE!B87="","",SAISIE!B87) -> Communication digitale — Relation client | C17: =IF(SAISIE!B87="","",SAISIE!C87) -> Renaud | D17: =IF(SAISIE!B87="","",SAISIE!D87) -> 7 | E17: =IF(SAISIE!B87="","",SAISIE!E87) -> 0 | F17: =IF(SAISIE!B87="","",SAISIE!F87) -> microlearningAtlas | G17: =IF(SAISIE!B87="","",SAISIE!G87) -> Communication | H17: =IF(SAISIE!B87="","",SAISIE!H87) -> Compétence | I17: Communication (Renaud -0.75)
B18: =IF(SAISIE!B88="","",SAISIE!B88) -> Veille réglementaire IA — AI Act application | C18: =IF(SAISIE!B88="","",SAISIE!C88) -> Dupré | D18: =IF(SAISIE!B88="","",SAISIE!D88) -> 7 | E18: =IF(SAISIE!B88="","",SAISIE!E88) -> 0 | F18: =IF(SAISIE!B88="","",SAISIE!F88) -> Webinaire CNOEC (gratuit inscrit) | G18: =IF(SAISIE!B88="","",SAISIE!G88) -> IA | H18: =IF(SAISIE!B88="","",SAISIE!H88) -> Conformité | I18: IA / AI Act (Dupré -2.0)
B19: =IF(SAISIE!B89="","",SAISIE!B89) -> PIX I Atlas — Évaluation compétences numériques | C19: =IF(SAISIE!B89="","",SAISIE!C89) -> Renaud | D19: =IF(SAISIE!B89="","",SAISIE!D89) -> 3.5 | E19: =IF(SAISIE!B89="","",SAISIE!E89) -> 0 | F19: =IF(SAISIE!B89="","",SAISIE!F89) -> PIX I Atlas (100% gratuit, toutes tailles) | G19: =IF(SAISIE!B89="","",SAISIE!G89) -> SaaS | H19: =IF(SAISIE!B89="","",SAISIE!H89) -> Compétence | I19: SaaS / Numérique (Renaud -0.25)
B20: SOUS-TOTAL FORMATIONS EXTERNES | D20: =SUM(D7:D19) -> 105 | E20: =SUM(E7:E19) -> 6470
B22: B. FINANCEMENT OPCO ATLAS (CCN 3020 — Cabinets EC)
B23: Source : opco-atlas.fr/criteres-financement — Critères 2026
B24: Poste | C24: Montant € | E24: Note / Source
B25: Budget formations HT | C25: =E20 -> 6470 | E25: Somme coûts catalogue planifiés
B26: Plafond PDC Atlas (< 11 sal.) | C26: =SAISIE!C13 -> 2800 | E26: opco-atlas.fr — Critères 2026
B27: Plafond DEC/CAC supplémentaire | C27: =SAISIE!C14 -> 1000 | E27: 1 000€/sal/an — 1 salarié en stage DEC (L. Martin)
B28: TOTAL prise en charge OPCO | C28: =C26+C27 -> 3800
B29: Coût net cabinet (HT) | C29: =C25-C28 -> 2670 | E29: Budget – OPCO
B31: C. ÉCONOMIES FORMATIONS INTERNES (AFEST — 7 sessions rationalisées)
B32: AFEST finançable par Atlas : 20€ HT/h dans plafond PDC (Art. L6313-2 CT)
B33: Binôme | C33: Domaine | D33: Durée | E33: Heures compt. | F33: Éco. externe €
B34: =IF(SAISIE!B95="","",SAISIE!B95) -> Martin | C34: =IF(SAISIE!B95="","",SAISIE!C95) -> Lambert | D34: =IF(SAISIE!B95="","",SAISIE!D95) -> IA & Prompting SaaS — Mentorat inversé | E34: =IF(SAISIE!B95="","",SAISIE!E95) -> 14 | F34: =IF(SAISIE!B95="","",SAISIE!F95) -> 890
B35: =IF(SAISIE!B96="","",SAISIE!B96) -> Lambert | C35: =IF(SAISIE!B96="","",SAISIE!C96) -> Martin | D35: =IF(SAISIE!B96="","",SAISIE!D96) -> Révision comptable — Tutorat | E35: =IF(SAISIE!B96="","",SAISIE!E96) -> 14 | F35: =IF(SAISIE!B96="","",SAISIE!F96) -> 980
B36: =IF(SAISIE!B97="","",SAISIE!B97) -> Lambert | C36: =IF(SAISIE!B97="","",SAISIE!C97) -> Renaud | D36: =IF(SAISIE!B97="","",SAISIE!D97) -> Fiscalité appliquée — Cas pratiques | E36: =IF(SAISIE!B97="","",SAISIE!E97) -> 7 | F36: =IF(SAISIE!B97="","",SAISIE!F97) -> 450
B37: =IF(SAISIE!B98="","",SAISIE!B98) -> Lambert | C37: =IF(SAISIE!B98="","",SAISIE!C98) -> Renaud | D37: =IF(SAISIE!B98="","",SAISIE!D98) -> IA appliquée — Prompts comptabilité | E37: =IF(SAISIE!B98="","",SAISIE!E98) -> 7 | F37: =IF(SAISIE!B98="","",SAISIE!F98) -> 890
B38: =IF(SAISIE!B99="","",SAISIE!B99) -> Lambert | C38: =IF(SAISIE!B99="","",SAISIE!C99) -> Dupré | D38: =IF(SAISIE!B99="","",SAISIE!D99) -> Cybersécurité — Bonnes pratiques cabinet | E38: =IF(SAISIE!B99="","",SAISIE!E99) -> 3.5 | F38: =IF(SAISIE!B99="","",SAISIE!F99) -> 325
B39: =IF(SAISIE!B100="","",SAISIE!B100) -> Lambert | C39: =IF(SAISIE!B100="","",SAISIE!C100) -> Martin | D39: =IF(SAISIE!B100="","",SAISIE!D100) -> Cybersécurité — Bonnes pratiques cabinet | E39: =IF(SAISIE!B100="","",SAISIE!E100) -> 3.5 | F39: =IF(SAISIE!B100="","",SAISIE!F100) -> 0
B40: =IF(SAISIE!B101="","",SAISIE!B101) -> Lambert | C40: =IF(SAISIE!B101="","",SAISIE!C101) -> Renaud | D40: =IF(SAISIE!B101="","",SAISIE!D101) -> Cybersécurité — Bonnes pratiques cabinet | E40: =IF(SAISIE!B101="","",SAISIE!E101) -> 3.5 | F40: =IF(SAISIE!B101="","",SAISIE!F101) -> 0
B41: =IF(SAISIE!B102="","",SAISIE!B102) -> Dupré | C41: =IF(SAISIE!B102="","",SAISIE!C102) -> Martin | D41: =IF(SAISIE!B102="","",SAISIE!D102) -> E-facture PA — Cascade post-formation | E41: =IF(SAISIE!B102="","",SAISIE!E102) -> 3.5 | F41: =IF(SAISIE!B102="","",SAISIE!F102) -> 225
B42: =IF(SAISIE!B103="","",SAISIE!B103) -> Dupré | C42: =IF(SAISIE!B103="","",SAISIE!C103) -> Lambert | D42: =IF(SAISIE!B103="","",SAISIE!D103) -> E-facture PA — Cascade post-formation | E42: =IF(SAISIE!B103="","",SAISIE!E103) -> 3.5 | F42: =IF(SAISIE!B103="","",SAISIE!F103) -> 0
B43: =IF(SAISIE!B104="","",SAISIE!B104) -> Dupré | C43: =IF(SAISIE!B104="","",SAISIE!C104) -> Renaud | D43: =IF(SAISIE!B104="","",SAISIE!D104) -> E-facture PA — Cascade post-formation | E43: =IF(SAISIE!B104="","",SAISIE!E104) -> 3.5 | F43: =IF(SAISIE!B104="","",SAISIE!F104) -> 0
B44: =IF(SAISIE!B105="","",SAISIE!B105) -> Dupré | C44: =IF(SAISIE!B105="","",SAISIE!C105) -> Martin | D44: =IF(SAISIE!B105="","",SAISIE!D105) -> Déontologie — Actualités normes 2026 | E44: =IF(SAISIE!B105="","",SAISIE!E105) -> 3.5 | F44: =IF(SAISIE!B105="","",SAISIE!F105) -> 175
B45: =IF(SAISIE!B106="","",SAISIE!B106) -> Dupré | C45: =IF(SAISIE!B106="","",SAISIE!C106) -> Lambert | D45: =IF(SAISIE!B106="","",SAISIE!D105) -> Déontologie — Actualités normes 2026 | E45: =IF(SAISIE!B106="","",SAISIE!E106) -> 3.5 | F45: =IF(SAISIE!B106="","",SAISIE!F106) -> 0
B46: =IF(SAISIE!B107="","",SAISIE!B107) -> Dupré | C46: =IF(SAISIE!B107="","",SAISIE!C107) -> Renaud | D46: =IF(SAISIE!B107="","",SAISIE!D107) -> Déontologie — Actualités normes 2026 | E46: =IF(SAISIE!B107="","",SAISIE!E107) -> 3.5 | F46: =IF(SAISIE!B107="","",SAISIE!F107) -> 0
D47: =E20 -> 6470 | F47: =SUM(F34:F46) -> 3935
B48: Prise en charge OPCO Atlas | D48: =-C28 -> -3800 | F48: =SUM(F34:F47) -> 7870
B49: Coût net formations | D49: =D47+D48 -> 2670 | F49: Budget – OPCO
B50: Économies formations internes | D50: =-F47 -> -3935 | F50: Formations externes évitées
B51: INVESTISSEMENT NET | D51: =D49+D50 -> -1265 | F51: Résultat négatif = gain net : le financement OPCO Atlas + les économies AFEST couvrent plus que le coût catalogue. Ce gain finance le temps consacré par les formateurs internes.
B53: E. HYPOTHÈSES ET SOURCES
B54: Taux horaire complet | D54: ="≈ "&SAISIE!G16&" €/h" -> ≈ 52 €/h | F54: Masse sal. brute / (ETP×1607h) × 1.45 × 1.18 — voir onglet _REF
B55: Charges patronales × 1.45 | D55: ≈ 45% moyen | F55: URSSAF 2026 : cadres EC env. 43-45% — Hausse cotis. vieillesse déplaf. LFSS 2026 (2,02→2,11%)
B56: Frais de structure × 1.18 | D56: 18% coût direct | F56: OMECA Baromètre S2 2025 (janv. 2026) — Ratio frais structure / charges directes cabinets <10 sal.
B57: OPCO Atlas — PDC | D57: ="→ "&TEXT(SAISIE!C13,"# ##0")&" €/an" -> → 2 800 €/an | F57: opco-atlas.fr — Critères 2026 (MAJ 05/01/2026)
B58: OPCO Atlas — DEC/CAC | D58: ="→ "&TEXT(SAISIE!C14,"# ##0")&" €/sal/an" -> → 1 000 €/sal/an | F58: opco-atlas.fr — Supplément stage DEC/CAC 2026 (MAJ 05/01/2026)
B59: AFEST (formation interne) | D59: 20 €/h max 150h | F59: Atlas 2026 : dans plafond PDC. Art. L6313-2 CT. microlearningAtlas cyber : gratuit <50 sal.
B62: F. SUIVI COMBLEMENT DU DÉFICIT (heures sur 3 ans)
B63: Collaborateur | C63: Déficit actuel | D63: H. ext. planifiées | E63: H. int. (AFEST) | F63: Total planifié | G63: Solde résiduel | H63: Statut
B64: =DIAGNOSTIC!B13 -> M. Dupré | C64: =IF(DIAGNOSTIC!B13="","",DIAGNOSTIC!F13) -> -33.5 | D64: =IF(DIAGNOSTIC!B13="","",SUMIF(SAISIE!C77:C89,SAISIE!C20,SAISIE!D77:D89)+SUMPRODUCT((SAISIE!C77:C89="Équipe")*SAISIE!D77:D89)) -> 31.5 | E64: =IF(DIAGNOSTIC!B13="","",SUMIF(SAISIE!C95:C107,SAISIE!C20,SAISIE!E95:E107)) -> 3.5 | F64: =IF(DIAGNOSTIC!B13="","",D64+E64) -> 35 | G64: =IF(DIAGNOSTIC!B13="","",C64+F64) -> 1.5 | H64: =IF(DIAGNOSTIC!B13="","",IF(C64>=0,"✅ Déjà conforme",IF(G64>=0,"✅ Résolu","🟠 Partiel ("&TEXT(ABS(G64),"0.#")&"h restantes)"))) -> ✅ Résolu
B65: =DIAGNOSTIC!B14 -> L. Martin | C65: =IF(DIAGNOSTIC!B14="","",DIAGNOSTIC!F14) -> -22.5 | D65: =IF(DIAGNOSTIC!B14="","",SUMIF(SAISIE!C77:C89,SAISIE!C21,SAISIE!D77:D89)+SUMPRODUCT((SAISIE!C77:C89="Équipe")*SAISIE!D77:D89)) -> 3.5 | E65: =IF(DIAGNOSTIC!B14="","",SUMIF(SAISIE!C95:C107,SAISIE!C21,SAISIE!E95:E107)) -> 24.5 | F65: =IF(DIAGNOSTIC!B14="","",D65+E65) -> 28 | G65: =IF(DIAGNOSTIC!B14="","",C65+F65) -> 5.5 | H65: =IF(DIAGNOSTIC!B14="","",IF(C65>=0,"✅ Déjà conforme",IF(G65>=0,"✅ Résolu","🟠 Partiel ("&TEXT(ABS(G65),"0.#")&"h restantes)"))) -> ✅ Résolu
B66: =DIAGNOSTIC!B15 -> M. Lambert | C66: =IF(DIAGNOSTIC!B15="","",DIAGNOSTIC!F15) -> -43 | D66: =IF(DIAGNOSTIC!B15="","",SUMIF(SAISIE!C77:C89,SAISIE!C22,SAISIE!D77:D89)+SUMPRODUCT((SAISIE!C77:C89="Équipe")*SAISIE!D77:D89)) -> 24.5 | E66: =IF(DIAGNOSTIC!B15="","",SUMIF(SAISIE!C95:C107,SAISIE!C22,SAISIE!E95:E107)) -> 21 | F66: =IF(DIAGNOSTIC!B15="","",D66+E66) -> 45.5 | G66: =IF(DIAGNOSTIC!B15="","",C66+F66) -> 2.5 | H66: =IF(DIAGNOSTIC!B15="","",IF(C66>=0,"✅ Déjà conforme",IF(G66>=0,"✅ Résolu","🟠 Partiel ("&TEXT(ABS(G66),"0.#")&"h restantes)"))) -> ✅ Résolu
B67: =DIAGNOSTIC!B16 -> T. Renaud | C67: =IF(DIAGNOSTIC!B16="","",DIAGNOSTIC!F16) -> -71 | D67: =IF(DIAGNOSTIC!B16="","",SUMIF(SAISIE!C77:C89,SAISIE!C23,SAISIE!D77:D89)+SUMPRODUCT((SAISIE!C77:C89="Équipe")*SAISIE!D77:D89)) -> 56 | E67: =IF(DIAGNOSTIC!B16="","",SUMIF(SAISIE!C95:C107,SAISIE!C23,SAISIE!E95:E107)) -> 24.5 | F67: =IF(DIAGNOSTIC!B16="","",D67+E67) -> 80.5 | G67: =IF(DIAGNOSTIC!B16="","",C67+F67) -> 9.5 | H67: =IF(DIAGNOSTIC!B16="","",IF(C67>=0,"✅ Déjà conforme",IF(G67>=0,"✅ Résolu","🟠 Partiel ("&TEXT(ABS(G67),"0.#")&"h restantes)"))) -> ✅ Résolu
B68: =DIAGNOSTIC!B17 | C68: =IF(DIAGNOSTIC!B17="","",DIAGNOSTIC!F17) | D68: =IF(DIAGNOSTIC!B17="","",SUMIF(SAISIE!C77:C89,SAISIE!C24,SAISIE!D77:D89)+SUMPRODUCT((SAISIE!C77:C89="Équipe")*SAISIE!D77:D89)) | E68: =IF(DIAGNOSTIC!B17="","",SUMIF(SAISIE!C95:C107,SAISIE!C24,SAISIE!E95:E107)) | F68: =IF(DIAGNOSTIC!B17="","",D68+E68) | G68: =IF(DIAGNOSTIC!B17="","",C68+F68) | H68: =IF(DIAGNOSTIC!B17="","",IF(C68>=0,"✅ Déjà conforme",IF(G68>=0,"✅ Résolu","🟠 Partiel ("&TEXT(ABS(G68),"0.#")&"h restantes)")))
B69: =DIAGNOSTIC!B18 | C69: =IF(DIAGNOSTIC!B18="","",DIAGNOSTIC!F18) | D69: =IF(DIAGNOSTIC!B18="","",SUMIF(SAISIE!C77:C89,SAISIE!C25,SAISIE!D77:D89)+SUMPRODUCT((SAISIE!C77:C89="Équipe")*SAISIE!D77:D89)) | E69: =IF(DIAGNOSTIC!B18="","",SUMIF(SAISIE!C95:C107,SAISIE!C25,SAISIE!E95:E107)) | F69: =IF(DIAGNOSTIC!B18="","",D69+E69) | G69: =IF(DIAGNOSTIC!B18="","",C69+F69) | H69: =IF(DIAGNOSTIC!B18="","",IF(C69>=0,"✅ Déjà conforme",IF(G69>=0,"✅ Résolu","🟠 Partiel ("&TEXT(ABS(G69),"0.#")&"h restantes)")))
B70: =DIAGNOSTIC!B19 | C70: =IF(DIAGNOSTIC!B19="","",DIAGNOSTIC!F19) | D70: =IF(DIAGNOSTIC!B19="","",SUMIF(SAISIE!C77:C89,SAISIE!C26,SAISIE!D77:D89)+SUMPRODUCT((SAISIE!C77:C89="Équipe")*SAISIE!D77:D89)) | E70: =IF(DIAGNOSTIC!B19="","",SUMIF(SAISIE!C95:C107,SAISIE!C26,SAISIE!E95:E107)) | F70: =IF(DIAGNOSTIC!B19="","",D70+E70) | G70: =IF(DIAGNOSTIC!B19="","",C70+F70) | H70: =IF(DIAGNOSTIC!B19="","",IF(C70>=0,"✅ Déjà conforme",IF(G70>=0,"✅ Résolu","🟠 Partiel ("&TEXT(ABS(G70),"0.#")&"h restantes)")))
B71: =DIAGNOSTIC!B20 | C71: =IF(DIAGNOSTIC!B20="","",DIAGNOSTIC!F20) | D71: =IF(DIAGNOSTIC!B20="","",SUMIF(SAISIE!C77:C89,SAISIE!C27,SAISIE!D77:D89)+SUMPRODUCT((SAISIE!C77:C89="Équipe")*SAISIE!D77:D89)) | E71: =IF(DIAGNOSTIC!B20="","",SUMIF(SAISIE!C95:C107,SAISIE!C27,SAISIE!E95:E107)) | F71: =IF(DIAGNOSTIC!B20="","",D71+E71) | G71: =IF(DIAGNOSTIC!B20="","",C71+F71) | H71: =IF(DIAGNOSTIC!B20="","",IF(C71>=0,"✅ Déjà conforme",IF(G71>=0,"✅ Résolu","🟠 Partiel ("&TEXT(ABS(G71),"0.#")&"h restantes)")))
B72: =DIAGNOSTIC!B21 | C72: =IF(DIAGNOSTIC!B21="","",DIAGNOSTIC!F21) | D72: =IF(DIAGNOSTIC!B21="","",SUMIF(SAISIE!C77:C89,SAISIE!C28,SAISIE!D77:D89)+SUMPRODUCT((SAISIE!C77:C89="Équipe")*SAISIE!D77:D89)) | E72: =IF(DIAGNOSTIC!B21="","",SUMIF(SAISIE!C95:C107,SAISIE!C28,SAISIE!E95:E107)) | F72: =IF(DIAGNOSTIC!B21="","",D72+E72) | G72: =IF(DIAGNOSTIC!B21="","",C72+F72) | H72: =IF(DIAGNOSTIC!B21="","",IF(C72>=0,"✅ Déjà conforme",IF(G72>=0,"✅ Résolu","🟠 Partiel ("&TEXT(ABS(G72),"0.#")&"h restantes)")))
B73: =DIAGNOSTIC!B22 | C73: =IF(DIAGNOSTIC!B22="","",DIAGNOSTIC!F22) | D73: =IF(DIAGNOSTIC!B22="","",SUMIF(SAISIE!C77:C89,SAISIE!C29,SAISIE!D77:D89)+SUMPRODUCT((SAISIE!C77:C89="Équipe")*SAISIE!D77:D89)) | E73: =IF(DIAGNOSTIC!B22="","",SUMIF(SAISIE!C95:C107,SAISIE!C29,SAISIE!E95:E107)) | F73: =IF(DIAGNOSTIC!B22="","",D73+E73) | G73: =IF(DIAGNOSTIC!B22="","",C73+F73) | H73: =IF(DIAGNOSTIC!B22="","",IF(C73>=0,"✅ Déjà conforme",IF(G73>=0,"✅ Résolu","🟠 Partiel ("&TEXT(ABS(G73),"0.#")&"h restantes)")))
B74: ⚠️ Note : les formations affectées à « Équipe » (ex. LCB-FT) sont comptabilisées à 100 % pour chaque participant présent (attestation individuelle). Les AFEST (section F de SAISIE) complètent le plan externe et sont comptabilisées à 100 % pour l'apprenant (Art. L6313-2 CT).
B76: G. CALENDRIER DE MISE EN ŒUVRE (S2 2026)
B77: Formation | C77: Collab. | D77: Heures | E77: Juil. | F77: Août | G77: Sept. | H77: Oct. | I77: Nov. | J77: Déc.
B78: =IF(SAISIE!B77<>"",SAISIE!B77,"") -> IA dans l'exercice professionnel | C78: =IF(SAISIE!C77<>"",SAISIE!C77,"") -> Lambert | D78: =IF(SAISIE!D77<>"",SAISIE!D77,"") -> 14 | E78: =IF(SAISIE!$J$77="Juil.",SAISIE!$D$77,"") | F78: =IF(SAISIE!$J$77="Août",SAISIE!$D$77,"") | G78: =IF(SAISIE!$J$77="Sept.",SAISIE!$D$77,"") -> 14 | H78: =IF(SAISIE!$J$77="Oct.",SAISIE!$D$77,"") | I78: =IF(SAISIE!$J$77="Nov.",SAISIE!$D$77,"") | J78: =IF(SAISIE!$J$77="Déc.",SAISIE!$D$77,"")
B79: =IF(SAISIE!B78<>"",SAISIE!B78,"") -> Cybersécurité des cabinets | C79: =IF(SAISIE!C78<>"",SAISIE!C78,"") -> Lambert | D79: =IF(SAISIE!D78<>"",SAISIE!D78,"") -> 7 | E79: =IF(SAISIE!$J$78="Juil.",SAISIE!$D$78,"") | F79: =IF(SAISIE!$J$78="Août",SAISIE!$D$78,"") | G79: =IF(SAISIE!$J$78="Sept.",SAISIE!$D$78,"") | H79: =IF(SAISIE!$J$78="Oct.",SAISIE!$D$78,"") -> 7 | I79: =IF(SAISIE!$J$78="Nov.",SAISIE!$D$78,"") | J79: =IF(SAISIE!$J$78="Déc.",SAISIE!$D$78,"")
B80: =IF(SAISIE!B79<>"",SAISIE!B79,"") -> RGPD — Conformité cabinet EC | C80: =IF(SAISIE!C79<>"",SAISIE!C79,"") -> Renaud | D80: =IF(SAISIE!D79<>"",SAISIE!D79,"") -> 7 | E80: =IF(SAISIE!$J$79="Juil.",SAISIE!$D$79,"") | F80: =IF(SAISIE!$J$79="Août",SAISIE!$D$79,"") | G80: =IF(SAISIE!$J$79="Sept.",SAISIE!$D$79,"") | H80: =IF(SAISIE!$J$79="Oct.",SAISIE!$D$79,"") | I80: =IF(SAISIE!$J$79="Nov.",SAISIE!$D$79,"") -> 7 | J80: =IF(SAISIE!$J$79="Déc.",SAISIE!$D$79,"")
B81: =IF(SAISIE!B80<>"",SAISIE!B80,"") -> E-facture 2026 — Réforme PA | C81: =IF(SAISIE!C80<>"",SAISIE!C80,"") -> Dupré | D81: =IF(SAISIE!D80<>"",SAISIE!D80,"") -> 14 | E81: =IF(SAISIE!$J$80="Juil.",SAISIE!$D$80,"") | F81: =IF(SAISIE!$J$80="Août",SAISIE!$D$80,"") | G81: =IF(SAISIE!$J$80="Sept.",SAISIE!$D$80,"") | H81: =IF(SAISIE!$J$80="Oct.",SAISIE!$D$80,"") -> 14 | I81: =IF(SAISIE!$J$80="Nov.",SAISIE!$D$80,"") | J81: =IF(SAISIE!$J$80="Déc.",SAISIE!$D$80,"")
B82: =IF(SAISIE!B81<>"",SAISIE!B81,"") -> LCB-FT vigilance annuelle | C82: =IF(SAISIE!C81<>"",SAISIE!C81,"") -> Équipe | D82: =IF(SAISIE!D81<>"",SAISIE!D81,"") -> 3.5 | E82: =IF(SAISIE!$J$81="Juil.",SAISIE!$D$81,"") -> 3.5 | F82: =IF(SAISIE!$J$81="Août",SAISIE!$D$81,"") | G82: =IF(SAISIE!$J$81="Sept.",SAISIE!$D$81,"") | H82: =IF(SAISIE!$J$81="Oct.",SAISIE!$D$81,"") | I82: =IF(SAISIE!$J$81="Nov.",SAISIE!$D$81,"") | J82: =IF(SAISIE!$J$81="Déc.",SAISIE!$D$81,"")
B83: =IF(SAISIE!B82<>"",SAISIE!B82,"") -> Déontologie & normes 2026 | C83: =IF(SAISIE!C82<>"",SAISIE!C82,"") -> Dupré | D83: =IF(SAISIE!D82<>"",SAISIE!D82,"") -> 7 | E83: =IF(SAISIE!$J$82="Juil.",SAISIE!$D$82,"") | F83: =IF(SAISIE!$J$82="Août",SAISIE!$D$82,"") -> 7 | G83: =IF(SAISIE!$J$82="Sept.",SAISIE!$D$82,"") | H83: =IF(SAISIE!$J$82="Oct.",SAISIE!$D$82,"") | I83: =IF(SAISIE!$J$82="Nov.",SAISIE!$D$82,"") | J83: =IF(SAISIE!$J$82="Déc.",SAISIE!$D$82,"")
B84: =IF(SAISIE!B83<>"",SAISIE!B83,"") -> Signature électronique avancée | C84: =IF(SAISIE!C83<>"",SAISIE!C83,"") -> Renaud | D84: =IF(SAISIE!D83<>"",SAISIE!D83,"") -> 7 | E84: =IF(SAISIE!$J$83="Juil.",SAISIE!$D$83,"") | F84: =IF(SAISIE!$J$83="Août",SAISIE!$D$83,"") | G84: =IF(SAISIE!$J$83="Sept.",SAISIE!$D$83,"") | H84: =IF(SAISIE!$J$83="Oct.",SAISIE!$D$83,"") | I84: =IF(SAISIE!$J$83="Nov.",SAISIE!$D$83,"") -> 7 | J84: =IF(SAISIE!$J$83="Déc.",SAISIE!$D$83,"")
B85: =IF(SAISIE!B84<>"",SAISIE!B84,"") -> GED & archivage probant | C85: =IF(SAISIE!C84<>"",SAISIE!C84,"") -> Renaud | D85: =IF(SAISIE!D84<>"",SAISIE!D84,"") -> 7 | E85: =IF(SAISIE!$J$84="Juil.",SAISIE!$D$84,"") | F85: =IF(SAISIE!$J$84="Août",SAISIE!$D$84,"") | G85: =IF(SAISIE!$J$84="Sept.",SAISIE!$D$84,"") | H85: =IF(SAISIE!$J$84="Oct.",SAISIE!$D$84,"") | I85: =IF(SAISIE!$J$84="Nov.",SAISIE!$D$84,"") | J85: =IF(SAISIE!$J$84="Déc.",SAISIE!$D$84,"") -> 7
B86: =IF(SAISIE!B85<>"",SAISIE!B85,"") -> Comptabilité avancée — Arrêté et consolidation | C86: =IF(SAISIE!C85<>"",SAISIE!C85,"") -> Renaud | D86: =IF(SAISIE!D85<>"",SAISIE!D85,"") -> 14 | E86: =IF(SAISIE!$J$85="Juil.",SAISIE!$D$85,"") -> 14 | F86: =IF(SAISIE!$J$85="Août",SAISIE!$D$85,"") | G86: =IF(SAISIE!$J$85="Sept.",SAISIE!$D$85,"") | H86: =IF(SAISIE!$J$85="Oct.",SAISIE!$D$85,"") | I86: =IF(SAISIE!$J$85="Nov.",SAISIE!$D$85,"") | J86: =IF(SAISIE!$J$85="Déc.",SAISIE!$D$85,"")
B87: =IF(SAISIE!B86<>"",SAISIE!B86,"") -> Outils SaaS avancés — Automatisation flux | C87: =IF(SAISIE!C86<>"",SAISIE!C86,"") -> Renaud | D87: =IF(SAISIE!D86<>"",SAISIE!D86,"") -> 7 | E87: =IF(SAISIE!$J$86="Juil.",SAISIE!$D$86,"") | F87: =IF(SAISIE!$J$86="Août",SAISIE!$D$86,"") | G87: =IF(SAISIE!$J$86="Sept.",SAISIE!$D$86,"") | H87: =IF(SAISIE!$J$86="Oct.",SAISIE!$D$86,"") -> 7 | I87: =IF(SAISIE!$J$86="Nov.",SAISIE!$D$86,"") | J87: =IF(SAISIE!$J$86="Déc.",SAISIE!$D$86,"")
B88: =IF(SAISIE!B87<>"",SAISIE!B87,"") -> Communication digitale — Relation client | C88: =IF(SAISIE!C87<>"",SAISIE!C87,"") -> Renaud | D88: =IF(SAISIE!D87<>"",SAISIE!D87,"") -> 7 | E88: =IF(SAISIE!$J$87="Juil.",SAISIE!$D$87,"") | F88: =IF(SAISIE!$J$87="Août",SAISIE!$D$87,"") | G88: =IF(SAISIE!$J$87="Sept.",SAISIE!$D$87,"") -> 7 | H88: =IF(SAISIE!$J$87="Oct.",SAISIE!$D$87,"") | I88: =IF(SAISIE!$J$87="Nov.",SAISIE!$D$87,"") | J88: =IF(SAISIE!$J$87="Déc.",SAISIE!$D$87,"")
B89: =IF(SAISIE!B88<>"",SAISIE!B88,"") -> Veille réglementaire IA — AI Act application | C89: =IF(SAISIE!C88<>"",SAISIE!C88,"") -> Dupré | D89: =IF(SAISIE!D88<>"",SAISIE!D88,"") -> 7 | E89: =IF(SAISIE!$J$88="Juil.",SAISIE!$D$88,"") | F89: =IF(SAISIE!$J$88="Août",SAISIE!$D$88,"") | G89: =IF(SAISIE!$J$88="Sept.",SAISIE!$D$88,"") -> 7 | H89: =IF(SAISIE!$J$88="Oct.",SAISIE!$D$88,"") | I89: =IF(SAISIE!$J$88="Nov.",SAISIE!$D$88,"") | J89: =IF(SAISIE!$J$88="Déc.",SAISIE!$D$88,"")
B90: =IF(SAISIE!B89<>"",SAISIE!B89,"") -> PIX I Atlas — Évaluation compétences numériques | C90: =IF(SAISIE!C89<>"",SAISIE!C89,"") -> Renaud | D90: =IF(SAISIE!D89<>"",SAISIE!D89,"") -> 3.5 | E90: =IF(SAISIE!$J$89="Juil.",SAISIE!$D$89,"") -> 3.5 | F90: =IF(SAISIE!$J$89="Août",SAISIE!$D$89,"") | G90: =IF(SAISIE!$J$89="Sept.",SAISIE!$D$89,"") | H90: =IF(SAISIE!$J$89="Oct.",SAISIE!$D$89,"") | I90: =IF(SAISIE!$J$89="Nov.",SAISIE!$D$89,"") | J90: =IF(SAISIE!$J$89="Déc.",SAISIE!$D$89,"")
B91: Charge mensuelle (h) | D91: =SUM(D78:D90) -> 105 | E91: =SUM(E78:E90) -> 21 | F91: =SUM(F78:F90) -> 7 | G91: =SUM(G78:G90) -> 28 | H91: =SUM(H78:H90) -> 28 | I91: =SUM(I78:I90) -> 14 | J91: =SUM(J78:J90) -> 7
B92: ⚠️ Ce calendrier est 100% automatisé. Pour modifier le planning, changer le mois dans la colonne J de l'onglet SAISIE (section E). Les heures se repositionnent automatiquement.

Sheet FICHE QUALITÉ
B2: FICHE QUALITÉ — FORMATION CONTINUE
B3: Art. 22 Code de déontologie • NPMQ 2025 §21-25 & §44 • À imprimer pour le dossier qualité annuel
B4: ⚠️ 100% automatisé — Ne rien modifier
B6: IDENTIFICATION DU CABINET
B7: Raison sociale | D7: =SAISIE!C8 -> Cabinet X
B8: N° OEC | D8: =SAISIE!C9 -> IDF-XXXXX
B9: Expert-comptable titulaire | D9: =SAISIE!C10 -> M. Dupré
B10: Effectif ETP | D10: =SAISIE!E16 -> 3.8
B11: OPCO de branche | D11: =SAISIE!C12&" (CCN 3020)" -> OPCO Atlas (CCN 3020)
B12: Date de synthèse | D12: =TODAY() -> 46077
B14: CONFORMITÉ FORMATION CONTINUE
B15: Collaborateur | D15: Heures 3 ans | E15: Objectif | F15: Écart | G15: Statut
B16: =DIAGNOSTIC!B13 -> M. Dupré | D16: =IF(DIAGNOSTIC!B13="","",DIAGNOSTIC!D13) -> 86.5 | E16: =IF(DIAGNOSTIC!B13="","",DIAGNOSTIC!E13) -> 120 | F16: =IF(DIAGNOSTIC!B13="","",DIAGNOSTIC!F13) -> -33.5 | G16: =IF(DIAGNOSTIC!B13="","",DIAGNOSTIC!G13) -> 🔴 Non conforme
B17: =DIAGNOSTIC!B14 -> L. Martin | D17: =IF(DIAGNOSTIC!B14="","",DIAGNOSTIC!D14) -> 17.5 | E17: =IF(DIAGNOSTIC!B14="","",DIAGNOSTIC!E14) -> 40 | F17: =IF(DIAGNOSTIC!B14="","",DIAGNOSTIC!F14) -> -22.5 | G17: =IF(DIAGNOSTIC!B14="","",DIAGNOSTIC!G14) -> 🔴 Non conforme
B18: =DIAGNOSTIC!B15 -> M. Lambert | D18: =IF(DIAGNOSTIC!B15="","",DIAGNOSTIC!D15) -> 77 | E18: =IF(DIAGNOSTIC!B15="","",DIAGNOSTIC!E15) -> 120 | F18: =IF(DIAGNOSTIC!B15="","",DIAGNOSTIC!F15) -> -43 | G18: =IF(DIAGNOSTIC!B15="","",DIAGNOSTIC!G15) -> 🔴 Non conforme
B19: =DIAGNOSTIC!B16 -> T. Renaud | D19: =IF(DIAGNOSTIC!B16="","",DIAGNOSTIC!D16) -> 49 | E19: =IF(DIAGNOSTIC!B16="","",DIAGNOSTIC!E16) -> 120 | F19: =IF(DIAGNOSTIC!B16="","",DIAGNOSTIC!F16) -> -71 | G19: =IF(DIAGNOSTIC!B16="","",DIAGNOSTIC!G16) -> 🔴 Non conforme
B20: =DIAGNOSTIC!B17 | D20: =IF(DIAGNOSTIC!B17="","",DIAGNOSTIC!D17) | E20: =IF(DIAGNOSTIC!B17="","",DIAGNOSTIC!E17) | F20: =IF(DIAGNOSTIC!B17="","",DIAGNOSTIC!F17) | G20: =IF(DIAGNOSTIC!B17="","",DIAGNOSTIC!G17)
B21: =DIAGNOSTIC!B18 | D21: =IF(DIAGNOSTIC!B18="","",DIAGNOSTIC!D18) | E21: =IF(DIAGNOSTIC!B18="","",DIAGNOSTIC!E18) | F21: =IF(DIAGNOSTIC!B18="","",DIAGNOSTIC!F18) | G21: =IF(DIAGNOSTIC!B18="","",DIAGNOSTIC!G18)
B22: =DIAGNOSTIC!B19 | D22: =IF(DIAGNOSTIC!B19="","",DIAGNOSTIC!D19) | E22: =IF(DIAGNOSTIC!B19="","",DIAGNOSTIC!E19) | F22: =IF(DIAGNOSTIC!B19="","",DIAGNOSTIC!F19) | G22: =IF(DIAGNOSTIC!B19="","",DIAGNOSTIC!G19)
B23: =DIAGNOSTIC!B20 | D23: =IF(DIAGNOSTIC!B20="","",DIAGNOSTIC!D20) | E23: =IF(DIAGNOSTIC!B20="","",DIAGNOSTIC!E20) | F23: =IF(DIAGNOSTIC!B20="","",DIAGNOSTIC!F20) | G23: =IF(DIAGNOSTIC!B20="","",DIAGNOSTIC!G20)
B24: =DIAGNOSTIC!B21 | D24: =IF(DIAGNOSTIC!B21="","",DIAGNOSTIC!D21) | E24: =IF(DIAGNOSTIC!B21="","",DIAGNOSTIC!E21) | F24: =IF(DIAGNOSTIC!B21="","",DIAGNOSTIC!F21) | G24: =IF(DIAGNOSTIC!B21="","",DIAGNOSTIC!G21)
B25: =DIAGNOSTIC!B22 | D25: =IF(DIAGNOSTIC!B22="","",DIAGNOSTIC!D22) | E25: =IF(DIAGNOSTIC!B22="","",DIAGNOSTIC!E22) | F25: =IF(DIAGNOSTIC!B22="","",DIAGNOSTIC!F22) | G25: =IF(DIAGNOSTIC!B22="","",DIAGNOSTIC!G22)
B27: Taux conformité actuel | D27: =COUNTIF(DIAGNOSTIC!G13:G22,"✅*")&" / "&COUNTIF(DIAGNOSTIC!B13:B22,"?*") -> 0 / 4
B28: Taux conformité après plan d'action | D28: =COUNTIF('PLAN D''ACTION'!H64:H73,"✅*")&" / "&COUNTIF('PLAN D''ACTION'!B64:B73,"?*") -> 4 / 4
B30: BUDGET FORMATION
B31: Budget formations externes HT | D31: ='PLAN D''ACTION'!D47 -> 6470
B32: Prise en charge OPCO Atlas | D32: ='PLAN D''ACTION'!D48 -> -3800
B33: Coût net formations | D33: ='PLAN D''ACTION'!D49 -> 2670
B34: Économies formations internes (AFEST) | D34: ='PLAN D''ACTION'!D50 -> -3935
B35: INVESTISSEMENT NET | D35: ='PLAN D''ACTION'!D51 -> -1265
B38: PIÈCES JUSTIFICATIVES (Checklist contrôle qualité)
B39: ☐ | C39: Attestations de formation (GED cabinet) | F39: Obligatoire — NPMQ §23
B40: ☐ | C40: Émargements formations internes (AFEST) | F40: Obligatoire — Art. L6313-2 CT
B41: ☐ | C41: Justificatifs OPCO Atlas (accords PDC) | F41: Recommandé
B42: ☐ | C42: Planning formations N+1 | F42: Obligatoire — NPMQ §24
B43: ☐ | C43: Attestation LCB-FT annuelle | F43: Obligatoire — Art. L561-32 CMF
B44: ☐ | C44: Procédure formation continue | F44: NPMQ 2025 §21-25
B45: ☐ | C45: Grilles évaluation compétences | F45: Art. 148 Code de déontologie
B46: ☐ | C46: Entretiens professionnels biennaux | F46: Art. L6315-1 Code du travail
B47: ☐ | C47: Sensibilisation AI literacy (art. 4 Règl. UE 2024/1689) | F47: Obligatoire depuis fév. 2025 — Règl. (UE) 2024/1689
B48: ☐ | C48: Registre des formations (cette annexe) | F48: Document de synthèse
B51: Prochaine revue prévue le : _________________ | E51: Fréquence recommandée : annuelle (NPMQ §25)
B53: Date : _________________ | E53: Signature EC : _________________
B55: RÉFÉRENCES NORMATIVES ET LÉGALES
B56: • Art. 22 Code de déontologie (Décret n°2012-432 mod. Décret n°2023-388 — éd. janv. 2026)
B57: • NPMQ 2025 §21-25 — Compétence des collaborateurs et formation continue
B58: • Art. 148 Code de déontologie — Responsabilité de l'expert-comptable
B59: • Art. L561-32 Code monétaire et financier — Formation LCB-FT annuelle
B60: • Art. L6313-2 Code du travail — AFEST (Loi n°2018-771 du 5 sept. 2018)
B61: • Art. L6315-1 Code du travail — Entretien professionnel biennal
B62: • Règlement (UE) 2024/1689 art. 4 — AI literacy (obligation fév. 2025)
B63: • OPCO Atlas — Critères financement 2026 (opco-atlas.fr — MAJ 05/01/2026)
B64: • CCN n°3020 (IDCC 0787) — Accord n°48 du 05/12/2025 (minima +2,9% 2026)
B65: • OMECA — Baromètre S2 2025 (publié 19/01/2026) et S2 2024 (publié 15/07/2025)
B66: • LFSS 2026 — Hausse cotisation patronale vieillesse déplafonnée (2,02 → 2,11%)
... B70: CONCLUSION
B71: Situation actuelle : | D71: =D27&" collaborateurs conformes au cycle triennal Art. 22 CD au point d'arrêté." -> 0 / 4 collaborateurs conformes au cycle triennal Art. 22 CD au point d'arrêté.
B72: Plan d'action : | D72: =TEXT(SUM(SAISIE!D77:D89),"0")&"h de formations externes + "&TEXT(SAISIE!E109,"0,0")&"h d'AFEST internes planifiées sur S2 2026." -> 105h de formations externes + 73,5h d'AFEST internes planifiées sur S2 2026.
B73: Projection : | D73: =D28&" collaborateurs conformes d'ici le 31/12/2026." -> 4 / 4 collaborateurs conformes d'ici le 31/12/2026.
B74: Investissement net : | D74: =TEXT(D35,"# ##0")&"€ (gain net : financement OPCO Atlas + économies AFEST > coûts catalogue)." -> -1 265€ (gain net : financement OPCO Atlas + économies AFEST > coûts catalogue).
B75: Priorité immédiate : | D75: =DIAGNOSTIC!C47&" (score "&TEXT(DIAGNOSTIC!D47,"0,0")&") — Priorité immédiate du plan d'action." -> Facture électronique (PA) (score 15,8) — Priorité immédiate du plan d'action.
B76: Prochaine revue : | D76: Revue qualité annuelle NPMQ §25 — Réactualiser cette grille avec le catalogue CFPC et les critères Atlas en vigueur.

Sheet _REF
A1: MÉTHODOLOGIE — Documentation technique Annexe 22 (Février 2026)
A3: 1. FONDEMENT RÉGLEMENTAIRE
A4: Art. 22 Code de déontologie (Décret 2012-432 modifié par Décret 2023-388)
A5: Édition janvier 2026 du Code de déontologie (CNOEC)
A6: Obligation : formation continue ≈ 120h/3 ans glissants (≈ 40h/an)
A7: dont ≥ 60h structurées homologuées par les CROEC
A8: NPMQ 2025 §21-25 : compétences collaborateurs, plan de formation, évaluation
A9: Art. 148 Code de déontologie : responsabilité de l'EC sur la compétence de l'équipe
A10: Art. L561-32 CMF : formation LCB-FT annuelle obligatoire
A11: Règl. (UE) 2024/1689 art. 4 : AI literacy — obligation applicable depuis fév. 2025
A13: Prorata pour les collaborateurs en cours de cycle :
A14: Pour un collaborateur entré en cours de période triennale, l'objectif est proratisé.
... A243: ⚠️ Après test, rétablir les valeurs d'origine du Cabinet X (données fictives).
